Workbook

Sheet Raw_Inflation
A1: Data Source | B1: World Development Indicators
A3: Last Updated Date | B3: 2026-10-08
A5: Country Name | B5: Country Code | C5: Indicator Name | D5: Indicator Code | E5: 1960 | F5: 1961 | G5: 1962 | H5: 1963 | I5: 1964 | J5: 1965 | K5: 1966 | L5: 1967 | M5: 1968 | N5: 1969 | O5: 1970 | P5: 1971 | Q5: 1972 | R5: 1973 | S5: 1974 | T5: 1975 | U5: 1976 | V5: 1977 | W5: 1978 | X5: 1979 | Y5: 1980 | Z5: 1981 | AA5: 1982 | AB5: 1983 | AC5: 1984 | AD5: 1985 | AE5: 1986 | AF5: 1987 | AG5: 1988 | AH5: 1989 | AI5: 1990 | AJ5: 1991 | AK5: 1992 | AL5: 1993 | AM5: 1994 | AN5: 1995 | AO5: 1996 | AP5: 1997 | AQ5: 1998 | AR5: 1999 | AS5: 2000 | AT5: 2001 | AU5: 2002 | AV5: 2003 | AW5: 2004 | AX5: 2005 | AY5: 2006 | AZ5: 2007 | BA5: 2008 | BB5: 2009 | BC5: 2010 | BD5: 2011 | BE5: 2012 | BF5: 2013 | BG5: 2014 | BH5: 2015 | BI5: 2016 | BJ5: 2017 | BK5: 2018 | BL5: 2019 | BM5: 2020 | BN5: 2021 | BO5: 2022 | BP5: 2023 | BQ5: 2024 | BR5: 2025
A6: Aruba | B6: ABW | C6: Inflation, consumer prices (annual %) | D6: FP.CPI.TOTL.ZG | AD6: 4.0322581 | AE6: 1.0739664 | AF6: 3.6430455 | AG6: 3.1218685 | AH6: 3.991628 | AI6: 5.8366878 | AJ6: 5.5555556 | AK6: 3.8733754 | AL6: 5.21556 | AM6: 6.3110797 | AN6: 3.3613911 | AO6: 3.225288 | AP6: 2.9999481 | AQ6: 1.8694885 | AR6: 2.280372 | AS6: 4.0440213 | AT6: 2.8836043 | AU6: 3.3152468 | AV6: 3.6563651 | AW6: 2.5291295 | AX6: 3.3977868 | AY6: 3.6080244 | AZ6: 5.3925678 | BA6: 8.9559871 | BB6: -2.1354287 | BC6: 2.0781407 | BD6: 4.3162974 | BE6: 0.62747199 | BF6: -2.3720652 | BG6: 0.42144092 | BH6: 0.4747636 | BI6: -0.93119599 | BJ6: -1.0282818 | BK6: 3.6260414 | BL6: 4.257462
A7: Africa Eastern and Southern | B7: AFE | C7: Inflation, consumer prices (annual %) | D7: FP.CPI.TOTL.ZG | S7: 19.598394 | T7: 15.224099 | U7: 11.216481 | V7: 14.238055 | W7: 12.526893 | X7: 15.06985 | Y7: 15.066512 | Z7: 14.461591 | AA7: 12.139918 | AB7: 11.567524 | AC7: 10.983863 | AD7: 13.006566 | AE7: 13.891972 | AF7: 12.563443 | AG7: 12.522258 | AH7: 12.558202 | AI7: 12.457914 | AJ7: 17.6781 | AK7: 16.167612 | AL7: 13.135661 | AM7: 14.852815 | AN7: 12.288591 | AO7: 9.7065863 | AP7: 10.249599 | AQ7: 7.4952554 | AR7: 7.8198648 | AS7: 8.6014851 | AT7: 5.840354 | AU7: 8.7637552 | AV7: 7.4497001 | AW7: 5.0234207 | AX7: 8.558038 | AY7: 8.8981638 | AZ7: 8.4507748 | BA7: 12.566645 | BB7: 8.954218 | BC7: 5.5375379 | BD7: 8.9712064 | BE7: 9.1587084 | BF7: 5.7488313 | BG7: 5.5258192 | BH7: 5.0985616 | BI7: 6.4468772 | BJ7: 6.2213753 | BK7: 4.6898065 | BL7: 4.1028508 | BM7: 5.1916294 | BN7: 6.8247271 | BO7: 10.883478 | BP7: 7.3991856 | BQ7: 4.7708573 | BR7: 4.2701114
A8: Afghanistan | B8: AFG | C8: Inflation, consumer prices (annual %) | D8: FP.CPI.TOTL.ZG | AX8: 12.686269 | AY8: 6.7845966 | AZ8: 8.6805708 | BA8: 26.418664 | BB8: -6.8111611 | BC8: 2.1785375 | BD8: 11.804186 | BE8: 6.4412128 | BF8: 7.3857718 | BG8: 4.673996 | BH8: -0.66170916 | BI8: 4.383892 | BJ8: 4.9759515 | BK8: 0.62614915 | BL8: 2.3023725 | BM8: 5.6018879 | BN8: 5.1332034 | BO8: 13.712102 | BP8: -4.6447087 | BQ8: -6.6011856
A9: Africa Western and Central | B9: AFW | C9: Inflation, consumer prices (annual %) | D9: FP.CPI.TOTL.ZG | Z9: 8.7992108 | AA9: 12.059765 | AB9: 10.671937 | AC9: 11.25 | AD9: 7.3549258 | AE9: 5.950965 | AF9: 0.24878856 | AG9: 2.5236593 | AH9: 0.86928702 | AI9: 1.0573614 | AJ9: 1.7418879 | AK9: -0.062999006 | AL9: 0.55345572 | AM9: 31.841017 | AN9: 10.563289 | AO9: 4.9142397 | AP9: 3.9971417 | AQ9: 4.4711254 | AR9: 0.37226617 | AS9: 2.5307752 | AT9: 4.3615291 | AU9: 3.1886933 | AV9: 1.7609041 | AW9: 0.69433631 | AX9: 5.6316335 | AY9: 4.4158998 | AZ9: 3.6073677 | BA9: 8.4529762 | BB9: 3.2824404 | BC9: 1.7848442 | BD9: 4.0186991 | BE9: 4.5783746 | BF9: 2.4392008 | BG9: 1.7684358 | BH9: 2.1308174 | BI9: 1.4874155 | BJ9: 1.725486 | BK9: 1.7840499 | BL9: 1.9830923 | BM9: 2.4903778 | BN9: 3.7455678 | BO9: 7.9492514 | BP9: 5.221168 | BQ9: 3.6080443 | BR9: 1.6578177
A10: Angola | B10: AGO | C10: Inflation, consumer prices (annual %) | D10: FP.CPI.TOTL.ZG | AJ10: 83.783784 | AK10: 299.5098 | AL10: 1378.5276 | AM10: 949.79253 | AN10: 2666.4506 | AO10: 4145.106 | AP10: 219.17672 | AQ10: 107.28482 | AR10: 248.1959 | AS10: 324.99687 | AT10: 152.56102 | AU10: 108.89744 | AV10: 98.224144 | AW10: 43.542107 | AX10: 22.953514 | AY10: 13.30521 | AZ10: 12.251497 | BA10: 12.475829 | BB10: 13.730284 | BC10: 14.469656 | BD10: 13.482468 | BE10: 10.277905 | BF10: 8.7778143 | BG10: 7.2803873 | BH10: 9.3559722 | BI10: 30.694415 | BJ10: 29.84448 | BK10: 19.628938 | BL10: 17.080954 | BM10: 22.271539 | BN10: 25.754295 | BO10: 21.35529 | BP10: 13.644102 | BQ10: 28.240495 | BR10: 20.16202
A11: Albania | B11: ALB | C11: Inflation, consumer prices (annual %) | D11: FP.CPI.TOTL.ZG | AK11: 226.00542 | AL11: 85.004751 | AM11: 22.565053 | AN11: 7.7932185 | AO11: 12.725478 | AP11: 33.180274 | AQ11: 20.642859 | AR11: 0.38943765 | AS11: 0.050018136 | AT11: 3.1075883 | AU11: 7.7705258 | AV11: 0.48400261 | AW11: 2.2800192 | AX11: 2.366582 | AY11: 2.3707283 | AZ11: 2.9326825 | BA11: 3.3208709 | BB11: 2.2669221 | BC11: 3.6271009 | BD11: 3.4280713 | BE11: 2.0315927 | BF11: 1.9376208 | BG11: 1.625865 | BH11: 1.896174 | BI11: 1.2754317 | BJ11: 1.9866613 | BK11: 2.0280596 | BL11: 1.4110908 | BM11: 1.6208866 | BN11: 2.0414716 | BO11: 6.7252027 | BP11: 4.7583456 | BQ11: 2.2158738 | BR11: 2.1461855
A12: Andorra | B12: AND | C12: Inflation, consumer prices (annual %) | D12: FP.CPI.TOTL.ZG
A13: Arab World | B13: ARB | C13: Inflation, consumer prices (annual %) | D13: FP.CPI.TOTL.ZG | R13: 8.2666667 | S13: 15.528282 | T13: 9.6696955 | U13: 10.317416 | V13: 11.989283 | W13: 9.7160327 | Y13: 9.6260566 | Z13: 10.758503 | AA13: 8.3312558 | AB13: 5.4936655 | AC13: 8.116398 | AD13: 7.2543618 | AE13: 6.7988584 | AF13: 4.2224167 | AG13: 5.911545 | AH13: 7.740886 | AI13: 8.4514624 | AJ13: 9 | AK13: 9.3597516 | AL13: 9.3703442 | AM13: 5.1125989 | AN13: 6.5437907 | AO13: 4.6813062 | AP13: 3.601161 | AQ13: 3.4173195 | AR13: 2.6693737 | AS13: 1.8537904 | AT13: 1.7722044 | AU13: 1.8329939 | AV13: 2.7125925 | AW13: 3.63228 | AX13: 3.4936853 | AY13: 3.5449859 | AZ13: 4.7439064 | BA13: 11.270665 | BB13: 2.9208971 | BC13: 3.911062 | BD13: 4.7531639 | BE13: 4.6118443 | BF13: 3.2219776 | BG13: 2.8994791 | BH13: 1.8313523 | BI13: 2.5395604 | BJ13: 2.0693293 | BK13: 2.3124301 | BL13: 1.3360157 | BM13: 1.4470366 | BN13: 2.8683303 | BO13: 5.1722209 | BP13: 4.0002588 | BQ13: 2.3089006 | BR13: 1.7664649
A14: United Arab Emirates | B14: ARE | C14: Inflation, consumer prices (annual %) | D14: FP.CPI.TOTL.ZG | BA14: 12.25042 | BB14: 1.5618132 | BC14: 0.87798329 | BD14: 0.8773466 | BE14: 0.6622689 | BF14: 1.1011184 | BG14: 2.3462687 | BH14: 4.0699661 | BI14: 1.6174881 | BJ14: 1.9668256 | BK14: 3.0686338 | BL14: -1.9310811 | BM14: -2.0794032 | BN14: 0.17993534 | BO14: 5.291226 | BP14: 1.6267084 | BQ14: 1.6633651 | BR14: 1.2508652
A15: Argentina | B15: ARG | C15: Inflation, consumer prices (annual %) | D15: FP.CPI.TOTL.ZG | BK15: 34.277224 | BL15: 53.548304 | BM15: 42.015095 | BN15: 48.409379 | BO15: 72.430758 | BP15: 133.48894 | BQ15: 219.88393
A16: Armenia | B16: ARM | C16: Inflation, consumer prices (annual %) | D16: FP.CPI.TOTL.ZG | AM16: 3373.7594 | AN16: 175.95133 | AO16: 18.681186 | AP16: 13.960764 | AQ16: 8.6724863 | AR16: 0.64824576 | AS16: -0.79088377 | AT16: 3.1459046 | AU16: 1.0600493 | AV16: 4.7215534 | AW16: 6.9612614 | AX16: 0.638928 | AY16: 2.8923566 | AZ16: 4.4073609 | BA16: 8.9499534 | BB16: 3.4067668 | BC16: 8.1763614 | BD16: 7.6500081 | BE16: 2.5580201 | BF16: 5.7896678 | BG16: 2.9813087 | BH16: 3.7316912 | BI16: -1.4036076 | BJ16: 0.96955327 | BK16: 2.5202338 | BL16: 1.4434466 | BM16: 1.2114358 | BN16: 7.1848363 | BO16: 8.6409111 | BP16: 1.9804188 | BQ16: 0.26951198 | BR16: 3.3069334
A17: American Samoa | B17: ASM | C17: Inflation, consumer prices (annual %) | D17: FP.CPI.TOTL.ZG
A18: Antigua and Barbuda | B18: ATG | C18: Inflation, consumer prices (annual %) | D18: FP.CPI.TOTL.ZG | AR18: 1.1212879 | AS18: 0.7717798 | AT18: 1.4027966 | AU18: 2.407658 | AV18: 1.9935306 | AW18: 2.0300776 | AX18: 2.098752 | AY18: 1.7877854 | AZ18: 1.4160526 | BA18: 5.3338064 | BB18: -0.55016 | BC18: 3.3700254 | BD18: 3.4567497 | BE18: 3.3768804 | BF18: 1.0594978 | BG18: 1.0894416 | BH18: 0.96899346 | BI18: -0.4894378 | BJ18: 2.4324879 | BK18: 1.2071579 | BL18: 1.431356 | BM18: 0.62598971 | BN18: 2.0629964 | BO18: 7.5310783 | BP18: 5.0671387 | BQ18: 6.198867 | BR18: 1.3687353
A19: Australia | B19: AUS | C19: Inflation, consumer prices (annual %) | D19: FP.CPI.TOTL.ZG | E19: 3.7288215 | F19: 2.2875804 | G19: -0.31948864 | H19: 0.64102529 | I19: 2.8662267 | J19: 3.4055848 | K19: 3.2934115 | L19: 3.4782591 | M19: 2.5210072 | N19: 3.278687 | O19: 3.4391519 | P19: 6.1381084 | Q19: 6.0241041 | R19: 9.0909043 | S19: 15.416677 | T19: 15.16242 | U19: 13.322903 | V19: 12.309827 | W19: 8.0049044 | X19: 9.1220206 | Y19: 10.135849 | Z19: 9.4876614 | AA19: 11.351832 | AB19: 10.0389 | AC19: 3.9604084 | AD19: 6.734686 | AE19: 9.0503532 | AF19: 8.5330036 | AG19: 7.2159572 | AH19: 7.5338985 | AI19: 7.3330237 | AJ19: 3.1766687 | AK19: 1.0122282 | AL19: 1.7536575 | AM19: 1.9696351 | AN19: 4.6277645 | AO19: 2.615379 | AP19: 0.22489503 | AQ19: 0.86012992 | AR19: 1.4831395 | AS19: 4.4574371 | AT19: 4.40713 | AU19: 2.9815712 | AV19: 2.7325975 | AW19: 2.3432569 | AX19: 2.6918295 | AY19: 3.555287 | AZ19: 2.3276144 | BA19: 4.3502973 | BB19: 1.7711203 | BC19: 2.918337 | BD19: 3.3038478 | BE19: 1.762783 | BF19: 2.4498825 | BG19: 2.4879293 | BH19: 1.508368 | BI19: 1.2769937 | BJ19: 1.9486431 | BK19: 1.9114 | BL19: 1.6107709 | BM19: 0.84690073 | BN19: 2.8639128 | BO19: 6.5940966 | BP19: 5.5970179 | BQ19: 3.1665667 | BR19: 2.8740379
A20: Austria | B20: AUT | C20: Inflation, consumer prices (annual %) | D20: FP.CPI.TOTL.ZG | E20: 1.9457494 | F20: 3.5422399 | G20: 4.3817986 | H20: 2.708767 | I20: 3.8685635 | J20: 4.9309164 | K20: 2.0548206 | L20: 3.9746729 | M20: 2.7648645 | N20: 3.0804042 | O20: 4.3728244 | P20: 4.7042581 | Q20: 6.3551461 | R20: 7.531078 | S20: 9.5217882 | T20: 8.4452586 | U20: 7.3186855 | V20: 5.4946157 | W20: 3.5743186 | X20: 3.707401 | Y20: 6.3283254 | Z20: 6.8030418 | AA20: 5.4360308 | AB20: 3.3391645 | AC20: 5.6631857 | AD20: 3.1895168 | AE20: 1.7054446 | AF20: 1.4019527 | AG20: 1.9157168 | AH20: 2.5683483 | AI20: 3.2618723 | AJ20: 3.337427 | AK20: 4.0208478 | AL20: 3.6317852 | AM20: 2.9534094 | AN20: 2.2433663 | AO20: 1.8609712 | AP20: 1.3059786 | AQ20: 0.9224672 | AR20: 0.56899377 | AS20: 2.3448629 | AT20: 2.6500008 | AU20: 1.8103579 | AV20: 1.3555537 | AW20: 2.0612062 | AX20: 2.2991379 | AY20: 1.4415485 | AZ20: 2.1685553 | BA20: 3.2159503 | BB20: 0.50630883 | BC20: 1.8135344 | BD20: 3.2865791 | BE20: 2.4856756 | BF20: 2.0001562 | BG20: 1.6058118 | BH20: 0.89656334 | BI20: 0.89159175 | BJ20: 2.0812691 | BK20: 1.9983798 | BL20: 1.5308956 | BM20: 1.3819106 | BN20: 2.7666667 | BO20: 8.5468699 | BP20: 7.8141342 | BQ20: 2.9379157 | BR20: 3.5271944
A21: Azerbaijan | B21: AZE | C21: Inflation, consumer prices (annual %) | D21: FP.CPI.TOTL.ZG | AK21: -10.630097 | AL21: 1128 | AM21: 1662.2159 | AN21: 411.75964 | AO21: 19.794803 | AP21: 3.6743481 | AQ21: -0.77269789 | AR21: -8.52517 | AS21: 1.805003 | AT21: 1.5471959 | AU21: 2.7711647 | AV21: 2.2338649 | AW21: 6.7089304 | AX21: 9.6795073 | AY21: 8.3289248 | AZ21: 16.699755 | BA21: 20.849087 | BB21: 1.4570484 | BC21: 5.7268722 | BD21: 7.8583333 | BE21: 1.0662134 | BF21: 2.4157175 | BG21: 1.3734418 | BH21: 4.0276857 | BI21: 12.443375 | BJ21: 12.935918 | BK21: 2.2685469 | BL21: 2.6105718 | BM21: 2.7598095 | BN21: 6.6502991 | BO21: 13.852259 | BP21: 8.7854305 | BQ21: 2.2121719 | BR21: 5.6220879
A22: Burundi | B22: BDI | C22: Inflation, consumer prices (annual %) | D22: FP.CPI.TOTL.ZG | K22: 4.4368601 | L22: -1.0893246 | M22: 6.0572687 | N22: 4.0238837 | O22: -0.19965061 | P22: 3.8509627 | Q22: 3.8285577 | R22: 6.0064935 | S22: 15.722307 | T22: 15.709875 | U22: 6.8565516 | V22: 6.834514 | W22: 23.895621 | X22: 36.540757 | Y22: 2.4985195 | Z22: 12.167394 | AA22: 5.8680964 | AB22: 8.1512314 | AC22: 14.31687 | AD22: 3.8042868 | AE22: 1.6756757 | AF22: 7.1132376 | AG22: 4.4867977 | AH22: 11.6616 | AI22: 7.0021696 | AJ22: 8.9969387 | AK22: 1.8233333 | AL22: 9.6793466 | AM22: 14.852815 | AN22: 19.263254 | AO22: 26.436782 | AP22: 31.11159 | AQ22: 12.500411 | AR22: 3.3854243 | AS22: 24.432024 | AT22: 9.2961877 | AU22: -1.3656801 | AV22: 10.647465 | AW22: 8.1764294 | AX22: 13.25207 | AY22: 2.74542 | AZ22: 8.4120629 | BA22: 24.406951 | BB22: 10.555436 | BC22: 6.4932659 | BD22: 9.5921661 | BE22: 18.161045 | BF22: 7.9379581 | BG22: 4.4053523 | BH22: 5.5446889 | BI22: 5.5576896 | BJ22: 16.052535 | BK22: -2.8146981 | BL22: -0.68677217 | BM22: 7.3211064 | BN22: 8.4045385 | BO22: 18.800879 | BP22: 26.941484 | BQ22: 20.212493 | BR22: 34.133999
A23: Belgium | B23: BEL | C23: Inflation, consumer prices (annual %) | D23: FP.CPI.TOTL.ZG | E23: 0.29945874 | F23: 0.99268334 | G23: 1.4045951 | H23: 2.1480222 | I23: 4.1687487 | J23: 4.0652093 | K23: 4.1743462 | L23: 2.7302884 | M23: 2.7014581 | N23: 3.753991 | O23: 3.9084882 | P23: 4.343614 | Q23: 5.4484353 | R23: 6.9552732 | S23: 12.677894 | T23: 12.768202 | U23: 9.0686075 | V23: 7.0959964 | W23: 4.4705887 | X23: 4.4690947 | Y23: 6.6486854 | Z23: 7.6274806 | AA23: 8.7265549 | AB23: 7.6616091 | AC23: 6.3417756 | AD23: 4.8687296 | AE23: 1.2943745 | AF23: 1.5533732 | AG23: 1.160939 | AH23: 3.1070553 | AI23: 3.4483067 | AJ23: 3.2153153 | AK23: 2.4279524 | AL23: 2.754427 | AM23: 2.3775478 | AN23: 1.4679587 | AO23: 2.0770234 | AP23: 1.6281618 | AQ23: 0.9492517 | AR23: 1.1208493 | AS23: 2.5445122 | AT23: 2.4692613 | AU23: 1.6452138 | AV23: 1.5889629 | AW23: 2.097285 | AX23: 2.7814321 | AY23: 1.7913158 | AZ23: 1.8230025 | BA23: 4.4862743 | BB23: -0.052074293 | BC23: 2.1895003 | BD23: 3.5325394 | BE23: 2.8386507 | BF23: 1.1127833 | BG23: 0.34955573 | BH23: 0.56183563 | BI23: 1.974434 | BJ23: 2.1246754 | BK23: 2.0525751 | BL23: 1.4382892 | BM23: 0.73693266 | BN23: 2.4425879 | BO23: 9.5976538 | BP23: 4.0486795 | BQ23: 3.1442663 | BR23: 2.4660576
A24: Benin | B24: BEN | C24: Inflation, consumer prices (annual %) | D24: FP.CPI.TOTL.ZG | AL24: 0.44059921 | AM24: 38.530866 | AN24: 14.462548 | AO24: 4.9142397 | AP24: 3.4662959 | AQ24: 5.7533146 | AR24: 0.32672289 | AS24: 4.1654044 | AT24: 3.9842955 | AU24: 2.4891624 | AV24: 1.4872425 | AW24: 0.87389083 | AX24: 5.3645209 | AY24: 3.782177 | AZ24: 1.2980681 | BA24: 7.9472988 | BB24: 0.89607236 | BC24: 2.2078353 | BD24: 2.7042391 | BE24: 6.7446825 | BF24: 0.42888889 | BG24: -0.54875755 | BH24: 0.21878592 | BI24: -0.79331015 | BJ24: 0.043264856 | BK24: 0.91917072 | BL24: 0.73284937 | BM24: 3.0227212 | BN24: 1.7335396 | BO24: 1.3507786 | BP24: 2.7387008 | BQ24: 1.1609309 | BR24: 1.1015525
A25: Burkina Faso | B25: BFA | C25: Inflation, consumer prices (annual %) | D25: FP.CPI.TOTL.ZG | E25: 7.788162 | F25: 18.562139 | G25: 1.6759096 | H25: 5.5742028 | I25: 1.8451232 | J25: -0.73025252 | K25: 2.364106 | L25: -4.3337539 | M25: -0.28671369 | N25: 9.6555294 | O25: 1.7726033 | P25: 2.0612182 | Q25: -2.9233566 | R25: 7.6038904 | S25: 8.7196095 | T25: 18.756947 | U25: -8.4007188 | V25: 29.986104 | W25: 8.2691401 | X25: 14.993466 | Y25: 12.202636 | Z25: 7.5557056 | AA25: 12.059765 | AB25: 8.1537628 | AC25: 4.8469577 | AD25: 6.9060578 | AE25: -2.6117429 | AF25: -2.6817842 | AG25: 4.255616 | AH25: -0.48179872 | AI25: -0.50430339 | AJ25: 2.1626005 | AK25: -1.9911358 | AL25: 0.55345572 | AM25: 25.177876 | AN25: 7.458845 | AO25: 6.0978044 | AP25: 2.3186906 | AQ25: 5.0843334 | AR25: -1.0726136 | AS25: -0.30421217 | AT25: 5.0074329 | AU25: 2.1756948 | AV25: 2.0345657 | AW25: -0.4002287 | AX25: 6.4150402 | AY25: 2.3331086 | AZ25: -0.23062731 | BA25: 10.659798 | BB25: 2.6081767 | BC25: -0.76423073 | BD25: 2.7597672 | BE25: 3.8181524 | BF25: 0.53373851 | BG25: -0.25808952 | BH25: 0.72483898 | BI25: 0.44104145 | BJ25: 1.482999 | BK25: 1.955943 | BL25: -3.2333893 | BM25: 1.8847007 | BN25: 3.6532676 | BO25: 14.290235 | BP25: 0.74291043 | BQ25: 4.1908172 | BR25: -0.58623532
A26: Bangladesh | B26: BGD | C26: Inflation, consumer prices (annual %) | D26: FP.CPI.TOTL.ZG | AF26: 9.8746961 | AG26: 7.412766 | AH26: 6.0454798 | AI26: 6.1267185 | AJ26: 6.3573641 | AK26: 3.6340769 | AL26: 3.0148186 | AM26: 5.3137401 | AN26: 10.297812 | AO26: 2.377129 | AP26: 5.3056011 | AQ26: 8.402238 | AR26: 6.1066959 | AS26: 2.2082562 | AT26: 2.0071737 | AU26: 3.3325649 | AV26: 5.6687077 | AW26: 7.5875364 | AX26: 7.0466182 | AY26: 6.7652612 | AZ26: 9.106985 | BA26: 8.9019449 | BB26: 5.4234724 | BC26: 8.1266764 | BD26: 11.395165 | BE26: 6.2175042 | BF26: 7.5304064 | BG26: 6.9916389 | BH26: 6.1942802 | BI26: 5.5135257 | BJ26: 5.7020702 | BK26: 5.5436214 | BL26: 5.5919964 | BM26: 5.6910747 | BN26: 5.5456543 | BO26: 7.6969544 | BP26: 9.883503 | BQ26: 10.465748 | BR26: 8.7687628
A27: Bulgaria | B27: BGR | C27: Inflation, consumer prices (annual %) | D27: FP.CPI.TOTL.ZG | AE27: 2.7 | AF27: 2.7263875 | AG27: 2.3696682 | AH27: 6.3888889 | AI27: 23.8 | AJ27: 338.44911 | AK27: 91.297933 | AL27: 72.878791 | AM27: 96.057338 | AN27: 62.054834 | AO27: 121.60754 | AP27: 1058.3736 | AQ27: 18.672204 | AR27: 2.5730428 | AS27: 10.316262 | AT27: 7.3609393 | AU27: 5.8101437 | AV27: 2.3486417 | AW27: 6.1471307 | AX27: 5.0388381 | AY27: 7.2615946 | AZ27: 8.4025342 | BA27: 12.34872 | BB27: 2.7532022 | BC27: 2.4389906 | BD27: 4.2199035 | BE27: 2.9545683 | BF27: 0.89009354 | BG27: -1.4181838 | BH27: -0.10463326 | BI27: -0.79864989 | BJ27: 2.0615962 | BK27: 2.8145447 | BL27: 3.1037294 | BM27: 1.672441 | BN27: 3.2977444 | BO27: 15.325259 | BP27: 9.4428414 | BQ27: 2.4465194 | BR27: 4.5808436
A28: Bahrain | B28: BHR | C28: Inflation, consumer prices (annual %) | D28: FP.CPI.TOTL.ZG | K28: 2.1344717 | L28: 4.2580982 | M28: 3.257329 | N28: -0.19412764 | O28: 1.6289813 | P28: 5.7894737 | Q28: 5.0881954 | R28: 14.331827 | S28: 24.392998 | T28: 16.159782 | U28: 22.495767 | V28: 17.731121 | W28: 15.785538 | X28: 2.205992 | Y28: 3.8695251 | Z28: 11.344597 | AA28: 8.8857131 | AB28: 2.9723992 | AC28: 0.32239925 | AD28: -2.6359693 | AE28: -2.2960932 | AF28: -1.7450018 | AG28: 0.30343597 | AH28: 1.4858973 | AI28: 0.92933544 | AJ28: 0.76441974 | AK28: -0.17241379 | AL28: 2.5388601 | AM28: 0.8169109 | AN28: 2.7040348 | AO28: -0.45222738 | AP28: 2.4315513 | AQ28: -0.36653386 | AR28: -1.287588 | AS28: -0.70485295 | AT28: -1.2075718 | AU28: -0.49554014 | AV28: 1.5936255 | AW28: 2.3529412 | AX28: 2.5862069 | AY28: 2.0074697 | AZ28: 3.2566667 | BA28: 3.5260032 | BB28: 2.7955128 | BC28: 1.9618847 | BD28: -0.4000407 | BE28: 2.7573967 | BF28: 3.3000116 | BG28: 2.6475532 | BH28: 1.8486274 | BI28: 2.7867935 | BJ28: 1.3867183 | BK28: 2.0876694 | BL28: 1.00582 | BM28: -2.3177063 | BN28: -0.60631939 | BO28: 3.625741 | BP28: 0.074620678 | BQ28: 0.91963546 | BR28: -0.13770886
A29: Bahamas, The | B29: BHS | C29: Inflation, consumer prices (annual %) | D29: FP.CPI.TOTL.ZG | L29: 5.4377565 | M29: 4.5410315 | N29: 8.9357741 | O29: 6.1520934 | P29: 4.6149718 | Q29: 6.8308113 | R29: 5.4817542 | S29: 13.071846 | T29: 10.359635 | U29: 4.2558366 | V29: 3.1898764 | W29: 6.1090704 | X29: 9.0913933 | Y29: 12.097837 | Z29: 11.114498 | AA29: 6.012621 | AB29: 4 | AC29: 3.9663462 | AD29: 4.6050096 | AE29: 5.4337815 | AF29: 5.756464 | AG29: 4.4024118 | AH29: 5.3876582 | AI29: 4.6693191 | AJ29: 7.1146812 | AK29: 5.7381989 | AL29: 2.7228977 | AM29: 1.3993342 | AN29: 2.066995 | AO29: 1.3791374 | AP29: 0.54415038 | AQ29: 1.3366134 | AR29: 1.2542483 | AS29: 1.6063294 | AT29: 2.0449898 | AU29: 2.1735779 | AV29: 3.0250453 | AW29: 0.98191404 | AX29: 1.5916062 | AY29: 2.3898263 | AZ29: 2.4925779 | BA29: 4.48956 | BB29: 2.0627347 | BC29: 1.3440274 | BD29: 3.1987814 | BE29: 1.9733676 | BF29: 0.72241478 | BG29: 1.5137564 | BH29: 1.861483 | BI29: -0.34637693 | BJ29: 1.518207 | BK29: 2.2658635 | BL29: 2.4912353 | BM29: 0.038521098 | BN29: 2.9049126 | BO29: 5.6054063 | BP29: 3.0529158 | BQ29: 0.40916249 | BR29: 1.1087978
A30: Bosnia and Herzegovina | B30: BIH | C30: Inflation, consumer prices (annual %) | D30: FP.CPI.TOTL.ZG | AY30: 6.1255662 | AZ30: 1.5007771 | BA30: 7.4270431 | BB30: -0.38146428 | BC30: 1.9962124 | BD30: 3.67125 | BE30: 2.0526745 | BF30: -0.093045684 | BG30: -0.89719405 | BH30: -1.036023 | BI30: -1.5841 | BJ30: 0.81013332 | BK30: 1.4171081 | BL30: 0.56278215 | BM30: -1.051296 | BN30: 1.981639 | BO30: 14.020844 | BP30: 6.1059011 | BQ30: 1.6921273 | BR30: 3.9782127
A31: Belarus | B31: BLR | C31: Inflation, consumer prices (annual %) | D31: FP.CPI.TOTL.ZG | AL31: 1190.2292 | AM31: 2221.0166 | AN31: 709.34603 | AO31: 52.712077 | AP31: 63.937366 | AQ31: 72.869717 | AR31: 293.67875 | AS31: 168.62024 | AT31: 61.134933 | AU31: 42.537548 | AV31: 28.39784 | AW31: 18.108242 | AX31: 10.338879 | AY31: 6.997129 | AZ31: 8.4267527 | BA31: 14.837876 | BB31: 12.945656 | BC31: 7.735748 | BD31: 53.228698 | BE31: 59.219736 | BF31: 18.312261 | BG31: 18.119554 | BH31: 13.53449 | BI31: 11.836581 | BJ31: 6.0318373 | BK31: 4.8723022 | BL31: 5.598156 | BM31: 5.5481436 | BN31: 9.4602839 | BO31: 15.209675 | BP31: 5.000599 | BQ31: 5.7853191 | BR31: 6.5987795
A32: Belize | B32: BLZ | C32: Inflation, consumer prices (annual %) | D32: FP.CPI.TOTL.ZG | Z32: 11.22449 | AA32: 6.8390325 | AB32: 4.9960968 | AC32: 3.3828996 | AD32: 6.2371661 | AE32: 0.79977149 | AF32: 2.0119014 | AG32: 3.1388889 | AH32: 2.1276596 | AI32: 3.0590717 | AJ32: 0.7619515 | AK32: 2.3967007 | AL32: 1.4725969 | AM32: 2.569343 | AN32: 2.8896158 | AO32: 5.965021 | AP32: 1.1490376 | AQ32: 2.1952625 | AR32: 2.6213952 | AS32: 3.0674397 | AT32: 3.6514179 | AU32: 4.2402666 | AV32: 2.3180827 | AW32: 6.394431 | AX32: -1.1043104 | AY32: -7.1137677 | AZ32: 2.3180827 | BA32: 6.394431 | BB32: -1.1043104 | BC32: 0.91797738 | BD32: 1.6020562 | BE32: 1.3005807 | BF32: 0.50974777 | BG32: 1.2013996 | BH32: -0.86158401 | BI32: 0.66342717 | BJ32: 1.1476534 | BK32: 0.26998262 | BL32: 0.18706939 | BM32: 0.12143464 | BN32: 3.2356366 | BO32: 6.2768932 | BP32: 4.3898402 | BQ32: 3.2895599 | BR32: 1.0628155
A33: Bermuda | B33: BMU | C33: Inflation, consumer prices (annual %) | D33: FP.CPI.TOTL.ZG
A34: Bolivia | B34: BOL | C34: Inflation, consumer prices (annual %) | D34: FP.CPI.TOTL.ZG | E34: 11.533153 | F34: 7.5614931 | G34: 5.8793314 | H34: -0.70635721 | I34: 10.181818 | J34: 2.860286 | K34: 6.9518717 | L34: 11.2 | M34: 5.4706235 | N34: 2.2097485 | O34: 3.9555092 | P34: 3.6746143 | Q34: 6.511544 | R34: 31.486029 | S34: 62.836076 | T34: 7.976746 | U34: 4.4940116 | V34: 8.1072555 | W34: 10.355672 | X34: 19.719717 | Y34: 47.24165 | Z34: 32.133601 | AA34: 123.53572 | AB34: 275.58628 | AC34: 1281.3499 | AD34: 11749.64 | AE34: 276.33597 | AF34: 14.578698 | AG34: 16.002091 | AH34: 15.173468 | AI34: 17.118775 | AJ34: 21.44707 | AK34: 12.060324 | AL34: 8.527877 | AM34: 7.8740442 | AN34: 10.193207 | AO34: 12.425487 | AP34: 4.7084444 | AQ34: 7.673229 | AR34: 2.1595163 | AS34: 4.60823 | AT34: 1.5896538 | AU34: 0.92825885 | AV34: 3.337275 | AW34: 4.4373808 | AX34: 5.3932311 | AY34: 4.282396 | AZ34: 8.7056092 | BA34: 14.006811 | BB34: 3.3464542 | BC34: 2.5032761 | BD34: 9.8844642 | BE34: 4.5156029 | BF34: 5.7364002 | BG34: 5.7666007 | BH34: 4.0596104 | BI34: 3.6232143 | BJ34: 2.8227581 | BK34: 2.2720599 | BL34: 1.839545 | BM34: 0.94074215 | BN34: 0.73738372 | BO34: 1.7463287 | BP34: 2.576888 | BQ34: 5.0997657 | BR34: 19.517121
A35: Brazil | B35: BRA | C35: Inflation, consumer prices (annual %) | D35: FP.CPI.TOTL.ZG | Z35: 101.72507 | AA35: 100.54336 | AB35: 135.02768 | AC35: 192.12173 | AD35: 225.98967 | AE35: 147.14283 | AF35: 228.33616 | AG35: 629.11451 | AH35: 1430.7237 | AI35: 2947.7328 | AJ35: 432.78666 | AK35: 951.96205 | AL35: 1927.3808 | AM35: 2075.8884 | AN35: 66.007034 | AO35: 15.757666 | AP35: 6.9267125 | AQ35: 3.1950763 | AR35: 4.8584475 | AS35: 7.0441411 | AT35: 6.840359 | AU35: 8.4501644 | AV35: 14.71492 | AW35: 6.5971851 | AX35: 6.8695372 | AY35: 4.1835681 | AZ35: 3.641273 | BA35: 5.6785939 | BB35: 4.8880348 | BC35: 5.0387269 | BD35: 6.6364496 | BE35: 5.4034991 | BF35: 6.2043107 | BG35: 6.3290402 | BH35: 9.029901 | BI35: 8.7391435 | BJ35: 3.4463734 | BK35: 3.6648503 | BL35: 3.7329762 | BM35: 3.211768 | BN35: 8.3016598 | BO35: 9.2801061 | BP35: 4.5935628 | BQ35: 4.3674641 | BR35: 5.0167528
A36: Barbados | B36: BRB | C36: Inflation, consumer prices (annual %) | D36: FP.CPI.TOTL.ZG | L36: 3.6348752 | M36: 7.4887432 | N36: 5.8352319 | O36: 7.2842164 | P36: 7.4692557 | Q36: 11.876656 | R36: 16.855082 | S36: 38.922928 | T36: 20.294469 | U36: 4.9867681 | V36: 8.3523697 | W36: 9.4823826 | X36: 13.169836 | Y36: 14.43052 | Z36: 14.567563 | AA36: 10.332466 | AB36: 5.2302988 | AC36: 4.6857973 | AD36: 3.9151053 | AE36: 1.3300685 | AF36: 3.3117311 | AG36: 4.8588592 | AH36: 6.1901141 | AI36: 3.0745727 | AJ36: 6.2575266 | AK36: 6.093893 | AL36: 1.1134393 | AM36: 0.077204388 | AN36: 1.8788628 | AO36: 2.3861522 | AP36: 7.7105388 | AQ36: -1.2688866 | AR36: 1.5600624 | AS36: 2.435813 | AT36: 2.5778349 | AU36: 0.12524946 | AV36: 1.6194332 | AW36: 1.3944223 | AX36: 6.0821873 | AY36: 7.3076626 | AZ36: 4.0342298 | BA36: 8.1081081 | BB36: 3.6438619 | BC36: 5.8242185 | BD36: 9.4322024 | BE36: 4.5333475 | BF36: 1.8141044 | BG36: 1.7695032 | BH36: -1.1127899 | BI36: 1.2819281 | BJ36: 4.6601846 | BK36: 3.1060057 | BL36: 1.6766247 | BP36: 3.1871891 | BQ36: 1.4464366 | BR36: 0.84657656
A37: Brunei Darussalam | B37: BRN | C37: Inflation, consumer prices (annual %) | D37: FP.CPI.TOTL.ZG | Z37: 9.1370558 | AA37: 6.3565891 | AB37: 1.1661808 | AC37: 3.0739673 | AD37: 2.3532153 | AE37: 1.7812429 | AF37: 1.2468549 | AG37: 1.1928429 | AH37: 1.3043004 | AI37: 2.1386629 | AJ37: 1.6 | AK37: 1.2795276 | AL37: 4.2517007 | AM37: 2.4625184 | AN37: 5.9666414 | AO37: 1.9961365 | AP37: 1.71156 | AQ37: -0.44137931 | AR37: -0.4156276 | AS37: 1.5581525 | AT37: 0.59589041 | AU37: -2.3149724 | AV37: 0.3 | AW37: 0.81422399 | AX37: 1.2444371 | AY37: 0.15988808 | AZ37: 0.96777412 | BA37: 2.0849802 | BB37: 1.0357177 | BC37: 0.35686913 | BD37: 0.13791156 | BE37: 0.11176626 | BF37: 0.38920505 | BG37: -0.20710873 | BH37: -0.41512193 | BI37: -0.73906872 | BJ37: -0.17131153 | BK37: 0.15052349 | BL37: -0.37137214 | BM37: 1.9403062 | BN37: 1.7334139 | BO37: 3.6822503 | BP37: 0.35706431 | BQ37: -0.38867417 | BR37: -0.30299441
A38: Bhutan | B38: BTN | C38: Inflation, consumer prices (annual %) | D38: FP.CPI.TOTL.ZG | Z38: 9.9723757 | AA38: 9.8467722 | AB38: 18.057779 | AC38: 7.0377066 | AD38: 1.8820123 | AE38: 9.964476 | AF38: 6.3317719 | AG38: 10.096714 | AH38: 8.7798372 | AI38: 10.011838 | AJ38: 12.275173 | AK38: 15.975217 | AL38: 11.198017 | AM38: 7.0099536 | AN38: 9.4875484 | AO38: 8.7900138 | AP38: 6.5054872 | AQ38: 10.58559 | AR38: 6.7769939 | AS38: 4.0121208 | AT38: 3.4147895 | AU38: 2.4553571 | AV38: 2.5723086 | AW38: 4.105937 | AX38: 5.312631 | AY38: 5.0004544 | AZ38: 5.1561114 | BA38: 8.3271605 | BB38: 4.3611222 | BC38: 7.0363832 | BD38: 8.8489857 | BE38: 10.919657 | BF38: 8.7763835 | BG38: 8.2710609 | BH38: 4.548144 | BI38: 3.2198869 | BJ38: 4.9550837 | BK38: 2.7239639 | BL38: 2.7264304 | BM38: 5.6293652 | BN38: 7.3468144 | BO38: 5.6391667 | BP38: 4.2293442 | BQ38: 2.7613157 | BR38: 3.5551366
A39: Botswana | B39: BWA | C39: Inflation, consumer prices (annual %) | D39: FP.CPI.TOTL.ZG | T39: 11.974755 | U39: 11.732424 | V39: 13.168724 | W39: 9.0439883 | X39: 11.736231 | Y39: 13.632425 | Z39: 16.428027 | AA39: 11.137206 | AB39: 10.477144 | AC39: 8.577469 | AD39: 8.0945758 | AE39: 10.001716 | AF39: 9.8019339 | AG39: 8.3516796 | AH39: 11.575015 | AI39: 11.396346 | AJ39: 11.765016 | AK39: 16.167612 | AL39: 14.330803 | AM39: 10.542921 | AN39: 10.512546 | AO39: 10.082858 | AP39: 8.7199313 | AQ39: 6.6613987 | AR39: 7.7492962 | AS39: 8.6014851 | AT39: 6.5590377 | AU39: 8.0327966 | AV39: 9.1899027 | AW39: 6.9457036 | AX39: 8.6102253 | AY39: 11.555219 | AZ39: 7.0809985 | BA39: 12.702188 | BB39: 8.027297 | BC39: 6.9488766 | BD39: 8.4598723 | BE39: 7.5369026 | BF39: 5.8846071 | BG39: 4.4022531 | BH39: 3.0620317 | BI39: 2.8149579 | BJ39: 3.3082808 | BK39: 3.2380156 | BL39: 2.7728644 | BM39: 1.8903592 | BN39: 7.2409777 | BO39: 11.665567 | BP39: 5.0676155 | BQ39: 2.8183513 | BR39: 2.6598504
A40: Central African Republic | B40: CAF | C40: Inflation, consumer prices (annual %) | D40: FP.CPI.TOTL.ZG | Z40: -0.033333333 | AA40: 13.296099 | AB40: 14.612611 | AC40: 2.5422097 | AD40: 10.42384 | AE40: 2.2451525 | AF40: -6.9868027 | AG40: -3.9644688 | AH40: 0.68905581 | AI40: -0.012330456 | AJ40: -2.7623628 | AK40: -1.0336081 | AL40: -2.9153585 | AM40: 24.571014 | AN40: 19.189404 | AO40: 3.7249411 | AP40: 1.6113135 | AQ40: -1.885201 | AR40: -1.4142022 | AS40: 3.2034009 | AT40: 3.8348606 | AU40: 2.331817 | AV40: 4.1347091 | AW40: -2.066406 | AX40: 2.8835207 | AY40: 6.6952647 | AZ40: 0.95991762 | BA40: 9.258951 | BB40: 3.5212623 | BC40: 1.4910237 | BD40: 1.1944757 | BE40: 5.4782959 | BF40: 6.9887934 | BG40: 14.898684 | BH40: 1.4029702 | BI40: 4.9454328 | BJ40: 4.1807233 | BK40: 1.6121569 | BL40: 2.6853736 | BM40: 1.7101566 | BN40: 4.2593642 | BO40: 5.5831674 | BP40: 2.9791385 | BQ40: 1.477336 | BR40: 1.0019801
A41: Canada | B41: CAN | C41: Inflation, consumer prices (annual %) | D41: FP.CPI.TOTL.ZG | E41: 1.3586957 | F41: 1.0187668 | G41: 1.0615711 | H41: 1.6281513 | I41: 1.9121447 | J41: 2.3326572 | K41: 3.8156591 | L41: 3.5799523 | M41: 4.0552995 | N41: 4.5615589 | O41: 3.3460398 | P41: 2.704918 | Q41: 4.9880287 | R41: 7.4876473 | S41: 10.997171 | T41: 10.672189 | U41: 7.5417386 | V41: 7.9764454 | W41: 8.9737234 | X41: 9.144677 | Y41: 10.129221 | Z41: 12.471612 | AA41: 10.768972 | AB41: 5.863588 | AC41: 4.3047783 | AD41: 3.9620305 | AE41: 4.1947863 | AF41: 4.3561087 | AG41: 4.0282341 | AH41: 4.9836219 | AI41: 4.7804769 | AJ41: 5.6258641 | AK41: 1.4901329 | AL41: 1.8650794 | AM41: 0.16556291 | AN41: 2.1487603 | AO41: 1.5705311 | AP41: 1.6212164 | AQ41: 0.99594246 | AR41: 1.734843 | AS41: 2.71944 | AT41: 2.5251201 | AU41: 2.2583944 | AV41: 2.7585632 | AW41: 1.8572587 | AX41: 2.213552 | AY41: 2.0020254 | AZ41: 2.138384 | BA41: 2.3702707 | BB41: 0.2994668 | BC41: 1.7768715 | BD41: 2.9121351 | BE41: 1.5156782 | BF41: 0.9382919 | BG41: 1.9066359 | BH41: 1.1252414 | BI41: 1.4287595 | BJ41: 1.5968841 | BK41: 2.2682257 | BL41: 1.949269 | BM41: 0.71699963 | BN41: 3.3951932 | BO41: 6.8028012 | BP41: 3.8790016 | BQ41: 2.3815838 | BR41: 2.0723241
A42: Central Europe and the Baltics | B42: CEB | C42: Inflation, consumer prices (annual %) | D42: FP.CPI.TOTL.ZG | AJ42: 118.52757 | AK42: 150.61586 | AL42: 72.878791 | AM42: 35.924705 | AN42: 27.951389 | AO42: 19.794967 | AP42: 8.8811294 | AQ42: 8.2083333 | AR42: 4.0191388 | AS42: 8.9065536 | AT42: 5.753643 | AU42: 3.1271422 | AV42: 2.3486417 | AW42: 3.5953918 | AX42: 3.3171782 | AY42: 3.9210432 | AZ42: 4.8373293 | BA42: 6.3586638 | BB42: 2.7532022 | BC42: 1.7968631 | BD42: 4.130288 | BE42: 3.3349227 | BF42: 1.4382979 | BG42: 0.053821313 | BH42: -0.464499 | BI42: -0.051046452 | BJ42: 2.0759355 | BK42: 2.5344542 | BL42: 2.6645613 | BM42: 1.672441 | BN42: 3.8398449 | BO42: 14.608144 | BP42: 9.4428414 | BQ42: 2.7576091 | BR42: 3.8141953
A43: Switzerland | B43: CHE | C43: Inflation, consumer prices (annual %) | D43: FP.CPI.TOTL.ZG | E43: 1.4387947 | F43: 1.8453979 | G43: 4.3159929 | H43: 3.4402129 | I43: 3.0805569 | J43: 3.4144786 | K43: 4.7759796 | L43: 4.0051962 | M43: 2.3958223 | N43: 2.489036 | O43: 3.6159868 | P43: 6.5732211 | Q43: 6.660007 | R43: 8.7546703 | S43: 9.7674143 | T43: 6.6965952 | U43: 1.7154763 | V43: 1.2959992 | W43: 1.0287929 | X43: 3.6476401 | Y43: 4.0225008 | Z43: 6.4903096 | AA43: 5.6551018 | AB43: 2.9497944 | AC43: 2.9314567 | AD43: 3.4353994 | AE43: 0.75030984 | AF43: 1.4403219 | AG43: 1.8724686 | AH43: 3.1552698 | AI43: 5.4039591 | AJ43: 5.8595966 | AK43: 4.0370302 | AL43: 3.2926218 | AM43: 0.852117 | AN43: 1.7998278 | AO43: 0.81163406 | AP43: 0.52022542 | AQ43: 0.017938438 | AR43: 0.80644438 | AS43: 1.5585292 | AT43: 0.98902033 | AU43: 0.64271151 | AV43: 0.63827293 | AW43: 0.80290873 | AX43: 1.1719542 | AY43: 1.0595093 | AZ43: 0.7323506 | BA43: 2.4260412 | BB43: -0.48048194 | BC43: 0.68823871 | BD43: 0.23134921 | BE43: -0.69255202 | BF43: -0.21732316 | BG43: -0.013202539 | BH43: -1.1439087 | BI43: -0.43461866 | BJ43: 0.53378784 | BK43: 0.93633546 | BL43: 0.36288618 | BM43: -0.72587493 | BN43: 0.58181417 | BO43: 2.835028 | BP43: 2.1354009 | BQ43: 1.0623404 | BR43: 0.15437698
A44: Channel Islands | B44: CHI | C44: Inflation, consumer prices (annual %) | D44: FP.CPI.TOTL.ZG
A45: Chile | B45: CHL | C45: Inflation, consumer prices (annual %) | D45: FP.CPI.TOTL.ZG | P45: 20.052241 | Q45: 77.795734 | R45: 352.811 | S45: 504.73852 | T45: 374.73524 | U45: 211.92432 | V45: 91.95416 | W45: 40.087211 | X45: 33.389196 | Y45: 35.138356 | Z45: 19.686838 | AA45: 9.9410195 | AB45: 27.257199 | AC45: 19.860203 | AD45: 30.703499 | AE45: 19.47687 | AF45: 19.880798 | AG45: 14.684351 | AH45: 17.027954 | AI45: 26.036474 | AJ45: 21.784427 | AK45: 15.425795 | AL45: 12.727762 | AM45: 11.443127 | AN45: 8.2326424 | AO45: 7.3591111 | AP45: 6.1338653 | AQ45: 5.1102417 | AR45: 3.3368827 | AS45: 3.8432746 | AT45: 3.5691003 | AU45: 2.4893966 | AV45: 2.810182 | AW45: 1.0547374 | AX45: 3.0525744 | AY45: 3.3920167 | AZ45: 4.4077956 | BA45: 8.7162683 | BB45: 0.35304856 | BC45: 1.4107068 | BD45: 3.3412231 | BE45: 3.0074474 | BF45: 1.7895559 | BG45: 4.7186747 | BH45: 4.3487728 | BI45: 3.7861947 | BJ45: 2.1827156 | BK45: 2.4348915 | BL45: 2.5575477 | BM45: 3.0454894 | BN45: 4.5245676 | BO45: 11.643867 | BP45: 7.5816748 | BQ45: 4.2976431 | BR45: 4.2129403
A46: China | B46: CHN | C46: Inflation, consumer prices (annual %) | D46: FP.CPI.TOTL.ZG | AF46: 7.2338355 | AG46: 18.811818 | AH46: 18.245638 | AI46: 3.0522901 | AJ46: 3.5566857 | AK46: 6.3539813 | AL46: 14.610079 | AM46: 24.25699 | AN46: 16.791225 | AO46: 8.3131603 | AP46: 2.7864651 | AQ46: -0.77318601 | AR46: -1.4014727 | AS46: 0.34781123 | AT46: 0.71912561 | AU46: -0.7319709 | AV46: 1.1276035 | AW46: 3.8246374 | AX46: 1.7764141 | AY46: 1.649431 | AZ46: 4.8167677 | BA46: 5.9252514 | BB46: -0.72816525 | BC46: 3.1753248 | BD46: 5.5538989 | BE46: 2.6195243 | BF46: 2.62105 | BG46: 1.9216416 | BH46: 1.4370238 | BI46: 2.0000018 | BJ46: 1.593136 | BK46: 2.0747904 | BL46: 2.8992342 | BM46: 2.4194219 | BN46: 0.98101514 | BO46: 1.9735756 | BP46: 0.23483683 | BQ46: 0.21812894 | BR46: 0.059564692
A47: Cote d'Ivoire | B47: CIV | C47: Inflation, consumer prices (annual %) | D47: FP.CPI.TOTL.ZG | F47: 11.616492 | G47: -1.3412489 | H47: 0.94346631 | I47: 0.61819252 | J47: 2.6111761 | K47: 4.191318 | L47: 2.291852 | M47: 5.3504548 | N47: 4.4502285 | O47: 8.2051905 | P47: -0.44374544 | Q47: 0.3103137 | R47: 11.102987 | S47: 17.359388 | T47: 11.444224 | U47: 12.07664 | V47: 27.421862 | W47: 13.242987 | X47: 16.342357 | Y47: 14.700981 | Z47: 8.7992108 | AA47: 7.5831259 | AB47: 5.6404284 | AC47: 4.2847611 | AD47: 1.8638033 | AE47: 9.6829547 | AF47: 6.9433063 | AG47: 6.9306862 | AH47: 1.0495182 | AI47: -0.8058797 | AJ47: 1.6833485 | AK47: 4.2313838 | AL47: 2.1647145 | AM47: 26.081572 | AN47: 14.295069 | AO47: 2.4808067 | AP47: 4.0208333 | AQ47: 4.6114476 | AR47: 0.70237581 | AS47: 2.5307752 | AT47: 4.3615291 | AU47: 3.0772649 | AV47: 3.2968075 | AW47: 1.4579884 | AX47: 3.8858304 | AY47: 2.4671915 | AZ47: 1.8920063 | BA47: 6.3085277 | BB47: 1.0195046 | BC47: 1.2264561 | BD47: 4.912434 | BE47: 1.3045112 | BF47: 2.5811704 | BG47: 0.44868208 | BH47: 1.2514995 | BI47: 0.72317846 | BJ47: 0.68588107 | BK47: 0.40129782 | BL47: 0.79085551 | BM47: 2.4125262 | BN47: 4.1591966 | BO47: 5.2335286 | BP47: 4.3697225 | BQ47: 3.4505303 | BR47: 0.12503877
A48: Cameroon | B48: CMR | C48: Inflation, consumer prices (annual %) | D48: FP.CPI.TOTL.ZG | N48: -1.1015912 | O48: 5.8580858 | P48: 4.0140296 | Q48: 8.0929187 | R48: 10.384749 | S48: 17.232933 | T48: 13.553329 | U48: 9.9306506 | V48: 14.698309 | W48: 12.463052 | X48: 6.5806108 | Y48: 9.5517543 | Z48: 10.7275 | AA48: 13.25702 | AB48: 16.631226 | AC48: 11.373322 | AD48: 8.5083743 | AE48: 7.770025 | AF48: 13.1405 | AG48: 1.6823326 | AH48: -1.6655259 | AI48: 1.0993813 | AJ48: 0.060051331 | AK48: -0.016055046 | AL48: -3.2065546 | AM48: 35.094462 | AN48: 9.0696907 | AO48: 3.9240637 | AP48: 4.7862388 | AQ48: 3.1707519 | AR48: 1.871745 | AS48: 1.2271901 | AT48: 4.4197725 | AU48: 2.8344226 | AV48: 0.62316356 | AW48: 0.23364738 | AX48: 2.0135395 | AY48: 5.1175782 | AZ48: 0.92140225 | BA48: 5.3378063 | BB48: 3.0436185 | BC48: 1.2753805 | BD48: 2.9396995 | BE48: 2.7352968 | BF48: 2.0503472 | BG48: 1.8548985 | BH48: 2.6762353 | BI48: 0.87419038 | BJ48: 0.64040915 | BK48: 1.0688581 | BL48: 2.4528021 | BM48: 2.4376088 | BN48: 2.2718576 | BO48: 6.2476771 | BP48: 7.3828138 | BQ48: 4.5333135 | BR48: 3.4037346
A49: Congo, Dem. Rep. | B49: COD | C49: Inflation, consumer prices (annual %) | D49: FP.CPI.TOTL.ZG | I49: 35.421065 | J49: -2.7269803 | K49: 15.780101 | L49: 36.926525 | M49: 53.321673 | N49: 6.1761957 | O49: 8.025284 | P49: 5.7773498 | Q49: 15.804215 | R49: 15.642762 | S49: 29.469281 | T49: 28.65797 | U49: 80.385959 | V49: 68.947708 | W49: 48.769038 | X49: 101.05126 | Y49: 46.625907 | Z49: 35.408265 | AA49: 36.699698 | AB49: 76.526698 | AC49: 52.227011 | AD49: 23.820785 | AE49: 44.4 | AF49: 78.67036 | AG49: 71.091731 | AH49: 104.06523 | AI49: 81.295405 | AJ49: 2154.4368 | AK49: 4129.1699 | AL49: 1986.9048 | AM49: 23773.132 | AN49: 541.90888 | AO49: 492.44185 | AP49: 198.51671 | AQ49: 29.148807 | AR49: 284.89498 | AS49: 513.90684 | AT49: 359.93661 | AU49: 31.522583 | AV49: 12.873966 | AW49: 3.994384 | AX49: 21.316817 | AY49: 13.052695 | AZ49: 16.945101 | BA49: 17.301385 | BB49: 2.8 | BC49: 7.1 | BD49: 15.316516 | BE49: 9.7218281 | BF49: 0.8082231 | BG49: 1.2430389 | BH49: 0.74419899 | BI49: 2.8858511
A50: Congo, Rep. | B50: COG | C50: Inflation, consumer prices (annual %) | D50: FP.CPI.TOTL.ZG | AE50: 4.1581109 | AF50: 0.44356826 | AG50: 1.030422 | AH50: -1.7969888 | AI50: 2.8890537 | AJ50: -1.6783497 | AK50: -3.9354681 | AL50: 4.9236641 | AM50: 42.439675 | AN50: 9.4180074 | AO50: 10.03112 | AR50: 4.1426714 | AS50: -0.88199152 | AT50: 0.055989922 | AU50: 4.3787597 | AV50: -0.63184499 | AW50: 2.4297661 | AX50: 3.0944901 | AY50: 6.537844 | AZ50: 2.6546465 | BA50: 4.9587509 | BB50: 4.4150037 | BC50: 0.39152501 | BD50: 1.759587 | BE50: 5.0101877 | BF50: 4.6316162 | BG50: 0.91213955 | BH50: 3.169098 | BI50: 3.1905618 | BJ50: 0.45006382 | BK50: 1.152779 | BL50: 2.2060731 | BM50: 1.7953715 | BN50: 1.7156428 | BO50: 3.0434433 | BP50: 4.3017456 | BQ50: 3.0914363 | BR50: 2.4006956
A51: Colombia | B51: COL | C51: Inflation, consumer prices (annual %) | D51: FP.CPI.TOTL.ZG | E51: 5.8140763 | F51: 8.2831905 | G51: 4.697094 | H51: 26.355436 | I51: 17.072435 | J51: 7.5906837 | K51: 16.728168 | L51: 8.3281914 | M51: 7.4475388 | N51: 6.9816631 | O51: 6.9086228 | P51: 11.940262 | Q51: 12.444459 | R51: 22.529649 | S51: 23.870957 | T51: 23.437503 | U51: 19.831225 | V51: 33.802818 | W51: 17.763159 | X51: 24.134076 | Y51: 26.552653 | Z51: 27.453762 | AA51: 24.720988 | AB51: 19.597317 | AC51: 16.161617 | AD51: 24.090174 | AE51: 18.842463 | AF51: 23.302028 | AG51: 28.108397 | AH51: 25.867548 | AI51: 29.152025 | AJ51: 30.38782 | AK51: 27.010627 | AL51: 22.442483 | AM51: 22.846242 | AN51: 20.891793 | AO51: 20.797576 | AP51: 18.470022 | AQ51: 18.67698 | AR51: 10.873687 | AS51: 9.2253482 | AT51: 7.9655609 | AU51: 6.3515073 | AV51: 7.1297886 | AW51: 5.9040201 | AX51: 5.0510196 | AY51: 4.2934236 | AZ51: 5.5443849 | BA51: 6.996885 | BB51: 4.2025166 | BC51: 2.2720023 | BD51: 3.4150334 | BE51: 3.1693019 | BF51: 2.0169922 | BG51: 2.8988379 | BH51: 4.9898312 | BI51: 7.5134602 | BJ51: 4.3143133 | BK51: 3.2405693 | BL51: 3.5230193 | BM51: 2.526635 | BN51: 3.4950576 | BO51: 10.177231 | BP51: 11.735904 | BQ51: 6.6090859 | BR51: 5.1422291
A52: Comoros | B52: COM | C52: Inflation, consumer prices (annual %) | D52: FP.CPI.TOTL.ZG | AT52: 5.5545939 | AU52: 3.5330421 | AV52: 3.7990814 | AW52: 4.4749929 | AX52: 3.013324 | AY52: 3.3743636 | AZ52: 4.4661671 | BA52: 1.7007818 | BB52: 4.3623483 | BC52: 3.3547577 | BD52: 1.842663 | BE52: 6.3147445 | BF52: -4.2948733 | BG52: 7.5475538 | BH52: -0.11717388 | BI52: 0.79751743 | BJ52: -0.23736222 | BK52: 2.1515508 | BL52: 3.5821354 | BM52: 0.78664193 | BN52: -0.0044179368 | BO52: 12.532031 | BP52: 8.3737396 | BQ52: 5.0519261 | BR52: 3.2490933
A53: Cabo Verde | B53: CPV | C53: Inflation, consumer prices (annual %) | D53: FP.CPI.TOTL.ZG | AC53: 11.25 | AD53: 5.3932584 | AE53: 10.8742 | AF53: 3.8461538 | AG53: 4.0740741 | AH53: 4.5551601 | AI53: 10.653506 | AJ53: 9.5509074 | AK53: 3.1166643 | AL53: 5.7883959 | AM53: 3.4520583 | AN53: 8.351525 | AO53: 5.9636196 | AP53: 8.5560626 | AQ53: 4.3942351 | AR53: 4.3564337 | AS53: -2.4774567 | AT53: 3.3499647 | AU53: 1.8845341 | AV53: 1.1881704 | AW53: -1.8908217 | AX53: 0.41889161 | AY53: 5.3690769 | AZ53: 4.410997 | BA53: 6.7744355 | BB53: 0.99110348 | BC53: 2.0786647 | BD53: 4.4738834 | BE53: 2.5403964 | BF53: 1.5065429 | BG53: -0.23877814 | BH53: 0.131188 | BI53: -1.4078164 | BJ53: 0.78441525 | BK53: 1.2569957 | BL53: 1.1066667 | BM53: 0.60579581 | BN53: 1.862153 | BO53: 7.9309293 | BP53: 3.7243752 | BQ53: 1.04817 | BR53: 2.343339
A54: Costa Rica | B54: CRI | C54: Inflation, consumer prices (annual %) | D54: FP.CPI.TOTL.ZG | E54: 0.79020582 | F54: 2.4307939 | G54: 2.6778597 | H54: 2.9316185 | I54: 3.3240332 | J54: -0.665 | K54: 0.18288284 | L54: 1.2083403 | M54: 4.0938914 | N54: 2.6293408 | O54: 4.6522975 | P54: 3.0830484 | Q54: 4.6011257 | R54: 15.214034 | S54: 30.073629 | T54: 17.369202 | U54: 3.4858333 | V54: 4.1902405 | W54: 6.0071271 | X54: 9.1884104 | Y54: 18.135171 | Z54: 37.056342 | AA54: 90.121333 | AB54: 32.623708 | AC54: 11.947427 | AD54: 15.05742 | AE54: 11.835062 | AF54: 16.84242 | AG54: 20.832533 | AH54: 16.509809 | AI54: 19.039753 | AJ54: 28.709291 | AK54: 21.791169 | AL54: 9.7786008 | AM54: 13.534469 | AN54: 23.186498 | AO54: 17.511452 | AP54: 13.248044 | AQ54: 11.6593 | AR54: 10.045282 | AS54: 10.96155 | AT54: 11.255616 | AU54: 9.1675205 | AV54: 9.4475809 | AW54: 12.314815 | AX54: 13.798295 | AY54: 11.470597 | AZ54: 9.3572446 | BA54: 13.424464 | BB54: 7.8427017 | BC54: 5.6627571 | BD54: 4.8779983 | BE54: 4.4954531 | BF54: 5.2313361 | BG54: 4.519201 | BH54: 0.80198201 | BI54: -0.017478851 | BJ54: 1.6259069 | BK54: 2.2211146 | BL54: 2.0960464 | BM54: 0.72491148 | BN54: 1.7264776 | BO54: 8.2747749 | BP54: 0.52519351 | BQ54: -0.412853 | BR54: -0.073671441
A55: Caribbean small states | B55: CSS | C55: Inflation, consumer prices (annual %) | D55: FP.CPI.TOTL.ZG | L55: 3.4210271 | M55: 4.9554752 | N55: 5.0255103 | O55: 6.7181549 | P55: 4.1261889 | Q55: 7.3556938 | R55: 13.190707 | S55: 28.122791 | T55: 16.97906 | U55: 10.069538 | V55: 9.617394 | W55: 9.152956 | X55: 14.72217 | Y55: 17.33889 | Z55: 13.001172 | AA55: 7.0336446 | AB55: 4.7039524 | AC55: 3.5358221 | AD55: 3.8275426 | AE55: 1.7601634 | AF55: 3.6681558 | AG55: 3.5694444 | AH55: 5.2788116 | AI55: 4.1392704 | AJ55: 5.5245327 | AK55: 5.3053617 | AL55: 2.2588796 | AM55: 2.0058063 | AN55: 2.8896158 | AO55: 2.0865739 | AP55: 2.4362972 | AQ55: 2.1952625 | AR55: 2.0907288 | AS55: 2.3088156 | AT55: 2.602624 | AU55: 2.1073345 | AV55: 2.1951824 | AW55: 2.3543322 | AX55: 3.6046181 | AY55: 3.4963142 | AZ55: 3.9465295 | BA55: 7.2138521 | BB55: 0.21390135 | BC55: 3.3101847 | BD55: 3.3277655 | BE55: 2.5046106 | BF55: 1.0832417 | BG55: 1.1454206 | BH55: -0.8527055 | BI55: 0.4026217 | BJ55: 1.6992957 | BK55: 1.2071579 | BL55: 1.0005429 | BM55: 0.12143464 | BN55: 2.2289133 | BO55: 5.8283864 | BP55: 4.1044928 | BQ55: 2.7362075 | BR55: 1.1087978
A56: Cuba | B56: CUB | C56: Inflation, consumer prices (annual %) | D56: FP.CPI.TOTL.ZG
A57: Curacao | B57: CUW | C57: Inflation, consumer prices (annual %) | D57: FP.CPI.TOTL.ZG | AT57: 1.7928287 | AU57: 0.39138943 | AV57: 1.6337139 | AW57: 1.3791214 | AX57: 4.1171171 | AY57: 3.1149952 | AZ57: 2.9957204 | BA57: 6.8763239 | BB57: 1.7533161 | BC57: 2.7794426 | BD57: 2.3325315 | BE57: 3.1839875 | BF57: 1.3323209 | BG57: 1.4987397 | BH57: -0.47654205 | BI57: -0.047207985 | BJ57: 1.585588 | BK57: 2.5836876 | BL57: 2.6222078
A58: Cayman Islands | B58: CYM | C58: Inflation, consumer prices (annual %) | D58: FP.CPI.TOTL.ZG | BC58: 0.27614086 | BD58: 1.3254358 | BE58: 1.1889485 | BF58: 2.1606115 | BG58: 1.2739791 | BH58: -2.3475277 | BI58: -0.62525836
A59: Cyprus | B59: CYP | C59: Inflation, consumer prices (annual %) | D59: FP.CPI.TOTL.ZG | E59: 0.82730093 | F59: -0.61538462 | G59: 0.10319917 | H59: 1.9587629 | I59: -0.3033367 | J59: 0.20283976 | K59: 0.50607287 | L59: 0.70493454 | M59: 3.7666667 | N59: 2.385159 | O59: 2.4001883 | P59: 4.1440061 | Q59: 4.8323036 | R59: 7.8088823 | S59: 16.176667 | T59: 4.6394858 | U59: 3.8543897 | V59: 7.3264605 | W59: 7.4362833 | X59: 9.4637083 | Y59: 13.517561 | Z59: 10.744694 | AA59: 6.4327973 | AB59: 5.0497142 | AC59: 5.9919511 | AD59: 5.0344537 | AE59: 1.2183693 | AF59: 2.7916667 | AG59: 3.4292663 | AH59: 3.7654805 | AI59: 4.5020546 | AJ59: 5.0352744 | AK59: 6.5102195 | AL59: 4.8541667 | AM59: 4.6985893 | AN59: 2.6158179 | AO59: 2.9789249 | AP59: 3.6053444 | AQ59: 2.2277073 | AR59: 1.63 | AS59: 4.1416576 | AT59: 1.9730419 | AU59: 2.8011551 | AV59: 4.1390654 | AW59: 2.2862171 | AX59: 2.5601613 | AY59: 2.3046873 | AZ59: 2.3726518 | BA59: 4.6690084 | BB59: 0.32627665 | BC59: 2.4300408 | BD59: 3.2894494 | BE59: 2.3890541 | BF59: -0.39935768 | BG59: -1.3549889 | BH59: -2.0969977 | BI59: -1.4291667 | BJ59: 0.5317665 | BK59: 1.4354912 | BL59: 0.250371 | BM59: -0.6384228 | BN59: 2.4460887 | BO59: 8.395483 | BP59: 3.5413419 | BQ59: 1.8002302 | BR59: 0.12652885
A60: Czechia | B60: CZE | C60: Inflation, consumer prices (annual %) | D60: FP.CPI.TOTL.ZG | AK60: 11.0865 | AL60: 20.81303 | AM60: 10.03943 | AN60: 8.9905236 | AO60: 8.7587747 | AP60: 8.5961567 | AQ60: 10.698366 | AR60: 2.1354484 | AS60: 3.7753883 | AT60: 4.6626756 | AU60: 1.902981 | AV60: 0.11873921 | AW60: 2.7601078 | AX60: 1.8570979 | AY60: 2.5339926 | AZ60: 2.8531244 | BA60: 6.3586638 | BB60: 1.0193774 | BC60: 1.4727273 | BD60: 1.9172191 | BE60: 3.2876231 | BF60: 1.4382979 | BG60: 0.34398859 | BH60: 0.30936455 | BI60: 0.68350421 | BJ60: 2.450534 | BK60: 2.1494949 | BL60: 2.847876 | BM60: 3.1612953 | BN60: 3.8398449 | BO60: 15.100165 | BP60: 10.66126 | BQ60: 2.435312 | BR60: 2.4599637
A61: Germany | B61: DEU | C61: Inflation, consumer prices (annual %) | D61: FP.CPI.TOTL.ZG | E61: 1.5366123 | F61: 2.293695 | G61: 2.8432702 | H61: 2.9669598 | I61: 2.3357358 | J61: 3.2423192 | K61: 3.5330604 | L61: 1.7960499 | M61: 1.4702893 | N61: 1.9126785 | O61: 3.4502494 | P61: 5.2409745 | Q61: 5.4849331 | R61: 7.032024 | S61: 6.9864311 | T61: 5.9103363 | U61: 4.246631 | V61: 3.7341624 | W61: 2.718697 | X61: 4.0436201 | Y61: 5.4410575 | Z61: 6.3442428 | AA61: 5.2410451 | AB61: 3.2934147 | AC61: 2.4057934 | AD61: 2.066233 | AE61: -0.12941336 | AF61: 0.24990611 | AG61: 1.2741189 | AH61: 2.7805696 | AI61: 2.6964682 | AJ61: 4.0470326 | AK61: 5.056978 | AL61: 4.4745765 | AM61: 2.6930564 | AN61: 1.7061604 | AO61: 1.449727 | AP61: 1.939372 | AQ61: 0.91118354 | AR61: 0.58543306 | AS61: 1.4402684 | AT61: 1.9838573 | AU61: 1.4208062 | AV61: 1.0342222 | AW61: 1.665737 | AX61: 1.5469111 | AY61: 1.5774264 | AZ61: 2.298344 | BA61: 2.6283798 | BB61: 0.31273901 | BC61: 1.1038104 | BD61: 2.0751728 | BE61: 2.0084888 | BF61: 1.5047233 | BG61: 0.906794 | BH61: 0.51442614 | BI61: 0.49174701 | BJ61: 1.5094949 | BK61: 1.7321688 | BL61: 1.4456598 | BM61: 0.14487793 | BN61: 3.0666667 | BO61: 6.8725744 | BP61: 5.9464367 | BQ61: 2.2564981 | BR61: 2.1717877
A62: Djibouti | B62: DJI | C62: Inflation, consumer prices (annual %) | D62: FP.CPI.TOTL.ZG | Y62: 12.058024 | Z62: 5.7173679 | AA62: -2.4107143 | AB62: 0.9018429 | AC62: 1.884715 | AD62: 2.128903 | AE62: 18.147633 | AF62: 4.0891164 | AT62: 1.7466522 | AU62: 0.63761955 | AV62: 1.9819673 | AW62: 3.122262 | AX62: 3.1049664 | AY62: 3.483407 | AZ62: 4.9659765 | BA62: 11.958621 | BB62: 1.6754959 | BC62: 3.9500788 | BD62: 5.0687139 | BE62: 3.7312095 | BF62: -12.563149 | BG62: 1.3418649 | BH62: -0.52216652 | BI62: 2.4025291 | BJ62: 0.57728572 | BK62: 0.1388364 | BL62: 3.317632 | BM62: 1.7790054 | BN62: 1.1808678 | BO62: 5.1722209 | BP62: 1.4490509 | BQ62: 2.1120117 | BR62: -0.3137318
A63: Dominica | B63: DMA | C63: Inflation, consumer prices (annual %) | D63: FP.CPI.TOTL.ZG | L63: 0.95245654 | M63: 5.369919 | N63: 4.2157887 | O63: 12.393499 | P63: 3.637406 | Q63: 3.6879956 | R63: 12.099117 | S63: 34.376074 | T63: 19.902788 | U63: 10.902496 | V63: 9.5036553 | W63: 7.7125791 | Z63: 13.266687 | AA63: 4.3945941 | AB63: 4.1479524 | AC63: 2.2179942 | AD63: 3.73998 | AE63: 2.7742337 | AF63: 4.0245804 | AG63: 2.9245916 | AH63: 6.2185215 | AI63: 3.1909232 | AJ63: 5.5570615 | AK63: 5.4718256 | AL63: 1.569026 | AM63: 0.015136735 | AN63: 1.3175375 | AO63: 1.6771645 | AP63: 2.4362972 | AQ63: 0.99914746 | AR63: 1.1794779 | AS63: 0.85694681 | AT63: 1.303894 | AU63: 0.17005533 | AV63: 1.453368 | AW63: 2.3941098 | AX63: 1.6819008 | AY63: 2.2023913 | AZ63: 3.6322213 | BA63: 6.3599218 | BB63: 0.0062635711 | BC63: 2.9993663 | BD63: 1.1312314 | BE63: 1.3567715 | BF63: -0.046411647 | BG63: 0.79925037 | BH63: -0.84382698 | BI63: 0.14181623 | BJ63: 0.29625289 | BK63: 0.98919112 | BL63: 1.5046235 | BM63: 1.2202644 | BN63: 2.2289133 | BO63: 2.8849023 | BP63: 5.0867748 | BQ63: 2.7362075 | BR63: 2.5338513
A64: Denmark | B64: DNK | C64: Inflation, consumer prices (annual %) | D64: FP.CPI.TOTL.ZG | E64: 1.2552301 | F64: 3.4516286 | G64: 7.3778195 | H64: 6.1050328 | I64: 3.0927835 | J64: 5.45 | K64: 7.0649597 | L64: 8.2078536 | M64: 8.0051689 | N64: 3.4879471 | O64: 6.5148416 | P64: 5.8698783 | Q64: 6.5623513 | R64: 9.3033737 | S64: 15.275196 | T64: 9.6056204 | U64: 9.0102945 | V64: 10.922253 | W64: 10.21364 | X64: 9.6110557 | Y64: 12.30532 | Z64: 11.76739 | AA64: 10.12082 | AB64: 6.9082297 | AC64: 6.290785 | AD64: 4.6787436 | AE64: 3.678186 | AF64: 4.0199908 | AG64: 4.535136 | AH64: 4.7727276 | AI64: 2.6415988 | AJ64: 2.3951536 | AK64: 2.0960428 | AL64: 1.2578636 | AM64: 1.9920125 | AN64: 2.083604 | AO64: 2.1263002 | AP64: 2.1821677 | AQ64: 1.8456485 | AR64: 2.4977966 | AS64: 2.9032795 | AT64: 2.3846785 | AU64: 2.4347984 | AV64: 2.0777581 | AW64: 1.1661267 | AX64: 1.8090919 | AY64: 1.8922067 | AZ64: 1.712131 | BA64: 3.4094859 | BB64: 1.3208456 | BC64: 2.3042901 | BD64: 2.7506377 | BE64: 2.415088 | BF64: 0.77748678 | BG64: 0.55441185 | BH64: 0.46520585 | BI64: 0.25725095 | BJ64: 1.1370497 | BK64: 0.82479355 | BL64: 0.74009019 | BM64: 0.42316018 | BN64: 1.8396231 | BO64: 7.7006331 | BP64: 3.3117824 | BQ64: 1.3798624 | BR64: 1.8900606
A65: Dominican Republic | B65: DOM | C65: Inflation, consumer prices (annual %) | D65: FP.CPI.TOTL.ZG | E65: -3.5621918 | F65: -3.9 | G65: 9.157128 | H65: 8.5795996 | I65: 2.1071115 | J65: -1.8916595 | K65: 0.26292726 | L65: 1.238345 | M65: 0.035976399 | N65: 0.95662807 | O65: 3.8166667 | P65: 3.5800289 | Q65: 8.6407316 | R65: 15.079535 | S65: 13.140767 | T65: 14.501726 | U65: 7.7655502 | V65: 12.853528 | W65: 3.4778503 | X65: 9.1738051 | Y65: 16.753136 | Z65: 7.5146389 | AA65: 7.6462431 | AB65: 5.6286233 | AC65: 20.151678 | AD65: 45.336176 | AE65: 7.6389727 | AF65: 13.550724 | AG65: 43.863832 | AH65: 40.657916 | AI65: 50.462479 | AJ65: 47.079157 | AK65: 4.2590264 | AL65: 5.2503388 | AM65: 8.260768 | AN65: 12.535959 | AO65: 5.3992939 | AP65: 8.2965675 | AQ65: 4.8316656 | AR65: 6.4705419 | AS65: 7.7241357 | AT65: 8.8830685 | AU65: 5.2233677 | AV65: 27.449713 | AW65: 51.46086 | AX65: 4.1902026 | AY65: 7.5728052 | AZ65: 6.1435666 | BA65: 10.644621 | BB65: 1.4421513 | BC65: 6.3299322 | BD65: 5.7967681 | BE65: 3.6944971 | BF65: 4.830951 | BG65: 2.9986423 | BH65: 0.83674635 | BI65: 1.6141661 | BJ65: 3.2795569 | BK65: 3.5644343 | BL65: 1.8106038 | BM65: 3.7810318 | BN65: 8.2430035 | BO65: 8.8110921 | BP65: 4.7856128 | BQ65: 3.3022334 | BR65: 3.8731177
A66: Algeria | B66: DZA | C66: Inflation, consumer prices (annual %) | D66: FP.CPI.TOTL.ZG | O66: 6.6 | P66: 2.6266417 | Q66: 3.6563071 | R66: 6.1728395 | S66: 4.6996124 | T66: 8.2303167 | U66: 9.4307354 | V66: 11.989283 | W66: 17.523923 | X66: 11.348601 | Y66: 9.5178245 | Z66: 14.654843 | AA66: 6.5425096 | AB66: 5.9671639 | AC66: 8.116398 | AD66: 10.482287 | AE66: 12.371609 | AF66: 7.4412609 | AG66: 5.911545 | AH66: 9.3043613 | AI66: 16.652534 | AJ66: 25.886387 | AK66: 31.669662 | AL66: 20.540326 | AM66: 29.047656 | AN66: 29.779626 | AO66: 18.679076 | AP66: 5.7335228 | AQ66: 4.9501616 | AR66: 2.6455111 | AS66: 0.33916319 | AT66: 4.2259883 | AU66: 1.4183019 | AV66: 4.268954 | AW66: 3.9618003 | AX66: 1.3824466 | AY66: 2.3114992 | AZ66: 3.6789957 | BA66: 4.8585906 | BB66: 5.7370604 | BC66: 3.911062 | BD66: 4.5242115 | BE66: 8.8914509 | BF66: 3.2542391 | BG66: 2.9169269 | BH66: 4.784447 | BI66: 6.3976948 | BJ66: 5.5911159 | BK66: 4.2699902 | BL66: 1.9517682 | BM66: 2.4151309 | BN66: 7.2260631 | BO66: 9.2655155 | BP66: 9.3221738 | BQ66: 4.0461146 | BR66: 1.4183515
A67: East Asia & Pacific (excluding high income) | B67: EAP | C67: Inflation, consumer prices (annual %) | D67: FP.CPI.TOTL.ZG | V67: 7.6012669 | W67: 6.263048 | X67: 7.8067582 | Y67: 14.492874 | Z67: 12.662993 | AA67: 7.0315569 | AB67: 6.704184 | AC67: 5.5164001 | AD67: 4.7245352 | AE67: 5.4537522 | AF67: 5.1748813 | AG67: 9.3421269 | AH67: 6.4625617 | AI67: 8.1913713 | AJ67: 6.9656813 | AK67: 7.5235101 | AL67: 5.7369058 | AM67: 7.6582395 | AN67: 5.8181818 | AO67: 7.3134826 | AP67: 5.6080284 | AQ67: 8.6148315 | AR67: 4.2907285 | AS67: 2.1585181 | AT67: 4.2726702 | AU67: 2.7227723 | AV67: 3.703698 | AW67: 4.4267753 | AX67: 5.5286116 | AY67: 4.8663205 | AZ67: 4.8167677 | BA67: 10.226666 | BB67: 4.2190305 | BC67: 3.6890123 | BD67: 5.2957322 | BE67: 3.0269639 | BF67: 2.9135419 | BG67: 3.1429905 | BH67: 1.223932 | BI67: 1.9173109 | BJ67: 2.9126356 | BK67: 3.1983476 | BL67: 1.942575 | BM67: 2.4062921 | BN67: 2.6989186 | BO67: 5.6696437 | BP67: 5.885859 | BQ67: 2.1815127 | BR67: 2.2119621
A68: Early-demographic dividend | B68: EAR | C68: Inflation, consumer prices (annual %) | D68: FP.CPI.TOTL.ZG | K68: 4.4798107 | L68: 1.9777415 | M68: 2.0792219 | N68: 2.9751392 | O68: 3.8126649 | P68: 4.1952984 | Q68: 6.075 | R68: 12.081933 | S68: 19.070473 | T68: 12.879182 | U68: 10.122084 | V68: 12.156932 | W68: 9.3141837 | X68: 11.542416 | Y68: 14.684503 | Z68: 12.413261 | AA68: 10.221727 | AB68: 10.243663 | AC68: 8.4973714 | AD68: 9.3533308 | AE68: 10.001716 | AF68: 9.7530031 | AG68: 8.9830034 | AH68: 9.0756241 | AI68: 11.906055 | AJ68: 15.050131 | AK68: 10.527444 | AL68: 9.9736648 | AM68: 9.5932496 | AN68: 10.022173 | AO68: 8.519952 | AP68: 7.018286 | AQ68: 6.4207324 | AR68: 5.0234435 | AS68: 3.8995298 | AT68: 3.7508206 | AU68: 4.2402666 | AV68: 5.4529322 | AW68: 4.4352611 | AX68: 4.8217005 | AY68: 5.6871377 | AZ68: 6.1778121 | BA68: 10.446988 | BB68: 4.3737677 | BC68: 4.3974138 | BD68: 5.8114922 | BE68: 5.0182725 | BF68: 4.8277871 | BG68: 4.0739296 | BH68: 3.1290027 | BI68: 3.5231732 | BJ68: 3.4653254 | BK68: 3.9572183 | BL68: 2.7676923 | BM68: 3.0751605 | BN68: 4.1939094 | BO68: 7.1192444 | BP68: 5.8828968 | BQ68: 3.2958966 | BR68: 3.3646219
A69: East Asia & Pacific | B69: EAS | C69: Inflation, consumer prices (annual %) | D69: FP.CPI.TOTL.ZG | AF69: 4.6859878 | AG69: 7.8873239 | AH69: 6.4155408 | AI69: 7.8191976 | AJ69: 6.4973456 | AK69: 6.2132815 | AL69: 4.8875555 | AM69: 5.6499089 | AN69: 4.6277645 | AO69: 5.5248099 | AP69: 3.7276576 | AQ69: 5.4910118 | AR69: 1.9838243 | AS69: 1.5919692 | AT69: 3.5775545 | AU69: 1.88572 | AV69: 2.2891566 | AW69: 3.2375139 | AX69: 3.0370233 | AY69: 3.9361626 | AZ69: 3.7640026 | BA69: 8.3420863 | BB69: 1.6217317 | BC69: 3.0573056 | BD69: 5.0214601 | BE69: 2.9719011 | BF69: 2.5826877 | BG69: 2.5108763 | BH69: 0.79527963 | BI69: 1.2769937 | BJ69: 1.8003422 | BK69: 2.3685491 | BL69: 1.714371 | BM69: 0.84690073 | BN69: 2.4771024 | BO69: 5.5181293 | BP69: 4.2515551 | BQ69: 2.2767355 | BR69: 2.0182143
A70: Europe & Central Asia (excluding high income) | B70: ECA | C70: Inflation, consumer prices (annual %) | D70: FP.CPI.TOTL.ZG | AM70: 891.18775 | AN70: 162.71715 | AO70: 35.56494 | AP70: 16.67432 | AQ70: 9.5649345 | AR70: 20.938174 | AS70: 15.940812 | AT70: 8.3541378 | AU70: 5.5878373 | AV70: 4.9506156 | AW70: 6.9216579 | AX70: 7.8816196 | AY70: 7.6630269 | AZ70: 8.5914693 | BA70: 11.427557 | BB70: 3.4367453 | BC70: 6.7777467 | BD70: 7.8583333 | BE70: 3.3160557 | BF70: 4.597879 | BG70: 3.0688121 | BH70: 4.0276857 | BI70: 2.1349271 | BJ70: 6.0318373 | BK70: 2.6112165 | BL70: 2.675992 | BM70: 2.7598095 | BN70: 7.1848363 | BO70: 13.852259 | BP70: 8.7854305 | BQ70: 3.4897409 | BR70: 4.0724918
A71: Europe & Central Asia | B71: ECS | C71: Inflation, consumer prices (annual %) | D71: FP.CPI.TOTL.ZG | AK71: 5.9245414 | AL71: 14.411264 | AM71: 12.144798 | AN71: 8.9625189 | AO71: 8.1945522 | AP71: 5.5360027 | AQ71: 4.6442142 | AR71: 2.3648184 | AS71: 3.7753883 | AT71: 4.2628716 | AU71: 2.7861599 | AV71: 2.3486417 | AW71: 2.829478 | AX71: 2.6092997 | AY71: 3.1928864 | AZ71: 2.9159826 | BA71: 6.0597405 | BB71: 1.5360765 | BC71: 2.4214547 | BD71: 3.8561124 | BE71: 2.7733385 | BF71: 1.7340396 | BG71: 0.62049064 | BH71: 0.36804684 | BI71: 0.38857707 | BJ71: 1.9557573 | BK71: 2.0280596 | BL71: 1.7841312 | BM71: 1.2000735 | BN71: 3.2307491 | BO71: 10.780581 | BP71: 6.7939671 | BQ71: 2.7740699 | BR71: 3.7457732
A72: Ecuador | B72: ECU | C72: Inflation, consumer prices (annual %) | D72: FP.CPI.TOTL.ZG | E72: 1.6765991 | F72: 3.9856205 | G72: 2.8708853 | H72: 5.9395091 | I72: 4.0342045 | J72: 3.0690707 | K72: 5.4537269 | L72: 3.8181382 | M72: 4.3176561 | N72: 6.3266814 | O72: 5.1712761 | P72: 9.5216708 | Q72: 7.5251179 | R72: 12.128146 | S72: 22.704082 | T72: 14.289674 | U72: 10.17463 | V72: 12.944414 | W72: 13.098139 | X72: 10.117191 | Y72: 11.909289 | Z72: 14.047969 | AA72: 16.284488 | AB72: 48.418222 | AC72: 31.219582 | AD72: 27.993611 | AE72: 23.030226 | AF72: 29.503997 | AG72: 58.216287 | AH72: 75.64819 | AI72: 48.519113 | AJ72: 48.718081 | AK72: 54.607822 | AL72: 44.955054 | AM72: 27.310882 | AN72: 22.934134 | AO72: 24.411459 | AP72: 30.657568 | AQ72: 36.098433 | AR72: 52.242005 | AS72: 96.096376 | AT72: 37.676745 | AU72: 12.483598 | AV72: 7.9293649 | AW72: 2.743232 | AX72: 2.168277 | AY72: 3.2987485 | AZ72: 2.2761848 | BA72: 8.4000959 | BB72: 5.1599683 | BC72: 3.5543773 | BD72: 4.4745327 | BE72: 5.1017218 | BF72: 2.7217758 | BG72: 3.5892202 | BH72: 3.9666462 | BI72: 1.7282646 | BJ72: 0.41733559 | BK72: -0.22410325 | BL72: 0.26601252 | BM72: -0.33887239 | BN72: 0.13325139 | BO72: 3.4661697 | BP72: 2.2156876 | BQ72: 1.5473252 | BR72: 0.71046932
A73: Egypt, Arab Rep. | B73: EGY | C73: Inflation, consumer prices (annual %) | D73: FP.CPI.TOTL.ZG | E73: 0.33282905 | F73: 0.69360675 | G73: -3.0030766 | H73: 0.74664571 | I73: 3.6609829 | J73: 14.839004 | K73: 9.0364407 | L73: 0.70189748 | M73: -1.6757594 | N73: 3.4098203 | O73: 3.7628986 | P73: 3.1404217 | Q73: 2.1023633 | R73: 5.112184 | S73: 10.024318 | T73: 9.6696955 | U73: 10.317416 | V73: 12.732163 | W73: 11.0781 | X73: 9.9043605 | Y73: 20.819225 | Z73: 10.317284 | AA73: 14.823009 | AB73: 16.079874 | AC73: 17.036366 | AD73: 12.106756 | AE73: 23.86429 | AF73: 19.693593 | AG73: 17.663486 | AH73: 21.261867 | AI73: 16.756375 | AJ73: 19.748545 | AK73: 13.637424 | AL73: 12.089792 | AM73: 8.1542313 | AN73: 15.742231 | AO73: 7.1871037 | AP73: 4.6256058 | AQ73: 3.8725755 | AR73: 3.0794991 | AS73: 2.6838054 | AT73: 2.2697572 | AU73: 2.7372386 | AV73: 4.5077764 | AW73: 11.270619 | AX73: 4.869397 | AY73: 7.6445264 | AZ73: 9.3189691 | BA73: 18.316832 | BB73: 11.763495 | BC73: 11.265188 | BD73: 10.064926 | BE73: 7.1117294 | BF73: 9.4697198 | BG73: 10.070215 | BH73: 10.37049 | BI73: 13.813606 | BJ73: 29.506608 | BK73: 14.401466 | BL73: 9.1527996 | BM73: 5.0449329 | BN73: 5.2140494 | BO73: 13.895661 | BP73: 33.884776 | BQ73: 28.27059 | BR73: 14.073514
A74: Euro area | B74: EMU | C74: Inflation, consumer prices (annual %) | D74: FP.CPI.TOTL.ZG | E74: 1.7411808 | F74: 1.8708429 | G74: 2.7526672 | H74: 2.9216411 | I74: 3.656731 | J74: 3.6664741 | K74: 3.4323701 | L74: 2.9875524 | M74: 3.242829 | N74: 2.6480854 | O74: 4.1406563 | P74: 5.0163205 | Q74: 5.9062514 | R74: 7.9155433 | S74: 14.66485 | T74: 12.227066 | U74: 9.7114204 | V74: 9.7674657 | W74: 7.5737058 | X74: 8.4653324 | Y74: 13.54007 | Z74: 11.509756 | AA74: 9.5849373 | AB74: 8.6692716 | AC74: 7.0676548 | AD74: 5.1956185 | AE74: 2.7 | AF74: 3.1594048 | AG74: 2.7008198 | AH74: 4.0890478 | AI74: 4.5020546 | AJ74: 4.310215 | AK74: 5.5975644 | AL74: 4.6267314 | AM74: 4.6985893 | AN74: 4.2228161 | AO74: 3.0689773 | AP74: 2.336863 | AQ74: 2.3852514 | AR74: 2.1347689 | AS74: 3.0420956 | AT74: 2.9294924 | AU74: 2.4653202 | AV74: 2.0987023 | AW74: 2.2256792 | AX74: 2.5601613 | AY74: 2.7737801 | AZ74: 2.5106683 | BA74: 4.1527971 | BB74: 0.50630883 | BC74: 1.5255152 | BD74: 3.2894494 | BE74: 2.5973732 | BF74: 1.2199948 | BG74: 0.19810126 | BH74: -0.10463326 | BI74: 0.14880952 | BJ74: 1.3796879 | BK74: 1.7036188 | BL74: 1.4456598 | BM74: 0.2190649 | BN74: 2.5269201 | BO74: 8.5468699 | BP74: 5.9464367 | BQ74: 2.2564981 | BR74: 2.4660576
A75: Eritrea | B75: ERI | C75: Inflation, consumer prices (annual %) | D75: FP.CPI.TOTL.ZG
A76: Spain | B76: ESP | C76: Inflation, consumer prices (annual %) | D76: FP.CPI.TOTL.ZG | E76: 1.1777563 | F76: 0.80926149 | G76: 5.7064864 | H76: 8.743692 | I76: 6.979249 | J76: 13.214145 | K76: 6.240356 | L76: 6.3916328 | M76: 4.9543673 | N76: 2.1603403 | O76: 5.7311549 | P76: 8.2368841 | Q76: 8.2722912 | R76: 11.416704 | S76: 15.680375 | T76: 16.953285 | U76: 17.62488 | V76: 24.538059 | W76: 19.773667 | X76: 15.660237 | Y76: 15.561908 | Z76: 14.549359 | AA76: 14.414987 | AB76: 12.174083 | AC76: 11.280268 | AD76: 8.8144577 | AE76: 8.7949369 | AF76: 5.2480231 | AG76: 4.8372643 | AH76: 6.7914354 | AI76: 6.721824 | AJ76: 5.9342091 | AK76: 5.9245414 | AL76: 4.5690668 | AM76: 4.7184126 | AN76: 4.6738042 | AO76: 3.5588447 | AP76: 1.9710718 | AQ76: 1.8343379 | AR76: 2.3103434 | AS76: 3.4335166 | AT76: 3.5898337 | AU76: 3.0654561 | AV76: 3.0391361 | AW76: 3.0394838 | AX76: 3.3683143 | AY76: 3.5158103 | AZ76: 2.7865918 | BA76: 4.0756625 | BB76: -0.28793363 | BC76: 1.7998277 | BD76: 3.1960943 | BE76: 2.4459574 | BF76: 1.408716 | BG76: -0.15092122 | BH76: -0.50032742 | BI76: -0.2027219 | BJ76: 1.9557573 | BK76: 1.6753982 | BL76: 0.69926714 | BM76: -0.32256462 | BN76: 3.0930499 | BO76: 8.3904194 | BP76: 3.5324729 | BQ76: 2.7740699 | BR76: 2.6732674
A77: Estonia | B77: EST | C77: Inflation, consumer prices (annual %) | D77: FP.CPI.TOTL.ZG | AL77: 89.811949 | AM77: 47.654691 | AN77: 28.776614 | AO77: 23.050343 | AP77: 10.581879 | AQ77: 8.2083333 | AR77: 3.3073928 | AS77: 4.008555 | AT77: 5.753643 | AU77: 3.5634554 | AV77: 1.3384981 | AW77: 3.0480288 | AX77: 4.08947 | AY77: 4.4304392 | AZ77: 6.5970925 | BA77: 10.366948 | BB77: -0.085756359 | BC77: 2.9773188 | BD77: 4.9763291 | BE77: 3.9354767 | BF77: 2.788053 | BG77: -0.11067152 | BH77: -0.49036822 | BI77: 0.14880952 | BJ77: 3.4145898 | BK77: 3.4325743 | BL77: 2.2878721 | BM77: -0.4475816 | BN77: 4.6497464 | BO77: 19.401477 | BP77: 9.1529323 | BQ77: 3.5224647 | BR77: 4.8289458
A78: Ethiopia | B78: ETH | C78: Inflation, consumer prices (annual %) | D78: FP.CPI.TOTL.ZG | K78: -1.3618677 | L78: 0.8086785 | M78: 0.18261267 | N78: 1.4256884 | O78: 10.121951 | P78: 0.53622428 | Q78: -6.081512 | R78: 8.9135802 | S78: 8.592156 | T78: 6.5501044 | U78: 28.53784 | V78: 16.65714 | W78: 14.308114 | X78: 16.032236 | Y78: 4.4825378 | Z78: 6.1359672 | AA78: 5.8900611 | AB78: -0.67537806 | AC78: 8.4172738 | AD78: 19.064685 | AE78: -9.8087651 | AF78: -2.4286725 | AG78: 7.0807153 | AH78: 7.8173012 | AI78: 5.1524812 | AJ78: 35.722598 | AK78: 10.527444 | AL78: 3.543066 | AM78: 7.593876 | AN78: 10.022173 | AO78: -8.4842487 | AP78: 2.3952096 | AQ78: 0.89480169 | AR78: 7.9414486 | AS78: 0.66245811 | AT78: -8.2378445 | AU78: 0.6750891 | AV78: 13.674045 | AW78: 3.3273705 | AX78: 9.9699712 | AY78: 12.299476 | AZ78: 17.240401 | BA78: 44.356686 | BB78: 8.483644 | BC78: 8.149264 | BD78: 33.24996 | BE78: 23.600418 | BF78: 7.4640219 | BG78: 6.8900195 | BH78: 9.5688996 | BI78: 6.6281334 | BJ78: 10.687115 | BK78: 13.833036 | BL78: 15.809632 | BM78: 20.356347 | BN78: 26.839522 | BO78: 33.88988 | BP78: 30.218828 | BQ78: 21.037746 | BR78: 13.229643
A79: European Union | B79: EUU | C79: Inflation, consumer prices (annual %) | D79: FP.CPI.TOTL.ZG | E79: 1.7411808 | F79: 2.0771324 | G79: 3.5534987 | H79: 2.9216411 | I79: 3.4162809 | J79: 3.9866148 | K79: 3.7033587 | L79: 3.3193346 | M79: 3.242829 | N79: 2.6746198 | O79: 4.5060889 | P79: 5.2409745 | Q79: 6.0073993 | R79: 7.7490861 | S79: 13.163609 | T79: 10.467572 | U79: 9.3470509 | V79: 9.7674657 | W79: 7.7552421 | X79: 8.2216844 | Y79: 12.91144 | Z79: 11.76739 | AA79: 9.5849373 | AB79: 8.6692716 | AC79: 7.6738045 | AD79: 5.3954922 | AE79: 3.678186 | AF79: 4.0199908 | AG79: 4.535136 | AH79: 6.2598439 | AI79: 6.1495583 | AJ79: 5.4847417 | AK79: 6.2173804 | AL79: 4.8541667 | AM79: 4.7184126 | AN79: 4.4266455 | AO79: 3.5588447 | AP79: 3.1120779 | AQ79: 2.4076809 | AR79: 2.1571779 | AS79: 3.1507671 | AT79: 3.3739683 | AU79: 2.4347984 | AV79: 2.0919946 | AW79: 2.2862171 | AX79: 2.4876967 | AY79: 2.6663149 | AZ79: 2.5106683 | BA79: 4.1649719 | BB79: 0.84221219 | BC79: 1.5331756 | BD79: 3.2894494 | BE79: 2.6628417 | BF79: 1.2199948 | BG79: 0.19810126 | BH79: -0.06164088 | BI79: 0.18444978 | BJ79: 1.4267707 | BK79: 1.7366803 | BL79: 1.6343724 | BM79: 0.47770085 | BN79: 2.554507 | BO79: 8.8334622 | BP79: 6.2994249 | BQ79: 2.435312 | BR79: 2.4660576
A80: Fragility, Conflict, and Violence (FCV) situations | B80: FCV | C80: Inflation, consumer prices (annual %) | D80: FP.CPI.TOTL.ZG | K80: 6.0476088 | L80: 1.2154717 | M80: 0.54079598 | N80: 5.7392537 | O80: 4.0277957 | P80: 4.0140296 | Q80: 5.6304752 | R80: 10.102118 | S80: 14.599816 | T80: 13.216256 | U80: 11.342357 | V80: 14.893072 | W80: 10.907585 | X80: 10.487237 | Y80: 12.064343 | Z80: 11.029028 | AA80: 11.8508 | AB80: 10.424433 | AC80: 8.823396 | AD80: 8.8234074 | AE80: 5.5854518 | AF80: 7.8230197 | AG80: 6.5838359 | AH80: 6.923905 | AI80: 7.3644003 | AJ80: 13.006973 | AK80: 11.009174 | AL80: 17.212886 | AM80: 33.270745 | AN80: 22.192058 | AO80: 9.9370342 | AP80: 4.7862388 | AQ80: 5.5796451 | AR80: 6.6183734 | AS80: 3.2034009 | AT80: 5.1870119 | AU80: 5.7095159 | AV80: 6.4894321 | AW80: 3.994384 | AX80: 8.5058508 | AY80: 8.2274368 | AZ80: 6.2509878 | BA80: 14.297122 | BB80: 3.0436185 | BC80: 4.3974138 | BD80: 6.3327948 | BE80: 6.0598039 | BF80: 4.765024 | BG80: 3.4381666 | BH80: 4.7733587 | BI80: 6.6509311 | BJ80: 5.4220457 | BK80: 4.3744892 | BL80: 3.0053895 | BM80: 3.4839357 | BN80: 6.0418649 | BO80: 10.279402 | BP80: 5.1147276 | BQ80: 5.5176491 | BR80: 4.3949416
A81: Finland | B81: FIN | C81: Inflation, consumer prices (annual %) | D81: FP.CPI.TOTL.ZG | E81: 3.4181268 | F81: 1.6910002 | G81: 4.383983 | H81: 4.9963809 | I81: 10.27586 | J81: 4.9405878 | K81: 3.8736571 | L81: 5.3777845 | M81: 9.1916642 | N81: 2.2056015 | O81: 2.7404419 | P81: 6.4757671 | Q81: 6.662472 | R81: 10.754482 | S81: 16.936399 | T81: 17.811403 | U81: 14.34268 | V81: 11.793354 | W81: 7.799356 | X81: 7.4669564 | Y81: 11.594614 | Z81: 11.305757 | AA81: 9.5849373 | AB81: 8.3662914 | AC81: 7.0676548 | AD81: 5.1956185 | AE81: 2.9335798 | AF81: 4.1130303 | AG81: 5.0859331 | AH81: 6.5929092 | AI81: 6.1495583 | AJ81: 4.310215 | AK81: 2.9193267 | AL81: 2.1906518 | AM81: 1.0885599 | AN81: 0.79123355 | AO81: 0.62919966 | AP81: 1.1925574 | AQ81: 1.3994724 | AR81: 1.1622379 | AS81: 3.0420956 | AT81: 2.5784421 | AU81: 1.5712186 | AV81: 0.87743886 | AW81: 0.18712 | AX81: 0.62387262 | AY81: 1.5666652 | AZ81: 2.5106683 | BA81: 4.0659515 | BB81: -1.1260725e-06 | BC81: 1.1841373 | BD81: 3.4168071 | BE81: 2.8083328 | BF81: 1.4782888 | BG81: 1.0412009 | BH81: -0.21884621 | BI81: 0.36524355 | BJ81: 0.73394495 | BK81: 1.0989678 | BL81: 1.0259644 | BM81: 0.29029733 | BN81: 2.2020469 | BO81: 7.1143418 | BP81: 6.2510716 | BQ81: 1.5763547 | BR81: 0.33278705
A82: Fiji | B82: FJI | C82: Inflation, consumer prices (annual %) | D82: FP.CPI.TOTL.ZG | O82: 4.1241786 | P82: 9.1381937 | Q82: 21.978504 | R82: 11.085318 | S82: 14.49847 | T82: 13.064881 | U82: 11.432436 | V82: 7.0063044 | W82: 6.108071 | X82: 7.8067582 | Y82: 14.492874 | Z82: 11.180667 | AA82: 7.0315569 | AB82: 6.704184 | AC82: 5.2912176 | AD82: 4.4209724 | AE82: 1.7988425 | AF82: 5.6637748 | AG82: 11.758327 | AH82: 6.189354 | AI82: 8.1913713 | AJ82: 6.4973456 | AK82: 4.8830227 | AL82: 5.2065893 | AM82: 0.81666667 | AN82: 2.1656472 | AO82: 3.0501618 | AP82: 3.3681401 | AQ82: 5.7116816 | AR82: 1.9686737 | AS82: 1.0921646 | AT82: 4.2726702 | AU82: 0.76203209 | AV82: 4.1727478 | AW82: 2.8274852 | AX82: 2.3657645 | AY82: 2.4908364 | AZ82: 4.8037064 | BA82: 7.7322786 | BB82: 3.1310356 | BC82: 3.6890123 | BD82: 7.2781178 | BE82: 3.4233752 | BF82: 2.9135419 | BG82: 0.51930647 | BH82: 1.3748854 | BI82: 3.8632254 | BJ82: 3.3475783 | BK82: 4.0814764 | BL82: 1.7938865 | BM82: -1.7001417 | BN82: 1.5345485 | BO82: 6.0788243 | BP82: 2.9754408 | BQ82: 3.8908424 | BR82: -1.3832683
A83: France | B83: FRA | C83: Inflation, consumer prices (annual %) | D83: FP.CPI.TOTL.ZG | E83: 4.1399396 | F83: 2.4004563 | G83: 5.3312754 | H83: 4.9991686 | I83: 3.2111879 | J83: 2.7031214 | K83: 2.6019784 | L83: 2.7917897 | M83: 4.5431843 | N83: 6.0459652 | O83: 5.2996613 | P83: 5.3975104 | Q83: 6.0630004 | R83: 7.3805961 | S83: 13.649324 | T83: 11.685929 | U83: 9.6254943 | V83: 9.4945565 | W83: 9.2505536 | X83: 10.646737 | Y83: 13.56258 | Z83: 13.3144 | AA83: 11.978472 | AB83: 9.4595493 | AC83: 7.6738045 | AD83: 5.8310977 | AE83: 2.5385268 | AF83: 3.2888994 | AG83: 2.7008198 | AH83: 3.4982964 | AI83: 3.1942827 | AJ83: 3.2134108 | AK83: 2.3637556 | AL83: 2.1044672 | AM83: 1.6555139 | AN83: 1.796481 | AO83: 1.9849797 | AP83: 1.2027469 | AQ83: 0.65001622 | AR83: 0.5401155 | AS83: 1.6706199 | AT83: 1.6381245 | AU83: 1.9219078 | AV83: 2.0987023 | AW83: 2.1461786 | AX83: 1.7415665 | AY83: 1.6761892 | AZ83: 1.488327 | BA83: 2.8129239 | BB83: 0.087594083 | BC83: 1.5331756 | BD83: 2.1080747 | BE83: 1.9551239 | BF83: 0.86272987 | BG83: 0.50773768 | BH83: 0.040333152 | BI83: 0.18444978 | BJ83: 1.0292061 | BK83: 1.8522207 | BL83: 1.1067657 | BM83: 0.47770085 | BN83: 1.6409062 | BO83: 5.2229408 | BP83: 4.8800022 | BQ83: 1.997426 | BR83: 0.94382476
A84: Faroe Islands | B84: FRO | C84: Inflation, consumer prices (annual %) | D84: FP.CPI.TOTL.ZG
A85: Micronesia, Fed. Sts. | B85: FSM | C85: Inflation, consumer prices (annual %) | D85: FP.CPI.TOTL.ZG | AS85: 2.1585181 | AT85: 0.50249735 | AU85: -0.11144243 | AV85: 0.12664335 | AW85: 2.276697 | AX85: 4.2576998 | AY85: 4.6373701 | AZ85: 3.3063428 | BA85: 8.4237257 | BB85: 6.3936026 | BC85: 3.3137096 | BD85: 5.082594 | BE85: 5.0185035 | BF85: 1.7523274 | BG85: 0.65028489 | BH85: -0.29811584 | BI85: -1.0374681 | BJ85: 0.58225374 | BK85: 1.4984002 | BL85: 1.9238517 | BM85: 0.55459463 | BN85: 3.1912841 | BO85: 5.4087438
A86: Gabon | B86: GAB | C86: Inflation, consumer prices (annual %) | D86: FP.CPI.TOTL.ZG | H86: 7.1583333 | I86: 3.3284081 | J86: 2.4384737 | K86: 3.6441114 | L86: 1.9777415 | M86: 2.3356041 | N86: 2.9751392 | O86: 3.8126649 | P86: 3.8632609 | Q86: 3.4870916 | R86: 6.2071412 | S86: 12.072804 | T86: 28.452943 | U86: 20.171564 | V86: 13.852569 | W86: 10.764169 | X86: 7.9526985 | Y86: 12.340359 | Z86: 8.7065021 | AA86: 16.685797 | AB86: 10.671937 | AC86: 5.8571429 | AD86: 7.3549258 | AE86: 6.2853551 | AF86: -0.94618569 | AG86: -8.7761194 | AH86: 6.7408377 | AI86: 7.7253219 | AJ86: -11.686113 | AK86: -9.5429133 | AL86: 0.53374656 | AM86: 36.116246 | AN86: 9.646531 | AO86: 0.68969338 | AP86: 3.9734501 | AQ86: 1.4487385 | AR86: -1.936604 | AS86: 0.50492003 | AT86: 2.1376205 | AU86: 0.036682889 | AV86: 2.2353531 | AW86: 0.40820531 | AX86: 3.7083333 | AY86: -1.4094014 | AZ86: 5.0303188 | BA86: 5.2643015 | BB86: 1.8857075 | BC86: 1.461544 | BD86: 1.2633171 | BE86: 2.6524183 | BF86: 0.50544106 | BG86: 4.6904575 | BH86: -0.33879519 | BI86: 2.1067071 | BJ86: 2.6519258 | BK86: 4.7490665 | BL86: 2.4645676 | BM86: 1.3527611 | BN86: 1.0869075 | BO86: 4.231248 | BP86: 3.6290153 | BQ86: 1.17312 | BR86: 1.7676661
A87: United Kingdom | B87: GBR | C87: Inflation, consumer prices (annual %) | D87: FP.CPI.TOTL.ZG | E87: 1.0035757 | F87: 3.4474962 | G87: 4.1964989 | H87: 2.0185436 | I87: 3.2815869 | J87: 4.7737746 | K87: 3.9096178 | L87: 2.4821156 | M87: 4.697428 | N87: 5.4466636 | O87: 6.3665684 | P87: 9.4448374 | Q87: 7.0710984 | R87: 9.1960332 | S87: 16.044011 | T87: 24.207288 | U87: 16.559523 | V87: 15.840267 | W87: 8.263141 | X87: 13.42128 | Y87: 17.965924 | Z87: 11.876627 | AA87: 8.5988638 | AB87: 4.6093033 | AC87: 4.960711 | AD87: 6.0713943 | AE87: 3.4276094 | AF87: 4.1489223 | AG87: 4.1553517 | AH87: 5.7602491 | AI87: 8.0634609 | AJ87: 7.461783 | AK87: 4.5915493 | AL87: 2.558578 | AM87: 2.2190126 | AN87: 2.6974952 | AO87: 2.8517824 | AP87: 2.2011431 | AQ87: 1.8205616 | AR87: 1.7529508 | AS87: 1.1829562 | AT87: 1.5323496 | AU87: 1.5204025 | AV87: 1.3765004 | AW87: 1.3903976 | AX87: 2.0891365 | AY87: 2.4556617 | AZ87: 2.3865615 | BA87: 3.5214086 | BB87: 1.9617317 | BC87: 2.4926547 | BD87: 3.8561124 | BE87: 2.5732348 | BF87: 2.2916667 | BG87: 1.4511202 | BH87: 0.36804684 | BI87: 1.0084174 | BJ87: 2.5577558 | BK87: 2.2928399 | BL87: 1.7381046 | BM87: 0.9894867 | BN87: 2.5183711 | BO87: 7.9220488 | BP87: 6.7939671 | BQ87: 3.2715729 | BR87: 3.8830688
A88: Georgia | B88: GEO | C88: Inflation, consumer prices (annual %) | D88: FP.CPI.TOTL.ZG | AN88: 162.71715 | AO88: 39.3575 | AP88: 7.0876176 | AQ88: 3.5668078 | AR88: 19.192676 | AS88: 4.063962 | AT88: 4.6460444 | AU88: 5.5878373 | AV88: 0.83773453 | AW88: 5.6563264 | AX88: 8.2470904 | AY88: 9.1609651 | AZ88: 9.2448975 | BA88: 9.9994876 | BB88: 1.7275146 | BC88: 7.110179 | BD88: 8.5429333 | BE88: -0.94365885 | BF88: -0.51205841 | BG88: 3.0688121 | BH88: 4.0035782 | BI88: 2.1349271 | BJ88: 6.0353173 | BK88: 2.6152447 | BL88: 4.8528982 | BM88: 5.2024649 | BN88: 9.5669143 | BO88: 11.898165 | BP88: 2.4877606 | BQ88: 1.1097176 | BR88: 3.8692132
A89: Ghana | B89: GHA | C89: Inflation, consumer prices (annual %) | D89: FP.CPI.TOTL.ZG | J89: 26.444785 | K89: 13.237885 | L89: -8.4224859 | M89: 7.8947368 | N89: 7.3170732 | O89: 3.030303 | P89: 9.5588235 | Q89: 10.067114 | R89: 17.682927 | S89: 18.134715 | T89: 29.824561 | U89: 56.081081 | V89: 116.45022 | W89: 73.091667 | X89: 54.441288 | Y89: 50.070139 | Z89: 116.5036 | AA89: 22.295566 | AB89: 122.87451 | AC89: 39.665314 | AD89: 10.305441 | AE89: 24.565416 | AF89: 39.815068 | AG89: 31.359268 | AH89: 25.223692 | AI89: 37.259066 | AJ89: 18.031439 | AK89: 10.056117 | AL89: 24.959842 | AM89: 24.870255 | AN89: 59.461554 | AO89: 46.56102 | AP89: 27.885209 | AQ89: 14.624167 | AR89: 4.8653979 | AS89: 40.240933 | AT89: 41.509496 | AU89: 9.3609324 | AV89: 29.77298 | AW89: 18.042739 | AX89: 15.438992 | AY89: 11.679184 | AZ89: 10.734267 | BA89: 16.49464 | BB89: 19.246948 | BC89: 10.73339 | BD89: 8.7284594 | BE89: 11.186341 | BF89: 11.666192 | BG89: 15.489616 | BH89: 17.14997 | BI89: 17.454635 | BJ89: 12.371922 | BK89: 7.8087652 | BL89: 7.14364 | BM89: 9.8872896 | BN89: 9.9710887 | BO89: 31.255895 | BP89: 38.106966 | BQ89: 22.848328 | BR89: 14.204676
A90: Gibraltar | B90: GIB | C90: Inflation, consumer prices (annual %) | D90: FP.CPI.TOTL.ZG
A91: Guinea | B91: GIN | C91: Inflation, consumer prices (annual %) | D91: FP.CPI.TOTL.ZG | AX91: 31.373303 | AY91: 34.695271 | AZ91: 18.175566 | BA91: 23.065613 | BB91: 4.6843887 | BC91: 15.050269 | BD91: 21.316927 | BE91: 15.226294 | BF91: 11.887588 | BG91: 6.1505056 | BH91: 11.780083 | BI91: 8.1726811 | BJ91: 8.9143595 | BK91: 9.827617 | BL91: 9.4700104 | BM91: 10.60162 | BN91: 12.597288 | BO91: 10.493041 | BP91: 7.8049759 | BQ91: 8.1231391 | BR91: 3.5709657
A92: Gambia, The | B92: GMB | C92: Inflation, consumer prices (annual %) | D92: FP.CPI.TOTL.ZG | G92: 1.7876179 | H92: 4.6161283 | I92: -4.5356538 | J92: 1.2180366 | K92: 0.23908193 | L92: 1.407219 | M92: 4.1787534 | N92: 5.0120409 | O92: -1.9850939 | P92: 3.0562258 | Q92: 8.6981199 | R92: 6.9186084 | S92: 9.2363104 | T92: 25.925 | U92: 17.027331 | V92: 12.389731 | W92: 8.8553459 | X92: 6.1289577 | Y92: 6.8246157 | Z92: 5.944227 | AA92: 10.855845 | AB92: 10.636304 | AC92: 22.098459 | AD92: 18.319885 | AE92: 56.560172 | AF92: 23.529167 | AG92: 11.690587 | AH92: 8.2750161 | AI92: 12.167784 | AJ92: 8.6423433 | AK92: 9.4865425 | AL92: 6.4638042 | AM92: 1.7102063 | AN92: 6.9809744 | AO92: 1.0994887 | AP92: 2.7812279 | AQ92: 1.1141884 | AR92: 3.8123721 | AS92: 0.84496957 | AT92: 4.4925961 | AU92: 8.6091247 | AV92: 17.032867 | AW92: 14.206743 | AX92: 4.8386218 | AY92: 2.0565034 | AZ92: 5.3691347 | BA92: 4.4436549 | BB92: 4.5615069 | BC92: 5.0496808 | BD92: 4.7958827 | BE92: 4.254322 | BF92: 5.6991299 | BG92: 5.9479994 | BH92: 6.8084549 | BI92: 7.2287927 | BJ92: 8.0341897 | BK92: 6.5209682 | BL92: 7.1156763 | BM92: 5.9312764 | BN92: 7.3703476 | BO92: 11.51312 | BP92: 16.974213 | BQ92: 11.561053
A93: Guinea-Bissau | B93: GNB | C93: Inflation, consumer prices (annual %) | D93: FP.CPI.TOTL.ZG | AG93: 60.281783 | AH93: 80.788141 | AI93: 33.001978 | AJ93: 57.595285 | AK93: 69.583636 | AL93: 48.108166 | AM93: 15.176347 | AN93: 45.365308 | AO93: 50.734055 | AP93: 49.100924 | AQ93: 8.0137552 | AR93: -2.0863051 | AS93: 8.6363209 | AT93: 3.3481227 | AU93: 3.3001218 | AV93: -3.5025855 | AW93: 0.8833027 | AX93: 3.3291992 | AY93: 1.9547372 | AZ93: 4.6174377 | BA93: 10.460073 | BB93: -1.6513973 | BC93: 2.5178514 | BD93: 5.0461023 | BE93: 2.1305458 | BF93: 1.2071256 | BG93: -1.5092446 | BH93: 1.4767205 | BI93: 1.5031206 | BJ93: 1.6911146 | BK93: 0.3813247 | BL93: 0.24660027 | BM93: 1.1400094 | BN93: 2.2424888 | BO93: 9.3907593 | BP93: 7.1022093 | BQ93: 3.7655583 | BR93: 0.87492969
A94: Equatorial Guinea | B94: GNQ | C94: Inflation, consumer prices (annual %) | D94: FP.CPI.TOTL.ZG | AE94: -17.640424 | AF94: -13.174473 | AG94: 2.5236593 | AH94: 6.1661538 | AI94: 0.85787155 | AJ94: -3.4252874 | AK94: -4.2787432 | AL94: 5.4522847 | AM94: 31.841017 | AN94: 19.872435 | AO94: 4.5407277 | AP94: 3.0165054 | AQ94: 7.9357107 | AR94: 0.37226617 | AS94: 4.8022889 | AT94: 8.8253893 | AU94: 7.5924785 | AV94: 7.323544 | AW94: 4.2196879 | AX94: 5.6316335 | AY94: 4.4158998 | AZ94: 2.8037383 | BA94: 6.5517669 | BB94: 4.6910657 | BC94: 7.7891655 | BD94: 4.8053892 | BE94: 3.6566205 | BF94: 2.9488769 | BG94: 4.3099987 | BH94: 1.6766309 | BI94: 1.4119392 | BJ94: 0.74435475 | BK94: 1.0600741 | BL94: 1.5302753 | BM94: 4.7666952 | BN94: -0.097100766 | BO94: 4.786717 | BP94: 2.8594951 | BQ94: 2.9214023
A95: Greece | B95: GRC | C95: Inflation, consumer prices (annual %) | D95: FP.CPI.TOTL.ZG | E95: 1.4778476 | F95: 2.1035793 | G95: -0.47542829 | H95: 3.1846627 | I95: 0.61730298 | J95: 3.2208725 | K95: 4.903416 | L95: 1.841357 | M95: 0.13906058 | N95: 2.6389187 | O95: 2.8416707 | P95: 3.2894707 | Q95: 4.3312012 | R95: 15.384624 | S95: 26.560847 | T95: 13.628762 | U95: 13.024279 | V95: 12.369797 | W95: 12.572426 | X95: 19.094175 | Y95: 24.675894 | Z95: 24.506068 | AA95: 20.991089 | AB95: 20.179481 | AC95: 18.456813 | AD95: 19.314693 | AE95: 23.015451 | AF95: 16.396863 | AG95: 13.528858 | AH95: 13.655564 | AI95: 20.433499 | AJ95: 19.455846 | AK95: 15.877074 | AL95: 14.411264 | AM95: 10.874076 | AN95: 8.9345142 | AO95: 8.1945522 | AP95: 5.5360027 | AQ95: 4.7662257 | AR95: 2.6366331 | AS95: 3.1511816 | AT95: 3.3739683 | AU95: 3.6293587 | AV95: 3.5306503 | AW95: 2.8988481 | AX95: 3.5450727 | AY95: 3.1959468 | AZ95: 2.8950032 | BA95: 4.1527971 | BB95: 1.2100727 | BC95: 4.7129891 | BD95: 3.3298532 | BE95: 1.501527 | BF95: -0.92126945 | BG95: -1.3125758 | BH95: -1.7256116 | BI95: -0.83768188 | BJ95: 1.120962 | BK95: 0.6251085 | BL95: 0.25527519 | BM95: -1.2474676 | BN95: 1.2239467 | BO95: 9.6448618 | BP95: 3.4645696 | BQ95: 2.7419751 | BR95: 2.4816269
A96: Grenada | B96: GRD | C96: Inflation, consumer prices (annual %) | D96: FP.CPI.TOTL.ZG | V96: 18.456884 | W96: 18.135377 | X96: 20.882883 | Y96: 21.821434 | Z96: 18.787471 | AA96: 7.8127414 | AB96: 6.0953473 | AC96: 5.6596128 | AD96: 2.5013849 | AE96: 0.5570799 | AF96: -0.87233339 | AG96: 4 | AH96: 5.5929487 | AI96: 2.7242374 | AJ96: 2.6446037 | AK96: 3.7783375 | AL96: 2.8085992 | AM96: 3.7706577 | AN96: 1.8688248 | AO96: 2.0323517 | AP96: 1.2445278 | AQ96: 1.3776933 | AR96: 0.57742764 | AS96: 2.1818182 | AT96: 3.1409931 | AU96: 1.0672155 | AV96: 2.1549281 | AW96: 2.3129168 | AX96: 3.4758069 | AY96: 4.2519532 | AZ96: 3.8588292 | BA96: 8.0332733 | BB96: -0.30865478 | BC96: 3.4365091 | BD96: 3.0334728 | BE96: 2.410777 | BF96: -0.043999786 | BG96: -0.98360306 | BH96: -0.51544803 | BI96: 1.6503899 | BJ96: 0.90845826 | BK96: 0.80410231 | BL96: 0.59814976 | BM96: -0.7407326 | BN96: 1.2195119 | BO96: 2.5805393 | BP96: 2.6961227 | BQ96: 1.0861537 | BR96: 0.61031198
A97: Greenland | B97: GRL | C97: Inflation, consumer prices (annual %) | D97: FP.CPI.TOTL.ZG
A98: Guatemala | B98: GTM | C98: Inflation, consumer prices (annual %) | D98: FP.CPI.TOTL.ZG | E98: -1.1906932 | F98: -0.55333538 | G98: 2.0525502 | H98: 0.1514509 | I98: -0.193564 | J98: -0.8 | K98: 0.68426197 | L98: 0.48543689 | M98: 1.9263285 | N98: 2.0972806 | O98: 2.3443393 | P98: -0.45359188 | Q98: 0.52970325 | R98: 13.796034 | S98: 16.494897 | T98: 13.159244 | U98: 10.725 | V98: 12.32458 | W98: 8.2879762 | X98: 11.343386 | Y98: 10.823843 | Z98: 11.433068 | AA98: 0.30738556 | AB98: 4.5386782 | AC98: 3.4067501 | AD98: 18.686791 | AE98: 36.931121 | AF98: 12.323213 | AG98: 10.832704 | AH98: 11.387132 | AI98: 41.221867 | AJ98: 33.166422 | AK98: 10.045918 | AL98: 11.81969 | AM98: 10.855321 | AN98: 8.4114131 | AO98: 11.056917 | AP98: 9.2329029 | AQ98: 6.6134607 | AR98: 5.2136106 | AS98: 5.9775773 | AT98: 7.2858737 | AU98: 8.1326305 | AV98: 5.6034768 | AW98: 7.5786225 | AX98: 9.1086499 | AY98: 6.5608528 | AZ98: 6.8216175 | BA98: 11.355761 | BB98: 1.8591025 | BC98: 3.8595091 | BD98: 6.2141239 | BE98: 3.7818075 | BF98: 4.3433713 | BG98: 3.4183617 | BH98: 2.3887203 | BI98: 4.448442 | BJ98: 4.4245366 | BK98: 3.7518619 | BL98: 3.699984 | BM98: 3.2144406 | BN98: 4.2610513 | BO98: 6.8851282 | BP98: 6.2065759 | BQ98: 2.8699275 | BR98: 1.4884159
A99: Guam | B99: GUM | C99: Inflation, consumer prices (annual %) | D99: FP.CPI.TOTL.ZG
A100: Guyana | B100: GUY | C100: Inflation, consumer prices (annual %) | D100: FP.CPI.TOTL.ZG | AN100: 12.210526 | AO100: 7.094712 | AP100: 3.5556709 | AQ100: 4.5864662 | AR100: 7.5382194 | AS100: 6.1485433 | AT100: 2.6274131 | AU100: 5.3410152 | AV100: 5.9809781 | AW100: 4.6684662 | AX100: 6.925543 | AY100: 6.6771579 | AZ100: 12.200154 | BA100: 8.1020221 | BB100: 2.952301 | BC100: 4.3005534 | BD100: 4.4073041 | BE100: 2.3905753 | BF100: 1.9111251 | BG100: 0.68370025 | BH100: -0.86540129 | BI100: 0.82617734 | BJ100: 1.9457162 | BK100: 1.2512857 | BL100: 2.1123899 | BM100: 0.72243405 | BN100: 4.5061986 | BO100: 6.9334607 | BP100: 2.8215939 | BQ100: 2.903795 | BR100: 3.3298234
A101: High income | B101: HIC | C101: Inflation, consumer prices (annual %) | D101: FP.CPI.TOTL.ZG | Z101: 11.509756 | AA101: 9.121382 | AB101: 7.0940618 | AC101: 6.0816023 | AD101: 4.6787436 | AE101: 2.9335798 | AF101: 3.6645632 | AG101: 4.4024118 | AH101: 5.2788116 | AI101: 5.6203234 | AJ101: 5.5555556 | AK101: 4.0370302 | AL101: 4.2517007 | AM101: 2.9534094 | AN101: 3.852524 | AO101: 2.9550645 | AP101: 2.499237 | AQ101: 2.0934211 | AR101: 2.1354484 | AS101: 2.71944 | AT101: 2.6274131 | AU101: 2.1154672 | AV101: 2.0667107 | AW101: 2.2067359 | AX101: 2.6584381 | AY101: 2.7200475 | AZ101: 2.8528984 | BA101: 4.6690084 | BB101: 1.6151046 | BC101: 2.1338205 | BD101: 3.4137452 | BE101: 2.7101192 | BF101: 1.5047233 | BG101: 1.0412009 | BH101: 0.33002717 | BI101: 0.38857707 | BJ101: 1.5890941 | BK101: 1.8818104 | BL101: 1.6152014 | BM101: 0.59898633 | BN101: 2.5183711 | BO101: 7.5310783 | BP101: 4.731513 | BQ101: 2.3815838 | BR101: 2.3360162
A102: Hong Kong SAR, China | B102: HKG | C102: Inflation, consumer prices (annual %) | D102: FP.CPI.TOTL.ZG | AA102: 10.970464 | AB102: 9.8859316 | AC102: 8.650519 | AD102: 3.5031847 | AE102: 3.3846154 | AF102: 5.6547619 | AG102: 7.8873239 | AH102: 10.182768 | AI102: 10.42654 | AJ102: 11.158798 | AK102: 9.6525097 | AL102: 8.8028169 | AM102: 8.7378641 | AN102: 9.077381 | AO102: 6.2755798 | AP102: 5.7766367 | AQ102: 2.9126214 | AR102: -4.009434 | AS102: -3.6855037 | AT102: -1.6581633 | AU102: -2.9831388 | AV102: -2.6737968 | AW102: -0.27472527 | AX102: 0.82644628 | AY102: 2.0002516 | AZ102: 2.0350271 | BA102: 4.3031548 | BB102: 0.57944142 | BC102: 2.2928909 | BD102: 5.3052489 | BE102: 4.0539095 | BF102: 4.3379934 | BG102: 4.4236453 | BH102: 2.9908482 | BI102: 2.4093074 | BJ102: 1.4938724 | BK102: 2.4061343 | BL102: 2.8832085 | BM102: 0.25096202 | BN102: 1.5687583 | BO102: 1.8813671 | BP102: 2.0966051 | BQ102: 1.7297212 | BR102: 1.4363354
...

Sheet Raw_GDP_Growth
A1: Data Source | B1: World Development Indicators
A3: Last Updated Date | B3: 2026-10-08
A5: Country Name | B5: Country Code | C5: Indicator Name | D5: Indicator Code | E5: 1960 | F5: 1961 | G5: 1962 | H5: 1963 | I5: 1964 | J5: 1965 | K5: 1966 | L5: 1967 | M5: 1968 | N5: 1969 | O5: 1970 | P5: 1971 | Q5: 1972 | R5: 1973 | S5: 1974 | T5: 1975 | U5: 1976 | V5: 1977 | W5: 1978 | X5: 1979 | Y5: 1980 | Z5: 1981 | AA5: 1982 | AB5: 1983 | AC5: 1984 | AD5: 1985 | AE5: 1986 | AF5: 1987 | AG5: 1988 | AH5: 1989 | AI5: 1990 | AJ5: 1991 | AK5: 1992 | AL5: 1993 | AM5: 1994 | AN5: 1995 | AO5: 1996 | AP5: 1997 | AQ5: 1998 | AR5: 1999 | AS5: 2000 | AT5: 2001 | AU5: 2002 | AV5: 2003 | AW5: 2004 | AX5: 2005 | AY5: 2006 | AZ5: 2007 | BA5: 2008 | BB5: 2009 | BC5: 2010 | BD5: 2011 | BE5: 2012 | BF5: 2013 | BG5: 2014 | BH5: 2015 | BI5: 2016 | BJ5: 2017 | BK5: 2018 | BL5: 2019 | BM5: 2020 | BN5: 2021 | BO5: 2022 | BP5: 2023 | BQ5: 2024 | BR5: 2025
A6: Aruba | B6: ABW | C6: GDP growth (annual %) | D6: NY.GDP.MKTP.KD.ZG | AF6: 16.078431 | AG6: 18.648649 | AH6: 12.129841 | AI6: 3.9614017 | AJ6: 7.9628717 | AK6: 5.882354 | AL6: 7.3076932 | AM6: 8.2039013 | AN6: 2.5471437 | AO6: 1.1857885 | AP6: 7.046875 | AQ6: 1.9919844 | AR6: 1.2380418 | AS6: 7.6229206 | AT6: 4.1820016 | AU6: -0.94495348 | AV6: 1.1105046 | AW6: 7.2937281 | AX6: -0.38313767 | AY6: 1.1274115 | AZ6: 3.0895444 | BA6: 1.8357552 | BB6: -11.677741 | BC6: -2.7334568 | BD6: 3.3692372 | BE6: -1.0407999 | BF6: 6.4314608 | BG6: 1.4260995 | BH6: 3.6114791 | BI6: 1.2343354 | BJ6: 3.4934299 | BK6: 3.2124711 | BL6: 1.2291441 | BM6: -23.940059 | BN6: 14.833692 | BO6: 10.607961 | BP6: 9.5163602 | BQ6: 6.8107767
A7: Africa Eastern and Southern | B7: AFE | C7: GDP growth (annual %) | D7: NY.GDP.MKTP.KD.ZG | F7: 0.41860452 | G7: 7.9370895 | H7: 5.6243171 | I7: 4.6503492 | J7: 5.1381532 | K7: 4.8275677 | L7: 5.3388033 | M7: 4.1564974 | N7: 5.1213578 | O7: 1.1123414 | P7: 5.4824776 | Q7: 2.7637494 | R7: 4.6210541 | S7: 5.47247 | T7: 1.3746952 | U7: 2.3486777 | V7: 1.1100761 | W7: 1.48045 | X7: 2.9275162 | Y7: 5.4525093 | Z7: 3.9285514 | AA7: 0.30873317 | AB7: 0.063309544 | AC7: 3.405999 | AD7: -0.086267474 | AE7: 2.2708785 | AF7: 3.938606 | AG7: 4.2863074 | AH7: 2.6661202 | AI7: 0.12124811 | AJ7: -0.1060836 | AK7: -2.3959973 | AL7: -0.83899814 | AM7: 1.92196 | AN7: 4.353927 | AO7: 5.4988963 | AP7: 3.8563472 | AQ7: 1.7747373 | AR7: 2.6341227 | AS7: 3.1809474 | AT7: 3.5033467 | AU7: 3.9168475 | AV7: 3.0092685 | AW7: 5.6346823 | AX7: 6.1737294 | AY7: 6.6374604 | AZ7: 6.7023633 | BA7: 4.4393342 | BB7: 0.9189169 | BC7: 5.3352128 | BD7: 3.7912405 | BE7: 1.8801298 | BF7: 4.6340001 | BG7: 3.9163617 | BH7: 2.9339035 | BI7: 2.2925006 | BJ7: 2.6788627 | BK7: 2.7062074 | BL7: 1.9355926 | BM7: -2.9307641 | BN7: 4.452643 | BO7: 3.6680291 | BP7: 1.9413816 | BQ7: 2.7879315 | BR7: 3.7430159
A8: Afghanistan | B8: AFG | C8: GDP growth (annual %) | D8: NY.GDP.MKTP.KD.ZG | AT8: -9.4319741 | AU8: 28.600001 | AV8: 8.8322778 | AW8: 1.414118 | AX8: 11.229715 | AY8: 5.3574032 | AZ8: 13.82632 | BA8: 3.9249838 | BB8: 21.390528 | BC8: 14.362441 | BD8: 0.42635478 | BE8: 12.752287 | BF8: 5.6007447 | BG8: 2.7245434 | BH8: 1.4513147 | BI8: 2.2603142 | BJ8: 2.6470032 | BK8: 1.1892281 | BL8: 3.9116034 | BM8: -2.3511007 | BN8: -20.738839 | BO8: -6.240172 | BP8: 2.2669437 | BQ8: 1.8731928
A9: Africa Western and Central | B9: AFW | C9: GDP growth (annual %) | D9: NY.GDP.MKTP.KD.ZG | F9: 1.8695932 | G9: 3.7260158 | H9: 7.0381715 | I9: 5.36458 | J9: 4.10566 | K9: -1.5129592 | L9: -8.9663244 | M9: 1.5745921 | N9: 15.016524 | O9: 17.309161 | P9: 10.407117 | Q9: 3.1672607 | R9: 3.921881 | S9: 9.9159601 | T9: -2.0139101 | U9: 8.4221251 | V9: 4.5611099 | W9: -1.9152738 | X9: 5.0308337 | Y9: 1.8685404 | Z9: -6.6405572 | AA9: -3.2706126 | AB9: -6.2893278 | AC9: 0.48370524 | AD9: 5.3198983 | AE9: 1.2663631 | AF9: 1.410625 | AG9: 4.7612941 | AH9: 1.7235101 | AI9: 5.6006394 | AJ9: 1.1181368 | AK9: 2.2891577 | AL9: -1.3253624 | AM9: -0.22887373 | AN9: 1.8518584 | AO9: 4.6218579 | AP9: 4.3875653 | AQ9: 3.6155743 | AR9: 1.5180542 | AS9: 3.8119429 | AT9: 5.2485252 | AU9: 9.9430962 | AV9: 5.6263902 | AW9: 8.0713967 | AX9: 5.7974954 | AY9: 5.2874693 | AZ9: 5.4473398 | BA9: 6.2106556 | BB9: 6.1410559 | BC9: 7.000647 | BD9: 4.9220318 | BE9: 5.1296897 | BF9: 6.0466542 | BG9: 5.6915234 | BH9: 2.932911 | BI9: 0.17617172 | BJ9: 2.3027606 | BK9: 2.8999542 | BL9: 3.2831424 | BM9: -3.7187933 | BN9: 2.5454727 | BO9: 4.4771076 | BP9: 3.6445909 | BQ9: 4.5961834 | BR9: 4.6001
A10: Angola | B10: AGO | C10: GDP growth (annual %) | D10: NY.GDP.MKTP.KD.ZG | Z10: -4.4000012 | AA10: 0 | AB10: 4.2000014 | AC10: 6.0000022 | AD10: 3.4999995 | AE10: 2.9000017 | AF10: 4.0827486 | AG10: 6.1288905 | AH10: 0.041621462 | AI10: -3.4500987 | AJ10: 0.9913593 | AK10: -5.8382807 | AL10: -23.983417 | AM10: 1.3393634 | AN10: 15 | AO10: 13.54437 | AP10: 7.2742774 | AQ10: 4.6911465 | AR10: 2.1814897 | AS10: 3.0546242 | AT10: 4.2059986 | AU10: 13.665689 | AV10: 3.4873124 | AW10: 11.419863 | AX10: 14.154778 | AY10: 11.841818 | AZ10: 13.002689 | BA10: 10.786636 | BB10: 1.9955891 | BC10: 5.2936657 | BD10: 3.5938696 | BE10: 8.5031228 | BF10: 4.8830613 | BG10: 4.6557236 | BH10: 0.76317771 | BI10: -0.23307695 | BJ10: -0.16468866 | BK10: -0.50669754 | BL10: -1.0552341 | BM10: -5.2734913 | BN10: 1.0905837 | BO10: 3.5574921 | BP10: 1.3201659 | BQ10: 4.9526786 | BR10: 3.1335354
A11: Albania | B11: ALB | C11: GDP growth (annual %) | D11: NY.GDP.MKTP.KD.ZG | Z11: 5.7456353 | AA11: 2.9485968 | AB11: 1.1049383 | AC11: -1.2515966 | AD11: 1.780644 | AE11: 5.6372432 | AF11: -0.78784265 | AG11: -1.4200397 | AH11: 9.836549 | AI11: -9.5756402 | AJ11: -28.002142 | AK11: -7.1871109 | AL11: 9.5594117 | AM11: 8.3028666 | AN11: 13.322333 | AO11: 7.3363289 | AP11: -11.711573 | AQ11: 8.3100252 | AR11: 12.250728 | AS11: 7.4628587 | AT11: 8.8637307 | AU11: 4.6283959 | AV11: 5.3332643 | AW11: 5.2662617 | AX11: 5.1308219 | AY11: 6.0189812 | AZ11: 6.5000926 | BA11: 6.9070623 | BB11: 2.6907515 | BC11: 2.9731544 | BD11: 2.4635168 | BE11: 0.98412988 | BF11: 1.7072283 | BG11: 2.240227 | BH11: 2.2277041 | BI11: 3.9089355 | BJ11: 3.2831759 | BK11: 3.6714193 | BL11: 2.0625779 | BM11: -3.3137564 | BN11: 8.9695762 | BO11: 4.8268006 | BP11: 4.0154172 | BQ11: 4.0459285 | BR11: 3.7889384
A12: Andorra | B12: AND | C12: GDP growth (annual %) | D12: NY.GDP.MKTP.KD.ZG | P12: 4.6494654 | Q12: 8.1497435 | R12: 7.7884672 | S12: 5.6187896 | T12: 0.54220567 | U12: 3.3037871 | V12: 2.8385756 | W12: 1.4630002 | X12: 0.041557223 | Y12: 2.2087276 | Z12: -0.13247449 | AA12: 1.2464611 | AB12: 1.7701183 | AC12: 1.7846867 | AD12: 2.321433 | AE12: 3.2533218 | AF12: 5.5471222 | AG12: 5.0943262 | AH12: 4.8270343 | AI12: 3.7813875 | AJ12: 2.5460035 | AK12: 0.92921404 | AL12: -1.0314844 | AM12: 2.3831822 | AN12: 2.7575016 | AO12: 4.6497387 | AP12: 9.0676721 | AQ12: 3.1947934 | AR12: 4.0990789 | AS12: 3.5283624 | AT12: 8.1193577 | AU12: 4.5463622 | AV12: 8.6942037 | AW12: 8.1356763 | AX12: 5.397796 | AY12: 4.8086887 | AZ12: 1.5531881 | BA12: -5.5591864 | BB12: -5.3028465 | BC12: -1.974958 | BD12: -0.0080697534 | BE12: -4.9744437 | BF12: -3.5475965 | BG12: 2.5044655 | BH12: 1.4341404 | BI12: 3.7096781 | BJ12: 0.34607189 | BK12: 1.5887655 | BL12: 2.0155476 | BM12: -11.18394 | BN12: 8.2867788 | BO12: 9.5646123 | BP12: 2.5835548 | BQ12: 3.8491605 | BR12: 3.8680345
A13: Arab World | B13: ARB | C13: GDP growth (annual %) | D13: NY.GDP.MKTP.KD.ZG | L13: 6.786332 | M13: 10.780642 | N13: 7.4546574 | O13: 22.941207 | P13: 7.4845697 | Q13: 13.939193 | R13: 13.291504 | S13: 10.513404 | T13: -0.038970754 | U13: 14.310714 | V13: 6.5891794 | W13: 2.954258 | X13: 10.647739 | Y13: 6.2791327 | Z13: 0.86580421 | AA13: -5.9736566 | AB13: -3.7601792 | AC13: 1.2453435 | AD13: -0.84660702 | AE13: -0.77095957 | AF13: 0.25409336 | AG13: 3.2791978 | AH13: 3.7932962 | AI13: 7.8321576 | AJ13: -0.69384519 | AK13: 6.5762999 | AL13: 3.2556746 | AM13: 3.3554661 | AN13: 2.8010926 | AO13: 4.8149922 | AP13: 5.4663114 | AQ13: 4.7704738 | AR13: 2.778466 | AS13: 6.3361914 | AT13: 2.143879 | AU13: 1.2934637 | AV13: 4.1919969 | AW13: 9.0874085 | AX13: 5.5790716 | AY13: 6.3082114 | AZ13: 4.6294113 | BA13: 5.59734 | BB13: 0.68094799 | BC13: 4.7365057 | BD13: 3.8486068 | BE13: 5.4813797 | BF13: 2.5856464 | BG13: 2.5877736 | BH13: 3.3499828 | BI13: 3.5724563 | BJ13: 1.3312699 | BK13: 2.6703834 | BL13: 1.7494924 | BM13: -5.2864142 | BN13: 4.431404 | BO13: 6.9966763 | BP13: 1.6487293 | BQ13: 2.0052181 | BR13: 3.6775799
A14: United Arab Emirates | B14: ARE | C14: GDP growth (annual %) | D14: NY.GDP.MKTP.KD.ZG | P14: 36.612378 | Q14: 39.079638 | R14: 76.620155 | S14: 14.498041 | T14: 6.2276109 | U14: 16.526679 | V14: 21.439699 | W14: -1.5896194 | X14: 20.923487 | Y14: 23.874579 | Z14: 4.6593642 | AA14: -6.7191448 | AB14: -4.7460697 | AC14: 4.017138 | AD14: -3.5948668 | AE14: -14.957772 | AF14: 3.3814507 | AG14: -2.6190537 | AH14: 12.338371 | AI14: 18.327723 | AJ14: 0.86010433 | AK14: 3.3452817 | AL14: 1.2610979 | AM14: 6.8960757 | AN14: 6.6876693 | AO14: 5.7985509 | AP14: 8.1902626 | AQ14: 0.29222649 | AR14: 2.9020534 | AS14: 10.852838 | AT14: 1.3989216 | AU14: 2.4333749 | AV14: 8.8005781 | AW14: 9.5665263 | AX14: 4.8551366 | AY14: 9.8372792 | AZ14: 3.1844128 | BA14: 3.1918124 | BB14: -5.2429219 | BC14: 1.60285 | BD14: 6.7365117 | BE14: 4.6832564 | BF14: 4.9184506 | BG14: 4.6329179 | BH14: 7.0876662 | BI14: 5.6579015 | BJ14: -1.0613711 | BK14: 1.5372063 | BL14: 1.2712912 | BM14: -8.6934336 | BN14: 4.5528014 | BO14: 7.5145241 | BP14: 4.3011365 | BQ14: 3.991812
A15: Argentina | B15: ARG | C15: GDP growth (annual %) | D15: NY.GDP.MKTP.KD.ZG | F15: 5.4278429 | G15: -0.85202152 | H15: -5.3081968 | I15: 10.130298 | J15: 10.569433 | K15: -0.65972617 | L15: 3.1919966 | M15: 4.8225008 | N15: 9.679526 | O15: 3.0456433 | P15: 5.6581311 | Q15: 1.6284165 | R15: 2.811754 | S15: 5.5338044 | T15: -0.028412104 | U15: -2.0182515 | V15: 6.9341478 | W15: -4.5061248 | X15: 10.222763 | Y15: 1.5187839 | Z15: -5.1897891 | AA15: -0.73565916 | AB15: 4.3490933 | AC15: 1.5707387 | AD15: -5.1890244 | AE15: 6.1533771 | AF15: 2.7048688 | AG15: -1.0899333 | AH15: -7.1569497 | AI15: -2.4672138 | AJ15: 9.1331106 | AK15: 7.9372916 | AL15: 8.2069791 | AM15: 5.8362007 | AN15: -2.8452096 | AO15: 5.5266898 | AP15: 8.1110468 | AQ15: 3.8501789 | AR15: -3.385457 | AS15: -0.78899894 | AT15: -4.4088397 | AU15: -10.894485 | AV15: 8.8370408 | AW15: 9.0295733 | AX15: 8.8516599 | AY15: 8.0471515 | AZ15: 9.0076509 | BA15: 4.0572331 | BB15: -5.9185251 | BC15: 10.125398 | BD15: 6.0039517 | BE15: -1.0264205 | BF15: 2.4053238 | BG15: -2.5126153 | BH15: 2.7311598 | BI15: -2.0803278 | BJ15: 2.818503 | BK15: -2.6173965 | BL15: -2.000861 | BM15: -9.9004848 | BN15: 10.441812 | BO15: 6.0207454 | BP15: -1.855788 | BQ15: -1.3429307 | BR15: 4.3673333
A16: Armenia | B16: ARM | C16: GDP growth (annual %) | D16: NY.GDP.MKTP.KD.ZG | AJ16: -11.699998 | AK16: -41.800003 | AL16: -8.7999988 | AM16: 5.4000028 | AN16: 6.8999984 | AO16: 5.8654007 | AP16: 3.3210797 | AQ16: 7.3 | AR16: 3.3 | AS16: 5.9 | AT16: 9.6 | AU16: 13.2 | AV16: 14 | AW16: 10.5 | AX16: 13.9 | AY16: 13.2 | AZ16: 13.7 | BA16: 6.9 | BB16: -14.1 | BC16: 2.2 | BD16: 4.7 | BE16: 7.2 | BF16: 3.3 | BG16: 3.6 | BH16: 3.2 | BI16: 0.2 | BJ16: 7.5 | BK16: 5.2 | BL16: 7.6 | BM16: -7.2 | BN16: 5.8 | BO16: 12.6 | BP16: 8.3 | BQ16: 5.9 | BR16: 7.2
A17: American Samoa | B17: ASM | C17: GDP growth (annual %) | D17: NY.GDP.MKTP.KD.ZG | AV17: 0.96551724 | AW17: 0.40983607 | AX17: -0.40816327 | AY17: -4.0983607 | AZ17: 1.8518519 | BA17: -2.6573427 | BB17: -4.1666667 | BC17: 0.29985007 | BD17: 0 | BE17: -4.3348281 | BF17: -2.5 | BG17: 1.7628205 | BH17: 3.1496063 | BI17: -1.6793893 | BJ17: -6.9875776 | BK17: 2.6711185 | BL17: -0.48780488 | BM17: 4.4117647 | BN17: -0.78247261 | BO17: 1.7350158
A18: Antigua and Barbuda | B18: ATG | C18: GDP growth (annual %) | D18: NY.GDP.MKTP.KD.ZG | W18: 4.3835125 | X18: 8.0794462 | Y18: 8.1619839 | Z18: 3.8144482 | AA18: -0.083506684 | AB18: 5.3638188 | AC18: 10.16523 | AD18: 7.6438444 | AE18: 11.493669 | AF18: 6.6261349 | AG18: 5.213132 | AH18: 5.2523015 | AI18: 3.0118132 | AJ18: 2.1768522 | AK18: 1.1585508 | AL18: 5.2798868 | AM18: 6.6764065 | AN18: -4.3597847 | AO18: 6.6049449 | AP18: 5.4712558 | AQ18: 4.7312791 | AR18: 3.7077459 | AS18: 6.2035521 | AT18: -4.5481098 | AU18: 1.0272349 | AV18: 6.0766367 | AW18: 5.7671034 | AX18: 6.4736894 | AY18: 12.708147 | AZ18: 9.3151827 | BA18: -0.014006598 | BB18: -11.962879 | BC18: -7.8405068 | BD18: -1.9587426 | BE18: 3.3731427 | BF18: -0.60098233 | BG18: 2.1982919 | BH18: 1.42162 | BI18: 4.1203675 | BJ18: 2.7127266 | BK18: 6.7120049 | BL18: 3.1722219 | BM18: -18.868777 | BN18: 8.1728631 | BO18: 8.4977634 | BP18: 3.8655016 | BQ18: 2.5404419 | BR18: 4.99804
A19: Australia | B19: AUS | C19: GDP growth (annual %) | D19: NY.GDP.MKTP.KD.ZG | F19: 2.4808574 | G19: 1.2969318 | H19: 6.2143763 | I19: 6.9775719 | J19: 5.9775054 | K19: 2.3810335 | L19: 6.3068995 | M19: 5.0951298 | N19: 7.0476024 | O19: 7.1746998 | P19: 4.0009866 | Q19: 3.9069786 | R19: 2.6185459 | S19: 4.106611 | T19: 1.3387006 | U19: 2.5878221 | V19: 3.5923758 | W19: 0.89536344 | X19: 4.0515509 | Y19: 3.0345351 | Z19: 3.3424202 | AA19: 3.32865 | AB19: -2.2258235 | AC19: 4.5644787 | AD19: 5.2816981 | AE19: 3.9697631 | AF19: 2.556768 | AG19: 5.7613701 | AH19: 3.8790178 | AI19: 3.5729757 | AJ19: -0.38463136 | AK19: 0.43306586 | AL19: 4.0458337 | AM19: 3.9788443 | AN19: 3.8901719 | AO19: 3.8656748 | AP19: 3.9179581 | AQ19: 4.6768137 | AR19: 5.0282204 | AS19: 3.9160575 | AT19: 2.0314588 | AU19: 3.9498054 | AV19: 3.0912801 | AW19: 4.2189415 | AX19: 3.1554812 | AY19: 2.7709262 | AZ19: 3.7894712 | BA19: 3.623985 | BB19: 1.9548483 | BC19: 2.210048 | BD19: 2.3947349 | BE19: 3.9524714 | BF19: 2.654453 | BG19: 2.6011898 | BH19: 2.1643478 | BI19: 2.7556407 | BJ19: 2.2933103 | BK19: 2.8741704 | BL19: 2.194017 | BM19: -0.1335319 | BN19: 2.0069484 | BO19: 4.2530456 | BP19: 3.583821 | BQ19: 1.3734077 | BR19: 1.3503979
A20: Austria | B20: AUT | C20: GDP growth (annual %) | D20: NY.GDP.MKTP.KD.ZG | F20: 5.537979 | G20: 2.6486746 | H20: 4.1382678 | I20: 6.1243535 | J20: 3.4801745 | K20: 5.6428614 | L20: 3.0080474 | M20: 4.4723124 | N20: 6.275867 | O20: 7.1228757 | P20: 5.1149684 | Q20: 6.2078606 | R20: 4.890436 | S20: 3.9421382 | T20: -0.36373578 | U20: 4.5784449 | V20: 5.0799812 | W20: -0.21065365 | X20: 5.3566999 | Y20: 1.7314855 | Z20: -0.14429473 | AA20: 2.0112546 | AB20: 2.9730878 | AC20: 0.051275157 | AD20: 2.4986788 | AE20: 2.3013928 | AF20: 1.357168 | AG20: 3.2958798 | AH20: 3.8870748 | AI20: 4.3456418 | AJ20: 3.4416275 | AK20: 2.0935244 | AL20: 0.52680977 | AM20: 2.4021184 | AN20: 2.6679839 | AO20: 2.2157671 | AP20: 2.1458351 | AQ20: 3.49288 | AR20: 3.7619244 | AS20: 3.1895229 | AT20: 1.3169875 | AU20: 1.4843688 | AV20: 1.141565 | AW20: 2.5652553 | AX20: 2.3203651 | AY20: 3.269336 | AZ20: 3.7752247 | BA20: 1.4533056 | BB20: -3.5862647 | BC20: 1.8089824 | BD20: 2.927468 | BE20: 0.62824624 | BF20: -0.25072642 | BG20: 0.75579885 | BH20: 1.3035233 | BI20: 2.1172196 | BJ20: 2.2722499 | BK20: 2.4842211 | BL20: 1.7549762 | BM20: -6.3182551 | BN20: 4.9230917 | BO20: 5.3309638 | BP20: -0.78624429 | BQ20: -0.65908957 | BR20: 0.61574728
A21: Azerbaijan | B21: AZE | C21: GDP growth (annual %) | D21: NY.GDP.MKTP.KD.ZG | AJ21: -0.70000018 | AK21: -22.6 | AL21: -23.099999 | AM21: -19.700001 | AN21: -11.799999 | AO21: 1.2999994 | AP21: 5.8000001 | AQ21: 9.9999996 | AR21: 7.4000013 | AS21: 11.099999 | AT21: 9.8999999 | AU21: 9.4389163 | AV21: 10.208299 | AW21: 9.2538018 | AX21: 27.961538 | AY21: 34.46621 | AZ21: 25.463216 | BA21: 10.591437 | BB21: 9.3695026 | BC21: 4.7888325 | BD21: -1.5729974 | BE21: 2.2029389 | BF21: 5.8434159 | BG21: 2.7975852 | BH21: 1.0495464 | BI21: -3.0635984 | BJ21: 0.15361466 | BK21: 1.5004017 | BL21: 2.4798088 | BM21: -4.1989607 | BN21: 5.6164403 | BO21: 4.7146803 | BP21: 1.3544775 | BQ21: 4.158068 | BR21: 1.4498559
A22: Burundi | B22: BDI | C22: GDP growth (annual %) | D22: NY.GDP.MKTP.KD.ZG | F22: -13.746135 | G22: 9.0631579 | H22: 4.1354074 | I22: 6.2730379 | J22: 3.9672256 | K22: 4.6129929 | L22: 13.821519 | M22: -0.29788367 | N22: -1.4595411 | O22: 21.325671 | P22: 2.7468287 | Q22: -6.4039649 | R22: 6.8890507 | S22: -0.72683956 | T22: 0.69792024 | U22: 7.942661 | V22: 11.469453 | W22: -0.94057599 | X22: 1.664955 | Y22: 0.99105573 | Z22: 12.163276 | AA22: -1.0535998 | AB22: 3.715327 | AC22: 0.155544 | AD22: 11.78318 | AE22: 3.2501805 | AF22: 5.5030961 | AG22: 5.0310244 | AH22: 1.3495022 | AI22: 3.4998221 | AJ22: 4.9968364 | AK22: 1.0099984 | AL22: -6.24 | AM22: -3.83 | AN22: -7.92 | AO22: -8 | AP22: -1.59 | AQ22: 4.75 | AR22: -1.01 | AS22: -0.85686406 | AT22: 2.0558071 | AU22: 4.4465194 | AV22: -1.223728 | AW22: 4.8336578 | AX22: 0.9 | AY22: 5.4138071 | AZ22: 3.4444936 | BA22: 4.9087419 | BB22: 3.7870758 | BC22: 5.093737 | BD22: 4.0244279 | BE22: 4.4230312 | BF22: 4.9239249 | BG22: 4.244908 | BH22: -0.4045256 | BI22: 3.2001747 | BJ22: 3.8318576 | BK22: 5.3422447 | BL22: 4.459342 | BM22: 0.30644381 | BN22: 3.2370748 | BO22: 2.3177012 | BP22: 3.254769 | BQ22: 4.1122738 | BR22: 4.2401053
A23: Belgium | B23: BEL | C23: GDP growth (annual %) | D23: NY.GDP.MKTP.KD.ZG | F23: 4.9784229 | G23: 5.2120032 | H23: 4.3515844 | I23: 6.956685 | J23: 3.5606602 | K23: 3.1558949 | L23: 3.8681472 | M23: 4.1941294 | N23: 6.6298001 | O23: 6.3526723 | P23: 3.9858272 | Q23: 5.2956047 | R23: 6.3817018 | S23: 4.5652585 | T23: -1.9659419 | U23: 5.6527461 | V23: 0.62615457 | W23: 2.8418968 | X23: 2.341073 | Y23: 4.4440539 | Z23: -0.27928359 | AA23: 0.59498677 | AB23: 0.31184301 | AC23: 2.4663825 | AD23: 1.651793 | AE23: 1.822762 | AF23: 2.3066597 | AG23: 4.7232087 | AH23: 3.469167 | AI23: 3.1374022 | AJ23: 1.8330744 | AK23: 1.5306548 | AL23: -0.96187308 | AM23: 3.2269715 | AN23: 2.3847572 | AO23: 1.3214321 | AP23: 3.7936717 | AQ23: 1.9618324 | AR23: 3.542718 | AS23: 3.7167051 | AT23: 1.0996036 | AU23: 1.7068943 | AV23: 1.0379552 | AW23: 3.5712067 | AX23: 2.3217379 | AY23: 2.5523409 | AZ23: 3.6769246 | BA23: 0.44690513 | BB23: -1.9064411 | BC23: 2.7103115 | BD23: 1.931155 | BE23: 0.21580361 | BF23: 0.30549455 | BG23: 1.7655404 | BH23: 1.4741643 | BI23: 1.1935027 | BJ23: 1.4744676 | BK23: 1.8779685 | BL23: 2.44289 | BM23: -4.7929839 | BN23: 6.2544569 | BO23: 4.0246085 | BP23: 1.5612554 | BQ23: 1.0977538 | BR23: 0.98311797
A24: Benin | B24: BEN | C24: GDP growth (annual %) | D24: NY.GDP.MKTP.KD.ZG | F24: 3.1412805 | G24: -3.4264098 | H24: 4.730028 | I24: 6.6507591 | J24: 5.2938628 | K24: 3.5758627 | L24: 1.0783987 | M24: 3.8423356 | N24: 2.877498 | O24: 2.0977576 | P24: -1.4968418 | Q24: 6.4263675 | R24: 3.7061653 | S24: 3.3393122 | T24: -4.8953454 | U24: 0.88435633 | V24: 4.9836637 | W24: 1.255078 | X24: 6.5357474 | Y24: 6.7817639 | Z24: 9.9542312 | AA24: 2.2350663 | AB24: -4.3478227 | AC24: 7.9298396 | AD24: 7.5303248 | AE24: 2.1711416 | AF24: -1.500003 | AG24: 3.4052453 | AH24: -2.8541605 | AI24: 8.9761344 | AJ24: 4.2257994 | AK24: 2.9577108 | AL24: 5.8361721 | AM24: 2.0204004 | AN24: 6.0451987 | AO24: 4.324284 | AP24: 5.7346884 | AQ24: 3.9610121 | AR24: 5.3414494 | AS24: 5.8577142 | AT24: 5.3331357 | AU24: 4.6430309 | AV24: 3.4435768 | AW24: 4.4296846 | AX24: 1.7131646 | AY24: 3.9437388 | AZ24: 5.9863493 | BA24: 4.8965771 | BB24: 2.3192921 | BC24: 2.1140647 | BD24: 2.9637529 | BE24: 4.8112233 | BF24: 7.1914337 | BG24: 6.3576791 | BH24: 1.7781511 | BI24: 3.3396734 | BJ24: 5.671562 | BK24: 6.6972536 | BL24: 6.8656866 | BM24: 3.8487924 | BN24: 7.1554516 | BO24: 6.2529471 | BP24: 6.3527774 | BQ24: 7.4531157 | BR24: 8.0740845
A25: Burkina Faso | B25: BFA | C25: GDP growth (annual %) | D25: NY.GDP.MKTP.KD.ZG | F25: 4.043928 | G25: 6.1287988 | H25: -1.2680164 | I25: 2.2828192 | J25: 3.7645454 | K25: 0.53761308 | L25: 8.823315 | M25: 3.0707739 | N25: 2.026081 | O25: 0.11701961 | P25: 1.4133399 | Q25: 2.3114987 | R25: 0.4493274 | S25: 8.2864265 | T25: 2.9983829 | U25: 8.534895 | V25: 0.37035356 | W25: 4.607825 | X25: 3.6646215 | Y25: 0.79687888 | Z25: 4.2553034 | AA25: 9.5621966 | AB25: 0.34598474 | AC25: -1.7786967 | AD25: 8.517365 | AE25: 7.9553627 | AF25: -0.23633679 | AG25: 5.795593 | AH25: 2.1502673 | AI25: -0.60292848 | AJ25: 9.0699845 | AK25: 0.23271076 | AL25: 3.4613849 | AM25: 1.3150073 | AN25: 5.7163739 | AO25: 11.014744 | AP25: 6.3168347 | AQ25: 7.3077196 | AR25: 7.3952378 | AS25: 1.8884739 | AT25: 6.6134057 | AU25: 4.3529638 | AV25: 7.8024939 | AW25: 4.4784521 | AX25: 8.6618732 | AY25: 6.2531647 | AZ25: 4.111379 | BA25: 5.7999917 | BB25: 2.9619509 | BC25: 8.4462816 | BD25: 6.6225626 | BE25: 6.4526724 | BF25: 5.7925848 | BG25: 4.3268456 | BH25: 3.9212288 | BI25: 5.9579767 | BJ25: 6.2034894 | BK25: 6.6045691 | BL25: 5.889205 | BM25: 2.0107726 | BN25: 6.9425249 | BO25: 1.6267326 | BP25: 3.0002742 | BQ25: 4.8339581 | BR25: 5.2946184
A26: Bangladesh | B26: BGD | C26: GDP growth (annual %) | D26: NY.GDP.MKTP.KD.ZG | F26: 6.0581608 | G26: 5.453031 | H26: -0.45589429 | I26: 10.952789 | J26: 1.6062582 | K26: 2.566812 | L26: -1.8758639 | M26: 9.489454 | N26: 1.2208579 | O26: 5.6198523 | P26: -5.479483 | Q26: -13.973729 | R26: 3.3256802 | S26: 9.5919563 | T26: -4.0882141 | U26: 5.6613612 | V26: 2.6730561 | W26: 7.0738377 | X26: 4.8016346 | Y26: 0.81914187 | Z26: 7.2339437 | AA26: 2.1343278 | AB26: 3.8810464 | AC26: 4.80331 | AD26: 3.3420147 | AE26: 4.1733826 | AF26: 3.7724019 | AG26: 2.4162569 | AH26: 2.8365821 | AI26: 5.6222582 | AJ26: 3.4852278 | AK26: 5.4426855 | AL26: 4.7115617 | AM26: 3.8901264 | AN26: 5.1212779 | AO26: 4.5229192 | AP26: 4.4898965 | AQ26: 5.1770269 | AR26: 4.6701564 | AS26: 5.2932947 | AT26: 5.0772878 | AU26: 3.8331239 | AV26: 4.7395674 | AW26: 5.2395329 | AX26: 6.5359449 | AY26: 6.671905 | AZ26: 7.0585994 | BA26: 6.0137898 | BB26: 5.0451248 | BC26: 5.5717882 | BD26: 6.4643791 | BE26: 6.5214588 | BF26: 6.0136057 | BG26: 6.0610594 | BH26: 6.5526399 | BI26: 7.1134782 | BJ26: 6.59025 | BK26: 7.3194126 | BL26: 7.8819152 | BM26: 3.4480176 | BN26: 6.9386791 | BO26: 7.0998288 | BP26: 5.7751124 | BQ26: 4.2232591 | BR26: 3.4899067
A27: Bulgaria | B27: BGR | C27: GDP growth (annual %) | D27: NY.GDP.MKTP.KD.ZG | Z27: 4.9001637 | AA27: 2.3345645 | AB27: 3.4303075 | AC27: 3.3964432 | AD27: 2.6834386 | AE27: 4.2076027 | AF27: 6.0545144 | AG27: 10.944692 | AH27: -3.2898823 | AI27: -9.1173762 | AJ27: -8.4453556 | AK27: -7.2723874 | AL27: -1.4802147 | AM27: 1.8180119 | AN27: 2.9023154 | AO27: 5.2054792 | AP27: -14.115377 | AQ27: 3.7891145 | AR27: -8.3960877 | AS27: 4.5872255 | AT27: 3.8237022 | AU27: 5.8719313 | AV27: 5.2371528 | AW27: 6.5104241 | AX27: 7.0563492 | AY27: 6.8025926 | AZ27: 6.6543851 | BA27: 6.1295589 | BB27: -3.3471431 | BC27: 1.5553627 | BD27: 2.090176 | BE27: 0.74881456 | BF27: -0.5427534 | BG27: 0.94944977 | BH27: 3.3975535 | BI27: 3.0266282 | BJ27: 2.7459274 | BK27: 2.3301505 | BL27: 3.7933196 | BM27: -3.1332354 | BN27: 7.8281731 | BO27: 4.083864 | BP27: 1.6815108 | BQ27: 3.3870896 | BR27: 3.0963664
A28: Bahrain | B28: BHR | C28: GDP growth (annual %) | D28: NY.GDP.MKTP.KD.ZG | P28: 1.6071429 | Q28: 11.072056 | R28: 13.924051 | S28: 8.4722222 | T28: -8.8348272 | U28: 30.476297 | V28: 13.01765 | W28: 3.8622686 | X28: 3.469268 | Y28: 2.5802793 | Z28: -5.3166974 | AA28: -7.5562177 | AB28: 6.3763768 | AC28: 5.003646 | AD28: -4.7582685 | AE28: 1.1829939 | AF28: 10.399009 | AG28: 6.9999916 | AH28: 0.36400714 | AI28: 4.4379972 | AJ28: 11.229998 | AK28: 6.6899981 | AL28: 12.870007 | AM28: -0.25000138 | AN28: 3.9299924 | AO28: 4.1100063 | AP28: 3.0929992 | AQ28: 4.7900036 | AR28: 4.2999982 | AS28: 5.3000694 | AT28: 2.4909488 | AU28: 3.3485507 | AV28: 6.2964413 | AW28: 6.9809618 | AX28: 6.7689974 | AY28: 6.4669995 | AZ28: 8.2939613 | BA28: 6.2450109 | BB28: 2.5398857 | BC28: 4.334299 | BD28: 1.9281579 | BE28: 3.803029 | BF28: 5.2926222 | BG28: 4.3088569 | BH28: 2.5078721 | BI28: 3.8149933 | BJ28: 4.9538353 | BK28: 2.0525886 | BL28: 2.0528777 | BM28: -5.911363 | BN28: 4.3500409 | BO28: 6.1801613 | BP28: 3.8781161 | BQ28: 2.8971054 | BR28: 3.4813757
A29: Bahamas, The | B29: BHS | C29: GDP growth (annual %) | D29: NY.GDP.MKTP.KD.ZG | F29: 10.667097 | G29: 10.451972 | H29: 10.524055 | I29: 10.501567 | J29: 10.425596 | K29: 9.0719287 | L29: 9.5981139 | M29: 8.4217636 | N29: 8.9816626 | O29: -5.6496495 | P29: 1.6265087 | Q29: -3.4973359 | R29: 7.5675688 | S29: -16.754229 | T29: -14.803126 | U29: 5.185185 | V29: 9.1549292 | W29: 14.17952 | X29: 26.139296 | Y29: 6.4952819 | Z29: -9.2264051 | AA29: 6.6988977 | AB29: 3.5970519 | AC29: 14.171149 | AD29: 4.8291801 | AE29: 1.7970002 | AF29: 2.9845193 | AG29: 2.3097077 | AH29: 6.7273298 | AI29: -1.5962491 | AJ29: -4.181785 | AK29: -3.8255823 | AL29: 0.3078066 | AM29: 3.148916 | AN29: 4.378752 | AO29: 4.2235304 | AP29: 1.2877532 | AQ29: 4.7167986 | AR29: 7.1441039 | AS29: 4.1484193 | AT29: 2.6260098 | AU29: 2.7049562 | AV29: -1.2649167 | AW29: 0.88237374 | AX29: 3.3960842 | AY29: 2.5165922 | AZ29: 1.4460999 | BA29: -2.3236481 | BB29: -4.1754281 | BC29: 1.5386625 | BD29: 0.61317074 | BE29: 4.5200389 | BF29: -2.8632008 | BG29: 1.8469701 | BH29: 0.99741168 | BI29: -1.1565081 | BJ29: 3.3713988 | BK29: 2.3979551 | BL29: -0.83858587 | BM29: -20.089366 | BN29: 17.586139 | BO29: 10.877901 | BP29: 3.0482418 | BQ29: 3.3786655
A30: Bosnia and Herzegovina | B30: BIH | C30: GDP growth (annual %) | D30: NY.GDP.MKTP.KD.ZG | AJ30: -9.3480254 | AK30: -6.4369076 | AL30: -2.1813473 | AM30: 11.131964 | AN30: 15.968301 | AO30: 54.1993 | AP30: 36.641129 | AQ30: 16.616375 | AR30: 9.52157 | AS30: 5.414316 | AT30: 2.4233131 | AU30: 5.0274446 | AV30: 3.8671355 | AW30: 6.3252679 | AX30: 3.8971832 | AY30: 5.414003 | AZ30: 5.8591169 | BA30: 5.4418473 | BB30: -3.0044555 | BC30: 0.86566724 | BD30: 0.95951171 | BE30: -0.82183725 | BF30: 2.3498587 | BG30: 1.1538479 | BH30: 4.2841302 | BI30: 3.2422582 | BJ30: 3.244099 | BK30: 3.829004 | BL30: 2.8858524 | BM30: -3.0150934 | BN30: 7.3916426 | BO30: 4.2268133 | BP30: 1.9943941 | BQ30: 3.2267998 | BR30: 2.1286191
A31: Belarus | B31: BLR | C31: GDP growth (annual %) | D31: NY.GDP.MKTP.KD.ZG | AJ31: -1.1999957 | AK31: -9.6000011 | AL31: -7.600002 | AM31: -11.700004 | AN31: -10.4 | AO31: 2.8000046 | AP31: 11.400005 | AQ31: 8.3999914 | AR31: 3.3999992 | AS31: 5.8000033 | AT31: 4.7253061 | AU31: 5.0452676 | AV31: 7.0431925 | AW31: 11.449743 | AX31: 9.4000015 | AY31: 9.9999947 | AZ31: 8.6000066 | BA31: 10.199999 | BB31: 0.19999523 | BC31: 7.7500171 | BD31: 5.5499747 | BE31: 1.7078525 | BF31: 0.9987193 | BG31: 1.6511247 | BH31: -3.8295706 | BI31: -2.5264464 | BJ31: 2.5321835 | BK31: 3.1491976 | BL31: 1.4464555 | BM31: -0.67274292 | BN31: 2.4388621 | BO31: -4.6583959 | BP31: 4.1265401 | BQ31: 4.3499964 | BR31: 1.3
A32: Belize | B32: BLZ | C32: GDP growth (annual %) | D32: NY.GDP.MKTP.KD.ZG | F32: 4.892277 | G32: 4.8926523 | H32: 4.9564342 | I32: 4.9998798 | J32: 4.930541 | K32: 4.7708452 | L32: 4.9131232 | M32: 7.3672255 | N32: 5.1063747 | O32: 4.8076934 | P32: 3.9594411 | Q32: 10.218304 | R32: 5.3518941 | S32: 13.559985 | T32: 3.5928244 | U32: -0.034020934 | V32: 6.4965944 | W32: 7.9208072 | X32: 7.5170214 | Y32: 12.10875 | Z32: 1.1332974 | AA32: -0.10672359 | AB32: -2.1474359 | AC32: 1.9761983 | AD32: 1.006424 | AE32: 4.5473818 | AF32: 10.726959 | AG32: 9.7884809 | AH32: 13.010842 | AI32: 11.342943 | AJ32: 11.778703 | AK32: 12.736223 | AL32: 6.1378854 | AM32: -0.019986339 | AN32: 0.73155801 | AO32: 1.1053058 | AP32: 4.2346159 | AQ32: 3.89302 | AR32: 9.4231947 | AS32: 12.240612 | AT32: 4.9935621 | AU32: 5.3990732 | AV32: 9.6652268 | AW32: 4.7806651 | AX32: 2.2191905 | AY32: 4.5114546 | AZ32: 3.3393974 | BA32: -1.6274778 | BB32: -0.44670964 | BC32: 1.417411 | BD32: -0.13007112 | BE32: 3.9438932 | BF32: 4.0664656 | BG32: 3.8922607 | BH32: 2.7602603 | BI32: -0.018741496 | BJ32: -1.8332373 | BK32: 0.82206859 | BL32: 4.2565871 | BM32: -13.5229 | BN32: 17.989924 | BO32: 9.2505133 | BP32: 0.50012794 | BQ32: 3.5046644 | BR32: 2.7483173
A33: Bermuda | B33: BMU | C33: GDP growth (annual %) | D33: NY.GDP.MKTP.KD.ZG | F33: 4.68 | G33: 4.47 | H33: 1.07 | I33: 11.11 | J33: 4.76 | K33: 14.363636 | L33: 13.27504 | M33: 2.1052631 | N33: 3.4364261 | O33: 6.3122923 | P33: 3.4375 | Q33: 1.8126888 | R33: 1.4836795 | S33: 0.87719298 | T33: 3.768116 | U33: 8.9385475 | V33: 5.8974359 | W33: 1.4527845 | X33: 2.1479713 | Y33: 7.9439252 | Z33: 2.3809524 | AA33: -5.2854123 | AB33: 2.0089286 | AC33: 0.48140044 | AD33: -2.0034843 | AE33: 6.6666667 | AF33: 3.75 | AG33: 4.0562249 | AH33: 0.44384409 | AI33: 0.019212285 | AJ33: -3.5343821 | AK33: -0.059738214 | AL33: 3.0085671 | AM33: 0.59961337 | AN33: 4.3991483 | AO33: 2.6004754 | AP33: 4.6000008 | AQ33: 3.9000001 | AR33: 3.382647 | AS33: 9.3171564 | AT33: 7.2224355 | AU33: -1.4777906 | AV33: 3.4107067 | AW33: 2.3212672 | AX33: 1.6742061 | AY33: 5.5438664 | AZ33: 3.3451397 | BA33: -1.8659558 | BB33: -5.6266977 | BC33: -2.5028783 | BD33: -3.7427443 | BE33: -5.3052991 | BF33: -0.27970855 | BG33: -3.7010676 | BH33: 0.7755297 | BI33: -0.6572063 | BJ33: 3.6114198 | BK33: -0.4328013 | BL33: 0.30710646 | BM33: -6.9716257 | BN33: 4.764979 | BO33: 6.2569552 | BP33: 4.3344728 | BQ33: 1.8882286
A34: Bolivia | B34: BOL | C34: GDP growth (annual %) | D34: NY.GDP.MKTP.KD.ZG | F34: 2.0892959 | G34: 5.5789179 | H34: 6.7976258 | I34: 3.9565965 | J34: 4.913442 | K34: 7.1705897 | L34: 6.3172195 | M34: 8.5294431 | N34: 4.4740973 | O34: 5.2310293 | P34: 5.0633364 | Q34: 7.9674852 | R34: 5.7391615 | S34: 2.9395678 | T34: 7.3110177 | U34: 4.6145675 | V34: 4.9712157 | W34: 2.0526946 | X34: 0.13334405 | Y34: -1.3717729 | Z34: 0.27561637 | AA34: -3.9387379 | AB34: -4.0421214 | AC34: -0.2006657 | AD34: -1.6763898 | AE34: -2.5738842 | AF34: 2.4634846 | AG34: 2.909498 | AH34: 3.790131 | AI34: 4.6357874 | AJ34: 5.2665266 | AK34: 1.6464982 | AL34: 4.2692962 | AM34: 4.6672651 | AN34: 4.6782766 | AO34: 4.361342 | AP34: 4.9542087 | AQ34: 5.0293548 | AR34: 0.42688538 | AS34: 2.5078108 | AT34: 1.6837991 | AU34: 2.4855658 | AV34: 2.7113398 | AW34: 4.1732956 | AX34: 4.4214331 | AY34: 4.7970088 | AZ34: 4.5643843 | BA34: 6.1484979 | BB34: 3.3569996 | BC34: 4.1267226 | BD34: 5.2040925 | BE34: 5.1222756 | BF34: 6.7960114 | BG34: 5.4605695 | BH34: 4.8571872 | BI34: 4.2639209 | BJ34: 4.1952063 | BK34: 2.868084 | BL34: 1.506721 | BM34: -12.719469 | BN34: 10.029049 | BO34: 3.7474178 | BP34: 2.5163659 | BQ34: -1.123356 | BR34: -1.5823757
A35: Brazil | B35: BRA | C35: GDP growth (annual %) | D35: NY.GDP.MKTP.KD.ZG | F35: 8.6 | G35: 6.6 | H35: 0.6 | I35: 3.4 | J35: 2.4 | K35: 6.7 | L35: 4.2 | M35: 9.8 | N35: 9.5 | O35: 10.4 | P35: 11.342922 | Q35: 11.940348 | R35: 13.968722 | S35: 8.1539387 | T35: 5.1666491 | U35: 10.25713 | V35: 4.9343281 | W35: 4.9698977 | X35: 6.7595601 | Y35: 9.2 | Z35: -4.25 | AA35: 0.83 | AB35: -2.93 | AC35: 5.4 | AD35: 7.85 | AE35: 7.49 | AF35: 3.53 | AG35: -0.06 | AH35: 3.16 | AI35: -4.35 | AJ35: 1.0321896 | AK35: -0.54407205 | AL35: 4.92469 | AM35: 5.8528704 | AN35: 4.2237936 | AO35: 2.2088641 | AP35: 3.394846 | AQ35: 0.3380979 | AR35: 0.46793757 | AS35: 4.3879494 | AT35: 1.3898964 | AU35: 3.0534619 | AV35: 1.140829 | AW35: 5.7599646 | AX35: 3.2021321 | AY35: 3.9619887 | AZ35: 6.0698706 | BA35: 5.0941954 | BB35: -0.125812 | BC35: 7.5282258 | BD35: 3.9744231 | BE35: 1.921176 | BF35: 3.0048227 | BG35: 0.50395574 | BH35: -3.5457634 | BI35: -3.2759169 | BJ35: 1.3228691 | BK35: 1.7836668 | BL35: 1.2207778 | BM35: -3.2767588 | BN35: 4.7626044 | BO35: 3.0166944 | BP35: 3.2416553 | BQ35: 3.4193152 | BR35: 2.2857465
A36: Barbados | B36: BRB | C36: GDP growth (annual %) | D36: NY.GDP.MKTP.KD.ZG | F36: 7.6965298 | G36: 9.0607586 | H36: -5.0784211 | I36: 5.0048758 | J36: 11.434843 | K36: 4.0033712 | L36: 10.636136 | M36: 6.9218213 | N36: 7.5184048 | O36: 9.509403 | P36: 3.9127224 | Q36: 1.2738007 | R36: 1.3407004 | S36: -4.6508412 | T36: -1.9 | U36: 4.360211 | V36: 3.6422058 | W36: 4.8769393 | X36: 7.8930081 | Y36: 4.3730648 | Z36: -1.8997516 | AA36: -4.9009385 | AB36: 0.50125313 | AC36: 3.6003741 | AD36: 1.0982398 | AE36: 5.1041667 | AF36: 2.590967 | AG36: 3.5053823 | AH36: 3.6 | AI36: -3.3075933 | AJ36: -3.8999072 | AK36: -5.6925208 | AL36: 0.79306884 | AM36: 2.0107821 | AN36: 2.0139983 | AO36: 3.9764759 | AP36: 4.7401036 | AQ36: 3.7284642 | AR36: 0.33465617 | AS36: 4.4471895 | AT36: -2.3654642 | AU36: 0.78740165 | AV36: 2.175481 | AW36: 1.4115979 | AX36: 3.9554571 | AY36: 6.0705468 | AZ36: 2.0791836 | BA36: 0.63346043 | BB36: -5.0172754 | BC36: -8.0807212 | BD36: -0.074211165 | BE36: -2.8579705 | BF36: 0.19532201 | BG36: 0.80732535 | BH36: -0.77262008 | BI36: 1.4163245 | BJ36: 0.6546556 | BK36: -0.25208533 | BL36: 0.24109979 | BM36: -17.405931 | BN36: 8.019877 | BO36: 15.945321 | BP36: 1.8141982 | BQ36: 3.3669493 | BR36: 2.7000002
A37: Brunei Darussalam | B37: BRN | C37: GDP growth (annual %) | D37: NY.GDP.MKTP.KD.ZG | T37: -0.64529158 | U37: 20.87414 | V37: 9.9340348 | W37: 7.0191343 | X37: 24.338389 | Y37: -9.7079602 | Z37: -22.384824 | AA37: 2.30153 | AB37: 0.39937736 | AC37: -2.3765937 | AD37: -2.9072441 | AE37: -5.4072203 | AF37: 2.0835442 | AG37: -1.5358632 | AH37: -2.7262144 | AI37: 2.6430736 | AJ37: 2.910656 | AK37: -3.1206188 | AL37: -0.63364966 | AM37: 0.99273496 | AN37: 1.3472938 | AO37: -0.027315466 | AP37: 6.343945 | AQ37: -6.6571593 | AR37: 4.2607222 | AS37: 3.4746763 | AT37: 1.4660608 | AU37: 3.9614389 | AV37: 3.5834291 | AW37: 0.10453837 | AX37: -0.0039253166 | AY37: 4.0984126 | AZ37: -3.7636233 | BA37: -3.900711 | BB37: -1.9002537 | BC37: 2.7413644 | BD37: 3.7444063 | BE37: 0.91313519 | BF37: -2.1247829 | BG37: -2.5078873 | BH37: -0.39238375 | BI37: -2.4779177 | BJ37: 1.3287266 | BK37: 0.052371042 | BL37: 3.8688444 | BM37: 1.1335733 | BN37: -1.5907626 | BO37: -1.6283315 | BP37: 1.1276442 | BQ37: 4.0525171 | BR37: 0.66956215
A38: Bhutan | B38: BTN | C38: GDP growth (annual %) | D38: NY.GDP.MKTP.KD.ZG | P38: 2.6771005 | Q38: 1.1632571 | R38: 1.4670896 | S38: 5.1582649 | T38: -3.3073207 | U38: 8.9546503 | V38: 7.9012345 | W38: 7.126512 | X38: 4.7909673 | Y38: 5.0087362 | Z38: 15.122295 | AA38: 3.4397739 | AB38: 10.431016 | AC38: 4.556659 | AD38: 4.028533 | AE38: 11.392198 | AF38: 29.054324 | AG38: 4.767373 | AH38: 7.3555673 | AI38: 10.383118 | AJ38: -0.40787572 | AK38: 4.6008912 | AL38: 1.9863666 | AM38: 4.9515037 | AN38: 7.0741175 | AO38: 5.5651729 | AP38: 5.3738385 | AQ38: 5.9140309 | AR38: 7.9839718 | AS38: 3.3550684 | AT38: 7.3283744 | AU38: 10.44378 | AV38: 7.7865604 | AW38: 5.1572574 | AX38: 6.9350715 | AY38: 5.6408052 | AZ38: 16.104784 | BA38: 4.5294488 | BB38: 7.6674924 | BC38: 11.931874 | BD38: 8.4892585 | BE38: 5.1648201 | BF38: 1.7363404 | BG38: 5.8810855 | BH38: 6.6608013 | BI38: 8.4759434 | BJ38: 2.0868452 | BK38: 3.5018719 | BL38: 5.7551485 | BM38: -10.218397 | BN38: 4.4213674 | BO38: 5.2138678 | BP38: 4.632157 | BQ38: 7.4985621 | BR38: 8.0050272
A39: Botswana | B39: BWA | C39: GDP growth (annual %) | D39: NY.GDP.MKTP.KD.ZG | F39: 6.3432837 | G39: 6.6666678 | H39: 5.9210451 | I39: 6.8323009 | J39: 5.8139551 | K39: 6.3440191 | L39: 5.9245599 | M39: 10.567057 | N39: 15.123405 | O39: 17.120268 | P39: 25.821107 | Q39: 26.361941 | R39: 21.303184 | S39: 8.7977952 | T39: 8.4462504 | U39: 10.647377 | V39: 12.01204 | W39: 14.332802 | X39: 12.148589 | Y39: 11.986901 | Z39: 9.0648575 | AA39: 12.165532 | AB39: 13.146729 | AC39: 8.5453836 | AD39: 7.1252713 | AE39: 8.1729243 | AF39: 11.881928 | AG39: 19.44997 | AH39: 13.059406 | AI39: 6.772822 | AJ39: 7.4587092 | AK39: 2.9170702 | AL39: 1.9161071 | AM39: 3.6279162 | AN39: 7.0304102 | AO39: 5.8298 | AP39: 8.3258909 | AQ39: 0.44366359 | AR39: 9.6672407 | AS39: 1.9876958 | AT39: 0.25057395 | AU39: 6.0695309 | AV39: 4.6258947 | AW39: 2.7058217 | AX39: 4.5566457 | AY39: 8.3638711 | AZ39: 5.7925558 | BA39: 3.252073 | BB39: -14.144235 | BC39: 10.119723 | BD39: 6.8384105 | BE39: -0.1708571 | BF39: 11.102907 | BG39: 5.6971442 | BH39: -4.8513251 | BI39: 7.2044248 | BJ39: 4.1143786 | BK39: 4.1886924 | BL39: 3.0317734 | BM39: -8.7288824 | BN39: 11.916272 | BO39: 5.4860171 | BP39: 3.2080681 | BQ39: -2.7798898 | BR39: -0.73389832
A40: Central African Republic | B40: CAF | C40: GDP growth (annual %) | D40: NY.GDP.MKTP.KD.ZG | F40: 4.9535538 | G40: -3.7138002 | H40: -0.70701075 | I40: 2.0803246 | J40: 0.94757871 | K40: 0.64478372 | L40: 4.6766131 | M40: 1.4041132 | N40: 7.0915425 | O40: 2.3328809 | P40: 1.1302024 | Q40: -0.00086717483 | R40: 1.88894 | S40: 6.3390336 | T40: 0.4049871 | U40: 5.432519 | V40: 3.8062349 | W40: 1.2092354 | X40: -2.4651378 | Y40: -4.4786388 | Z40: -1.5444657 | AA40: 7.7157836 | AB40: -8.1265136 | AC40: 9.4817267 | AD40: 3.9272195 | AE40: 3.5779793 | AF40: -4.9389879 | AG40: 1.7101653 | AH40: 1.9772704 | AI40: -2.1475281 | AJ40: -0.55254301 | AK40: -6.4240782 | AL40: 0.33527568 | AM40: 4.8999494 | AN40: 7.2000456 | AO40: -4.000093 | AP40: 5.299936 | AQ40: 4.7001424 | AR40: 3.5999749 | AS40: -2.4894324 | AT40: 4.464739 | AU40: 3.6165422 | AV40: -5.3974852 | AW40: 5.9948842 | AX40: 0.90821051 | AY40: 4.7710854 | AZ40: 4.6075349 | BA40: 2.054131 | BB40: 8.5872604 | BC40: 4.6308184 | BD40: 4.1946153 | BE40: 5.0537613 | BF40: -36.391977 | BG40: 0.081070515 | BH40: 4.337121 | BI40: 4.7503168 | BJ40: 4.5272782 | BK40: 3.7894436 | BL40: 3.1 | BM40: 0.9 | BN40: 0.98292 | BO40: 0.45390188 | BP40: 0.6999684 | BQ40: 1.5 | BR40: 4.4995
A41: Canada | B41: CAN | C41: GDP growth (annual %) | D41: NY.GDP.MKTP.KD.ZG | F41: 3.1632917 | G41: 7.4278373 | H41: 5.2974401 | I41: 6.656 | J41: 6.3171999 | K41: 6.7596901 | L41: 3.0654208 | M41: 5.0082741 | N41: 5.0670324 | O41: 2.9187131 | P41: 4.0188451 | Q41: 5.5196699 | R41: 6.7286415 | S41: 3.3577759 | T41: 1.5454033 | U41: 5.8892759 | V41: 3.5348266 | W41: 3.7359764 | X41: 3.7251995 | Y41: 2.1771992 | Z41: 3.4150652 | AA41: -3.1661503 | AB41: 2.5622537 | AC41: 5.8985695 | AD41: 4.7376807 | AE41: 2.1214809 | AF41: 4.0720157 | AG41: 4.4108391 | AH41: 2.3373298 | AI41: 0.20294785 | AJ41: -2.0910552 | AK41: 0.89046624 | AL41: 2.6577068 | AM41: 4.4940493 | AN41: 2.6823283 | AO41: 1.6889612 | AP41: 4.2801668 | AQ41: 3.8928866 | AR41: 5.1410035 | AS41: 5.1385392 | AT41: 1.8750981 | AU41: 2.9992553 | AV41: 1.8063851 | AW41: 3.0923638 | AX41: 3.2104544 | AY41: 2.6379438 | AZ41: 2.0499046 | BA41: 0.99540637 | BB41: -2.9150863 | BC41: 3.0908063 | BD41: 3.1371944 | BE41: 1.7556613 | BF41: 2.3258136 | BG41: 2.8734668 | BH41: 0.64997101 | BI41: 1.0385509 | BJ41: 3.0338349 | BK41: 2.7429634 | BL41: 1.9084319 | BM41: -5.0382334 | BN41: 5.950528 | BO41: 4.6954199 | BP41: 1.9530855 | BQ41: 2.0462661 | BR41: 1.7426854
A42: Central Europe and the Baltics | B42: CEB | C42: GDP growth (annual %) | D42: NY.GDP.MKTP.KD.ZG | AJ42: -10.872255 | AK42: -4.9353582 | AL42: 0.20890201 | AM42: 3.6884834 | AN42: 5.7117359 | AO42: 4.4861799 | AP42: 2.2351606 | AQ42: 2.6337711 | AR42: 1.9010529 | AS42: 3.9461705 | AT42: 3.0053965 | AU42: 3.5423527 | AV42: 3.9968763 | AW42: 5.8740503 | AX42: 4.9098997 | AY42: 6.6405739 | AZ42: 6.33884 | BA42: 3.96223 | BB42: -3.6222381 | BC42: 1.5384716 | BD42: 3.6005708 | BE42: 0.83797333 | BF42: 0.66790923 | BG42: 3.2619281 | BH42: 4.0016836 | BI42: 2.8072494 | BJ42: 5.1071307 | BK42: 4.9533722 | BL42: 4.0323261 | BM42: -3.3011076 | BN42: 6.5727168 | BO42: 4.0398915 | BP42: 0.7203283 | BQ42: 2.0953401 | BR42: 2.3670116
A43: Switzerland | B43: CHE | C43: GDP growth (annual %) | D43: NY.GDP.MKTP.KD.ZG | F43: 5.6812928 | G43: 4.2590473 | H43: 5.3279338 | I43: 6.8211646 | J43: 3.8215075 | K43: 2.0908442 | L43: 3.3653885 | M43: 3.6385058 | N43: 5.0090752 | O43: 6.4736739 | P43: 0.94464627 | Q43: 2.2887388 | R43: 3.9679811 | S43: 3.1981957 | T43: 2.5528626 | U43: 1.0581047 | V43: -1.5962585 | W43: 1.751548 | X43: 3.8400034 | Y43: 1.6999714 | Z43: 0.45483041 | AA43: 1.2486646 | AB43: 1.9006388 | AC43: 4.2295354 | AD43: 2.1603737 | AE43: 2.6913231 | AF43: 3.3538429 | AG43: 2.5590387 | AH43: 2.6548068 | AI43: 0.75467485 | AJ43: -1.1459748 | AK43: -1.1585927 | AL43: -2.0656163 | AM43: 4.0157659 | AN43: 4.0943899 | AO43: 0.56016692 | AP43: 2.0976168 | AQ43: 2.7761137 | AR43: 1.6800757 | AS43: 3.6332167 | AT43: 1.5921978 | AU43: 0.38041013 | AV43: -0.28422236 | AW43: 2.586929 | AX43: 2.9520849 | AY43: 4.1343225 | AZ43: 3.9831938 | BA43: 2.5315962 | BB43: -1.9349094 | BC43: 3.2606308 | BD43: 1.4076607 | BE43: 1.1241358 | BF43: 1.8361239 | BG43: 2.5434235 | BH43: 1.4545034 | BI43: 1.9115909 | BJ43: 1.4203461 | BK43: 3.3274326 | BL43: 1.1153219 | BM43: -2.2552579 | BN43: 6.1762284 | BO43: 3.5343029 | BP43: 0.82556093 | BQ43: 1.3903336 | BR43: 1.3000779
A44: Channel Islands | B44: CHI | C44: GDP growth (annual %) | D44: NY.GDP.MKTP.KD.ZG | BC44: -3.6066323 | BD44: 1.1250431 | BE44: -5.7536612 | BF44: 0.49393112 | BG44: 2.4271018 | BH44: 0.37436708 | BI44: 1.2130241 | BJ44: 1.8064813 | BK44: 1.1222436 | BL44: 1.573356 | BM44: -8.8967793 | BN44: 9.9368014 | BO44: 5.3419614 | BP44: 3.7150059
A45: Chile | B45: CHL | C45: GDP growth (annual %) | D45: NY.GDP.MKTP.KD.ZG | F45: 5.5196107 | G45: 3.9307848 | H45: 5.6866719 | I45: 2.4611343 | J45: 0.67083864 | K45: 11.463422 | L45: 3.5881107 | M45: 3.573717 | N45: 4.1031798 | O45: 1.6944726 | P45: 9.5710739 | Q45: -0.71236592 | R45: -5.0377561 | S45: 1.24958 | T45: -12.273762 | U45: 3.6046948 | V45: 11.149194 | W45: 8.0268249 | X45: 8.4358218 | Y45: 8.1722833 | Z45: 6.718639 | AA45: -11.502062 | AB45: -4.9352297 | AC45: 3.9837102 | AD45: 3.5523986 | AE45: 5.4055644 | AF45: 6.7388425 | AG45: 7.3508107 | AH45: 10.358357 | AI45: 3.598723 | AJ45: 7.7562019 | AK45: 11.501931 | AL45: 6.6855844 | AM45: 5.0768037 | AN45: 9.2554276 | AO45: 7.1148626 | AP45: 7.3917393 | AQ45: 4.1808866 | AR45: -0.2736314 | AS45: 4.9716215 | AT45: 3.1540349 | AU45: 3.2027991 | AV45: 4.7232453 | AW45: 6.6742542 | AX45: 5.8370457 | AY45: 6.0499908 | AZ45: 5.168231 | BA45: 3.7893928 | BB45: -1.1180372 | BC45: 5.851651 | BD45: 6.2238968 | BE45: 6.15534 | BF45: 3.3085082 | BG45: 1.7926495 | BH45: 2.1519425 | BI45: 1.7530387 | BJ45: 1.3576954 | BK45: 3.9900295 | BL45: 0.6442234 | BM45: -6.1396969 | BN45: 11.337403 | BO45: 2.0639186 | BP45: 0.67702483 | BQ45: 2.8051264 | BR45: 2.4592547
A46: China | B46: CHN | C46: GDP growth (annual %) | D46: NY.GDP.MKTP.KD.ZG | F46: -27.27 | G46: -5.58 | H46: 10.3 | I46: 18.18 | J46: 16.95 | K46: 10.65 | L46: -5.77 | M46: -4.1 | N46: 16.94 | O46: 19.3 | P46: 7.06 | Q46: 3.81 | R46: 7.76 | S46: 2.31 | T46: 8.72 | U46: -1.57 | V46: 7.57 | W46: 11.326954 | X46: 7.5948018 | Y46: 7.8414171 | Z46: 5.1148631 | AA46: 9.0243435 | AB46: 10.771838 | AC46: 15.192135 | AD46: 13.428482 | AE46: 8.9437464 | AF46: 11.655266 | AG46: 11.220912 | AH46: 4.2078569 | AI46: 3.9225196 | AJ46: 9.3756324 | AK46: 14.297623 | AL46: 13.926103 | AM46: 13.082712 | AN46: 11.015414 | AO46: 9.9732878 | AP46: 9.2975946 | AQ46: 7.9235454 | AR46: 7.7412383 | AS46: 8.5735733 | AT46: 8.324047 | AU46: 9.2360487 | AV46: 10.113812 | AW46: 10.140429 | AX46: 11.453513 | AY46: 12.675284 | AZ46: 14.150771 | BA46: 9.6687761 | BB46: 9.4061001 | BC46: 10.59169 | BD46: 9.4620525 | BE46: 7.8578201 | BF46: 7.7784295 | BG46: 7.4610074 | BH46: 6.9816226 | BI46: 6.7736887 | BJ46: 6.8912392 | BK46: 6.7578061 | BL46: 6.0673781 | BM46: 2.3395039 | BN46: 8.5703841 | BO46: 3.1338544 | BP46: 5.4160033 | BQ46: 4.9583038 | BR46: 4.9599489
A47: Cote d'Ivoire | B47: CIV | C47: GDP growth (annual %) | D47: NY.GDP.MKTP.KD.ZG | F47: 9.9325552 | G47: 1.2269945 | H47: 14.490356 | I47: 17.613088 | J47: -3.1096543 | K47: 11.57736 | L47: 4.5981518 | M47: 12.548249 | N47: 9.5392188 | O47: 10.375032 | P47: 9.4566377 | Q47: 4.236625 | R47: 5.9391975 | S47: 4.3273809 | T47: 8.2528864 | U47: 12.916397 | V47: 7.3144592 | W47: 10.909454 | X47: 2.3944075 | Y47: -10.957697 | Z47: 3.5004989 | AA47: 0.20082235 | AB47: -3.9002404 | AC47: -2.7012614 | AD47: 4.5012232 | AE47: 3.2593488 | AF47: -0.34897291 | AG47: 1.136484 | AH47: 2.9480049 | AI47: -1.0959084 | AJ47: 0.040925172 | AK47: -0.24456061 | AL47: -0.1924851 | AM47: 0.81120668 | AN47: 7.1257447 | AO47: 7.7293274 | AP47: 9.64884 | AQ47: 4.2639059 | AR47: 1.16686 | AS47: -0.26578946 | AT47: -2.1540125 | AU47: -2.7305265 | AV47: -4.7258666 | AW47: 3.1850382 | AX47: 0.99606556 | AY47: 2.8155786 | AZ47: 1.1014298 | BA47: 4.782666 | BB47: 3.6033216 | BC47: 6.8480494 | BD47: -5.3704472 | BE47: 7.6204118 | BF47: 10.760213 | BG47: 9.3719999 | BH47: 7.1949494 | BI47: 7.1727596 | BJ47: 7.4107624 | BK47: 4.8431461 | BL47: 6.7213717 | BM47: 0.69972859 | BN47: 7.0625371 | BO47: 6.3998836 | BP47: 6.6000005 | BQ47: 6.0195346 | BR47: 6.5
A48: Cameroon | B48: CMR | C48: GDP growth (annual %) | D48: NY.GDP.MKTP.KD.ZG | F48: 1.1836808 | G48: 3.0415591 | H48: 3.7425503 | I48: 3.5471597 | J48: 2.0260537 | K48: 4.6149556 | L48: -10.912066 | M48: 6.3463239 | N48: 4.9014795 | O48: 3.0920682 | P48: 3.4797078 | Q48: 2.6738433 | R48: 5.3556808 | S48: 10.734262 | T48: 11.245059 | U48: -5.4951384 | V48: 13.739872 | W48: 22.003005 | X48: 6.0351188 | Y48: -1.9652917 | Z48: 17.082682 | AA48: 7.5162026 | AB48: 6.8668306 | AC48: 7.4745725 | AD48: 8.0631617 | AE48: 6.7716631 | AF48: -2.1466502 | AG48: -7.823632 | AH48: -1.8191205 | AI48: -6.1056976 | AJ48: -3.8085994 | AK48: -3.1000032 | AL48: -7.9320666 | AM48: 1.8768092 | AN48: 2.8940014 | AO48: 4.2150721 | AP48: 4.5273138 | AQ48: 4.7255348 | AR48: 4.5113042 | AS48: 3.8324178 | AT48: 4.3242612 | AU48: 4.4770268 | AV48: 5.4531537 | AW48: 7.0488628 | AX48: 2.2282702 | AY48: 3.8095833 | AZ48: 4.327589 | BA48: 2.8476779 | BB48: 2.5792518 | BC48: 2.8990247 | BD48: 3.3792113 | BE48: 4.6259787 | BF48: 4.9955292 | BG48: 5.7198181 | BH48: 5.666953 | BI48: 4.5357942 | BJ48: 3.5411765 | BK48: 3.9555142 | BL48: 3.47506 | BM48: 0.25993292 | BN48: 3.3388575 | BO48: 3.736784 | BP48: 3.3475629 | BQ48: 3.5247231 | BR48: 3.2000002
A49: Congo, Dem. Rep. | B49: COD | C49: GDP growth (annual %) | D49: NY.GDP.MKTP.KD.ZG | F49: -10.851376 | G49: 21.200698 | H49: 5.2139901 | I49: -2.4402236 | J49: 0.99734879 | K49: 6.7754853 | L49: -0.98573866 | M49: 4.3326985 | N49: 9.3288374 | O49: -0.24505658 | P49: 6.0050181 | Q49: 0.15113551 | R49: 8.1372759 | S49: 3.1305859 | T49: -4.981631 | U49: -5.3090021 | V49: 0.7607936 | W49: -5.3452915 | X49: 0.43008826 | Y49: 2.1949129 | Z49: 2.3505241 | AA49: -0.45767761 | AB49: 1.4117037 | AC49: 5.541074 | AD49: 0.46785095 | AE49: 4.7172097 | AF49: 2.6756425 | AG49: 0.47038134 | AH49: -1.2660506 | AI49: -6.5683107 | AJ49: -8.4210515 | AK49: -10.500009 | AL49: -13.469051 | AM49: -3.8999968 | AN49: 0.69999883 | AO49: -1.0231726 | AP49: -5.6170466 | AQ49: -1.624154 | AR49: -4.2701408 | AS49: -6.9109273 | AT49: -2.100173 | AU49: 2.9477652 | AV49: 5.5778223 | AW49: 6.7383739 | AX49: 6.1351512 | AY49: 5.1089443 | AZ49: 8.583323 | BA49: 7.4333357 | BB49: 0.5415702 | BC49: 8.6186772 | BD49: -0.40316408 | BE49: 8.6685936 | BF49: 17.515912 | BG49: 7.3022775 | BH49: 6.3597376 | BI49: 0.3938328 | BJ49: 4.2412105 | BK49: 6.0716887 | BL49: 0.55538429 | BM49: 0.77542799 | BN49: 6.4296101 | BO49: 9.3111694 | BP49: 8.5334898 | BQ49: 6.1025294 | BR49: 5.7592447
A50: Congo, Rep. | B50: COG | C50: GDP growth (annual %) | D50: NY.GDP.MKTP.KD.ZG | F50: 8.3507267 | G50: 5.2023088 | H50: -4.0293004 | I50: 3.8167963 | J50: 3.6764677 | K50: 1.3589825 | L50: 2.1162721 | M50: 7.6313262 | N50: 7.5485252 | O50: 6.3584702 | P50: 7.7530359 | Q50: 8.6175508 | R50: 8.2311889 | S50: 7.8855208 | T50: 7.7315968 | U50: 0.91628675 | V50: -8.953428 | W50: 6.359747 | X50: 9.8132247 | Y50: 17.636605 | Z50: 17.619722 | AA50: 23.5977 | AB50: 5.8539628 | AC50: 6.9761311 | AD50: -1.1856609 | AE50: -6.8615264 | AF50: 0.18937664 | AG50: 1.7662634 | AH50: 2.5998765 | AI50: 1.0000036 | AJ50: 2.3953675 | AK50: 2.6119481 | AL50: -0.97968321 | AM50: -5.4930757 | AN50: 3.9853244 | AO50: 4.2904816 | AP50: -0.62481215 | AQ50: 3.7375528 | AR50: -2.5821994 | AS50: 7.5759804 | AT50: 3.8026019 | AU50: 4.5818701 | AV50: 0.81326408 | AW50: 3.4766316 | AX50: 7.755759 | AY50: 7.9862384 | AZ50: -6.6139948 | BA50: 6.306376 | BB50: 11.637289 | BC50: 9.9312654 | BD50: 2.2059194 | BE50: 9.9471531 | BF50: -0.71243445 | BG50: 6.6460654 | BH50: 0.41519306 | BI50: -8.6852434 | BJ50: -5.5947737 | BK50: -2.3043178 | BL50: 1.1244739 | BM50: -6.2677723 | BN50: 1.0150704 | BO50: 1.4753561 | BP50: 1.9068643 | BQ50: 2.0999892 | BR50: 3.0829273
A51: Colombia | B51: COL | C51: GDP growth (annual %) | D51: NY.GDP.MKTP.KD.ZG | F51: 5.089217 | G51: 5.4118896 | H51: 3.2867076 | I51: 6.1669413 | J51: 3.6000114 | K51: 5.2367359 | L51: 4.1348642 | M51: 5.933118 | N51: 6.1025173 | O51: 6.207797 | P51: 5.9607279 | Q51: 7.6691475 | R51: 6.722955 | S51: 5.7457572 | T51: 2.3232553 | U51: 4.7283687 | V51: 4.1585055 | W51: 8.4699008 | X51: 5.379119 | Y51: 4.0873537 | Z51: 2.2768727 | AA51: 0.94842079 | AB51: 1.573956 | AC51: 3.3506837 | AD51: 3.1071062 | AE51: 5.8240761 | AF51: 5.3689321 | AG51: 4.0641732 | AH51: 3.4140961 | AI51: 4.2819983 | AJ51: 2.0016076 | AK51: 4.0449294 | AL51: 5.3854099 | AM51: 5.8146619 | AN51: 5.2024376 | AO51: 2.0558547 | AP51: 3.4302937 | AQ51: 0.56978409 | AR51: -4.2040152 | AS51: 2.9248615 | AT51: 1.6778983 | AU51: 2.5039805 | AV51: 3.9182719 | AW51: 5.3330221 | AX51: 4.8287611 | AY51: 6.7168687 | AZ51: 6.7381947 | BA51: 3.2834462 | BB51: 1.1396486 | BC51: 4.494659 | BD51: 6.947892 | BE51: 3.9126358 | BF51: 5.1339935 | BG51: 4.49903 | BH51: 2.9559014 | BI51: 2.0873825 | BJ51: 1.3593609 | BK51: 2.5643243 | BL51: 3.1868554 | BM51: -7.1859141 | BN51: 10.801198 | BO51: 7.3282773 | BP51: 0.84181956 | BQ51: 1.4933073 | BR51: 2.6420155
A52: Comoros | B52: COM | C52: GDP growth (annual %) | D52: NY.GDP.MKTP.KD.ZG | Z52: 5.4619846 | AA52: 4.0579055 | AB52: 3.0930634 | AC52: 4.1665448 | AD52: 2.7791354 | AE52: 2.071035 | AF52: 2.077744 | AG52: 4.9705961 | AH52: -0.91705981 | AI52: 7.338811 | AJ52: -6.1669745 | AK52: 7.3580153 | AL52: 2.5473458 | AM52: -3.9865175 | AN52: 5.6372793 | AO52: -0.51036883 | AP52: 4.4104256 | AQ52: 0.025040799 | AR52: 2.6976865 | AS52: -1.0070189 | AT52: 5.4195997 | AU52: 4.5976826 | AV52: 1.9344281 | AW52: 3.1004121 | AX52: 5.6652024 | AY52: -1.7544468 | AZ52: 0.80359979 | BA52: 3.9646112 | BB52: 3.2407407 | BC52: 3.7777667 | BD52: 4.1435067 | BE52: 3.1684099 | BF52: 4.4662473 | BG52: 2.1066576 | BH52: 1.1473563 | BI52: 3.3204466 | BJ52: 3.8157629 | BK52: 3.6424511 | BL52: 1.7607802 | BM52: -0.19555684 | BN52: 2.0424524 | BO52: 2.4538117 | BP52: 3.1866132 | BQ52: 3.300715 | BR52: 3.7544428
A53: Cabo Verde | B53: CPV | C53: GDP growth (annual %) | D53: NY.GDP.MKTP.KD.ZG | Z53: 8.4515624 | AA53: 2.8250301 | AB53: 9.5207498 | AC53: 3.7832707 | AD53: 8.6420866 | AE53: 2.8714554 | AF53: 4.3090637 | AG53: 5.9968549 | AH53: 5.6979494 | AI53: 0.69217187 | AJ53: 1.404147 | AK53: 10.937647 | AL53: 8.7083116 | AM53: 19.182642 | AN53: 14.211636 | AO53: 11.346525 | AP53: 11.118426 | AQ53: 12.517286 | AR53: 11.222648 | AS53: 14.284869 | AT53: 2.2316545 | AU53: 5.2508912 | AV53: 4.1762593 | AW53: 10.197073 | AX53: 6.912458 | AY53: 7.9837504 | AZ53: 15.170688 | BA53: 7.0390113 | BB53: -1.5035867 | BC53: 1.8364191 | BD53: 3.9247182 | BE53: 1.0836485 | BF53: 0.63213673 | BG53: 0.69666684 | BH53: 0.93602651 | BI53: 4.2807148 | BJ53: 4.5513148 | BK53: 3.7069646 | BL53: 6.9478263 | BM53: -20.805276 | BN53: 7.0335301 | BO53: 15.843676 | BP53: 4.7947614 | BQ53: 6.9888828 | BR53: 6.2969852
A54: Costa Rica | B54: CRI | C54: GDP growth (annual %) | D54: NY.GDP.MKTP.KD.ZG | F54: 1.8792766 | G54: 5.4423914 | H54: 6.8989234 | I54: 3.6590483 | J54: 8.1905276 | K54: 6.969319 | L54: 5.6501259 | M54: 8.4733043 | N54: 5.4917999 | O54: 7.5031343 | P54: 6.7785054 | Q54: 8.1780451 | R54: 7.7089158 | S54: 5.5449 | T54: 2.100071 | U54: 5.5175644 | V54: 8.9044744 | W54: 6.2676868 | X54: 4.939124 | Y54: 0.7518954 | Z54: -2.2616555 | AA54: -7.2855688 | AB54: 2.8629927 | AC54: 8.0241079 | AD54: 0.72160173 | AE54: 5.5362508 | AF54: 4.7645333 | AG54: 3.4321474 | AH54: 5.6659755 | AI54: 3.5530634 | AJ54: 2.265655 | AK54: 9.2011036 | AL54: 7.0971909 | AM54: 4.5190284 | AN54: 4.1539533 | AO54: 1.3504595 | AP54: 5.476166 | AQ54: 7.0885373 | AR54: 4.1478005 | AS54: 3.8020721 | AT54: 3.4911701 | AU54: 3.4168762 | AV54: 4.31718 | AW54: 4.4245998 | AX54: 3.9766663 | AY54: 7.3266951 | AZ54: 8.2151321 | BA54: 4.7381751 | BB54: -0.87345609 | BC54: 5.3603435 | BD54: 4.4031592 | BE54: 4.8825925 | BF54: 2.494766 | BG54: 3.54211 | BH54: 3.6520809 | BI54: 4.2043232 | BJ54: 4.1576991 | BK54: 2.8528596 | BL54: 2.7081391 | BM54: -4.1415934 | BN54: 8.2181795 | BO54: 5.4611946 | BP54: 4.7918773 | BQ54: 4.0829244 | BR54: 4.5603355
A55: Caribbean small states | B55: CSS | C55: GDP growth (annual %) | D55: NY.GDP.MKTP.KD.ZG | F55: 9.6550926 | G55: 5.3945186 | H55: 2.1159508 | I55: 8.0851993 | J55: 7.1140295 | K55: 6.8758518 | L55: 6.6925699 | M55: 6.1663781 | N55: 5.9491813 | O55: 2.1771611 | P55: 2.3664323 | Q55: 1.028954 | R55: 2.4547449 | S55: -2.9308893 | T55: -1.7143377 | U55: 5.3450136 | V55: 6.6981819 | W55: 7.9400071 | X55: 7.4636177 | Y55: 5.1892556 | Z55: 0.35353773 | AA55: 0.47219666 | AB55: -3.5641728 | AC55: 1.9367352 | AD55: 1.0824863 | AE55: 1.3719294 | AF55: 0.15892405 | AG55: 1.7354845 | AH55: 3.1863742 | AI55: -0.34280647 | AJ55: -0.073596993 | AK55: 2.0157186 | AL55: 0.46446231 | AM55: 3.3308731 | AN55: 3.0782573 | AO55: 4.91095 | AP55: 4.6149029 | AQ55: 4.9139559 | AR55: 5.0431692 | AS55: 4.6905109 | AT55: 2.0850236 | AU55: 3.9726349 | AV55: 6.0851685 | AW55: 4.6489099 | AX55: 4.3936838 | AY55: 7.8259368 | AZ55: 3.8406602 | BA55: 1.6960599 | BB55: -3.3977581 | BC55: 1.1833609 | BD55: 0.91456819 | BE55: 4.1141902 | BF55: 1.5687013 | BG55: 2.5973483 | BH55: -0.064034307 | BI55: -3.0873982 | BJ55: -0.75065575 | BK55: 1.3101614 | BL55: 0.86508902 | BM55: -9.2732685 | BN55: 7.2364047 | BO55: 14.741356 | BP55: 8.8051466 | BQ55: 13.328165 | BR55: 7.9750557
A56: Cuba | B56: CUB | C56: GDP growth (annual %) | D56: NY.GDP.MKTP.KD.ZG | P56: 8.583859 | Q56: 4.8266858 | R56: 3.4344885 | S56: 0.98449182 | T56: 9.4764261 | U56: 5.4279605 | V56: 8.7095029 | W56: 6.5959986 | X56: 1.0881833 | Y56: -4.849443 | Z56: 19.688334 | AA56: 8.918235 | AB56: 5.4114707 | AC56: 7.9297165 | AD56: 1.5966746 | AE56: 0.095303386 | AF56: -2.4021725 | AG56: 3.7055399 | AH56: 0.68008323 | AI56: -2.9485649 | AJ56: -10.692697 | AK56: -11.580603 | AL56: -14.878181 | AM56: 0.71693031 | AN56: 2.4572012 | AO56: 7.8387497 | AP56: 2.783425 | AQ56: 0.15914605 | AR56: 6.1887553 | AS56: 5.9147602 | AT56: 3.1850299 | AU56: 1.4248213 | AV56: 3.7927402 | AW56: 5.7705381 | AX56: 11.201656 | AY56: 12.065863 | AZ56: 7.262137 | BA56: 4.116828 | BB56: 1.4513054 | BC56: 2.3903523 | BD56: 2.8023008 | BE56: 3.0149003 | BF56: 2.7476026 | BG56: 1.0475766 | BH56: 4.4383336 | BI56: 0.5128431 | BJ56: 1.8097918 | BK56: 2.2479485 | BL56: -0.16308722 | BM56: -10.949436 | BN56: 1.2544874 | BO56: 1.7746523 | BP56: -1.9293712 | BQ56: -1.0617327
A57: Curacao | B57: CUW | C57: GDP growth (annual %) | D57: NY.GDP.MKTP.KD.ZG | AT57: -0.6957537 | AU57: 0.39706522 | AV57: 0.28818668 | AW57: 0.20846107 | AX57: 0.67642535 | AY57: 1.6359347 | AZ57: 2.4699632 | BA57: 2.1880431 | BB57: -0.53130824 | BC57: 0.082306609 | BD57: 0.50845748 | BE57: -0.34895082 | BF57: -0.63569691 | BG57: -0.63739737 | BH57: 0.45815154 | BI57: -1.0677085 | BJ57: -1.2762081 | BK57: -2.1041113 | BL57: -3.2061323 | BM57: -18.43847 | BN57: 4.1837102 | BO57: 6.9060006 | BP57: 4.2019993 | BQ57: 5.0269002
A58: Cayman Islands | B58: CYM | C58: GDP growth (annual %) | D58: NY.GDP.MKTP.KD.ZG | AZ58: 3.1626252 | BA58: -0.3574012 | BB58: -7.2004824 | BC58: -2.7156353 | BD58: 1.1690622 | BE58: 1.2297537 | BF58: 1.279331 | BG58: 2.654528 | BH58: 2.8331222 | BI58: 3.2399743 | BJ58: 3.1840459 | BK58: 4.2672675 | BL58: 3.9156353 | BM58: -4.954807 | BN58: 4.8694166 | BO58: 5.6607937 | BP58: 5.8043696 | BQ58: 3.756412
A59: Cyprus | B59: CYP | C59: GDP growth (annual %) | D59: NY.GDP.MKTP.KD.ZG | U59: 20.266292 | V59: 16.362001 | W59: 7.7774034 | X59: 9.9055694 | Y59: 5.7532447 | Z59: 2.5169985 | AA59: 6.021709 | AB59: 5.5821817 | AC59: 8.7578944 | AD59: 4.8825408 | AE59: 3.7039503 | AF59: 7.0652508 | AG59: 8.6467779 | AH59: 7.9474255 | AI59: 7.4039995 | AJ59: 0.73950143 | AK59: 9.3999983 | AL59: 0.70000077 | AM59: 5.8999993 | AN59: 8.3624689 | AO59: 1.2485415 | AP59: 2.6409307 | AQ59: 6.1108829 | AR59: 4.9979547 | AS59: 5.9653045 | AT59: 3.9525626 | AU59: 3.7229749 | AV59: 2.6232996 | AW59: 5.0262723 | AX59: 4.8529876 | AY59: 4.7137836 | AZ59: 5.0982261 | BA59: 3.6469892 | BB59: -2.015082 | BC59: 2.282671 | BD59: 0.41671187 | BE59: -3.4473815 | BF59: -6.5874775 | BG59: -1.7760587 | BH59: 3.4189204 | BI59: 6.5735908 | BJ59: 5.7508324 | BK59: 6.2716636 | BL59: 5.8755958 | BM59: -3.2206302 | BN59: 11.397559 | BO59: 8.7385468 | BP59: 3.6204537 | BQ59: 3.9407693 | BR59: 3.7732535
A60: Czechia | B60: CZE | C60: GDP growth (annual %) | D60: NY.GDP.MKTP.KD.ZG | AJ60: -11.614942 | AK60: -0.50654234 | AL60: 0.061904242 | AM60: 2.9093095 | AN60: 6.221406 | AO60: 4.1685843 | AP60: -0.59583841 | AQ60: -0.39315019 | AR60: 1.3783606 | AS60: 4.0106696 | AT60: 2.9172195 | AU60: 1.5134595 | AV60: 3.3008368 | AW60: 4.7363397 | AX60: 6.3750289 | AY60: 6.623173 | AZ60: 5.488826 | BA60: 2.6122681 | BB60: -4.7983242 | BC60: 2.7146651 | BD60: 1.7723809 | BE60: -0.77066819 | BF60: -0.041812416 | BG60: 2.2452122 | BH60: 4.9587585 | BI60: 2.5808701 | BJ60: 5.1735653 | BK60: 2.8303059 | BL60: 3.5657766 | BM60: -5.3048796 | BN60: 4.0290183 | BO60: 2.8471707 | BP60: 0.047580331 | BQ60: 1.251311 | BR60: 2.5804667
A61: Germany | B61: DEU | C61: GDP growth (annual %) | D61: NY.GDP.MKTP.KD.ZG | F61: 4.2984395 | G61: 4.623471 | H61: 2.7352964 | I61: 6.6394699 | J61: 5.244164 | K61: 2.8121813 | L61: -0.33025645 | M61: 5.6687731 | N61: 7.4181027 | O61: 5.1031446 | P61: 3.1326998 | Q61: 4.3003413 | R61: 4.7774869 | S61: 0.8900687 | T61: -0.86673894 | U61: 4.9492584 | V61: 3.3472181 | W61: 3.0084929 | X61: 4.1503633 | Y61: 1.4088286 | Z61: 0.52924054 | AA61: -0.39484074 | AB61: 1.5724101 | AC61: 2.8229478 | AD61: 2.3279352 | AE61: 2.2873393 | AF61: 1.4021516 | AG61: 3.7072357 | AH61: 3.8965517 | AI61: 5.2550061 | AJ61: 5.1082615 | AK61: 2.0136134 | AL61: -0.97303308 | AM61: 2.5968557 | AN61: 1.5049938 | AO61: 1.0378756 | AP61: 1.8543224 | AQ61: 2.0956123 | AR61: 2.1295702 | AS61: 2.8765231 | AT61: 1.6361417 | AU61: -0.22825572 | AV61: -0.52980139 | AW61: 1.1620868 | AX61: 0.88548529 | AY61: 3.8666824 | AZ61: 2.8891174 | BA61: 0.88790233 | BB61: -5.5445545 | BC61: 4.1346378 | BD61: 3.7579688 | BE61: 0.46351204 | BF61: 0.39699558 | BG61: 2.180186 | BH61: 1.663006 | BI61: 2.2222222 | BJ61: 2.7979067 | BK61: 1.135696 | BL61: 0.9777347 | BM61: -4.1319144 | BN61: 3.9099999 | BO61: 1.8092581 | BP61: -0.86964758 | BQ61: -0.4958519 | BR61: 0.23957834
A62: Djibouti | B62: DJI | C62: GDP growth (annual %) | D62: NY.GDP.MKTP.KD.ZG | BG62: 7.1929873 | BH62: 7.3089856 | BI62: 7.1234323 | BJ62: 5.4580915 | BK62: 4.7743393 | BL62: 5.5450808 | BM62: 1.2021152 | BN62: 4.4071567 | BO62: 5.166537 | BP62: 6.8073353 | BQ62: 6.9804847 | BR62: 6.4954611
A63: Dominica | B63: DMA | C63: GDP growth (annual %) | D63: NY.GDP.MKTP.KD.ZG | W63: 10.535746 | X63: -18.359285 | Y63: 13.383182 | Z63: 10.829331 | AA63: 4.1276835 | AB63: 2.5563179 | AC63: 4.1966469 | AD63: 1.4209332 | AE63: 7.0733566 | AF63: 6.307561 | AG63: 7.816623 | AH63: -0.1911364 | AI63: 5.4179835 | AJ63: 1.3477692 | AK63: 2.0294134 | AL63: 2.1614214 | AM63: 0.034477527 | AN63: 3.0308659 | AO63: 3.1041957 | AP63: 2.1856274 | AQ63: 3.7742304 | AR63: 0.35407766 | AS63: 2.3402194 | AT63: -0.063843443 | AU63: -3.0874205 | AV63: 5.8049547 | AW63: 4.0978366 | AX63: 0.91528647 | AY63: 4.4007748 | AZ63: 5.3579376 | BA63: 7.1213122 | BB63: -1.1357515 | BC63: -0.10561086 | BD63: 0.042738888 | BE63: -0.15739179 | BF63: 0.0045039973 | BG63: 2.3352174 | BH63: -3.3733826 | BI63: 1.4472456 | BJ63: -7.5443638 | BK63: 2.9640106 | BL63: 3.9480976 | BM63: -15.706402 | BN63: 5.3798384 | BO63: 10.396808 | BP63: 3.6522101 | BQ63: 2.0527385 | BR63: 3.0524376
A64: Denmark | B64: DNK | C64: GDP growth (annual %) | D64: NY.GDP.MKTP.KD.ZG | F64: 6.3788324 | G64: 5.6668221 | H64: 0.63702122 | I64: 9.2699382 | J64: 4.5552549 | K64: 2.7409101 | L64: 5.8862312 | M64: 5.8529974 | N64: 6.7991205 | O64: 1.8560017 | P64: 3.1778217 | Q64: 3.7975982 | R64: 4.7194929 | S64: -0.96426738 | T64: -1.4098995 | U64: 5.993402 | V64: 1.9854303 | W64: 2.4169935 | X64: 4.0532998 | Y64: -0.75143 | Z64: -0.74098639 | AA64: 3.8921125 | AB64: 2.6548039 | AC64: 4.3393451 | AD64: 4.1530838 | AE64: 4.7334061 | AF64: 0.46295583 | AG64: 0.27295112 | AH64: 0.69717321 | AI64: 1.6602677 | AJ64: 1.4581801 | AK64: 2.0228112 | AL64: -0.078900413 | AM64: 5.2946962 | AN64: 3.0380215 | AO64: 2.8957507 | AP64: 3.1684814 | AQ64: 2.3263027 | AR64: 2.9673054 | AS64: 3.724009 | AT64: 0.95003225 | AU64: 0.45653002 | AV64: 0.44109101 | AW64: 2.7763518 | AX64: 2.3596088 | AY64: 3.8164877 | AZ64: 0.98717382 | BA64: -0.41717844 | BB64: -4.9744791 | BC64: 1.582897 | BD64: 1.3108038 | BE64: -0.0054323016 | BF64: 1.3926734 | BG64: 1.2779998 | BH64: 2.1044146 | BI64: 3.0730455 | BJ64: 3.0564772 | BK64: 1.8600075 | BL64: 1.7114009 | BM64: -1.780106 | BN64: 6.5002545 | BO64: 0.44383261 | BP64: 0.60458777 | BQ64: 3.4778359 | BR64: 2.9284328
A65: Dominican Republic | B65: DOM | C65: GDP growth (annual %) | D65: NY.GDP.MKTP.KD.ZG | F65: -2.3132487 | G65: 17.047241 | H65: 6.5029026 | I65: 6.7648651 | J65: -12.481834 | K65: 13.463345 | L65: 3.3275423 | M65: 0.23886048 | N65: 10.891446 | O65: 18.226683 | P65: 10.871466 | Q65: 10.394164 | R65: 12.895764 | S65: 6.0019029 | T65: 5.1932534 | U65: 6.7281226 | V65: 4.981784 | W65: 2.1406847 | X65: 4.5313992 | Y65: 7.9687385 | Z65: 4.2798675 | AA65: 1.6987086 | AB65: 4.6279463 | AC65: 1.252896 | AD65: -2.122535 | AE65: 3.5219932 | AF65: 10.117367 | AG65: 2.1559633 | AH65: 4.4005388 | AI65: -5.4543124 | AJ65: 0.94413889 | AK65: 11.237464 | AL65: 7.3666953 | AM65: 2.5937831 | AN65: 5.6999886 | AO65: 5.9611932 | AP65: 8.8995523 | AQ65: 6.7058557 | AR65: 5.9565102 | AS65: 4.6517255 | AT65: 2.4693702 | AU65: 4.4865037 | AV65: -1.3493574 | AW65: 2.5855667 | AX65: 9.4317893 | AY65: 9.1712065 | AZ65: 7.4184058 | BA65: 3.2680867 | BB65: 1.0034529 | BC65: 8.4011454 | BD65: 3.1919623 | BE65: 2.775671 | BF65: 4.934733 | BG65: 7.1112263 | BH65: 6.9877113 | BI65: 6.7197408 | BJ65: 3.9338618 | BK65: 7.0975164 | BL65: 4.8940301 | BM65: -7.9290523 | BN65: 14.012429 | BO65: 5.2379565 | BP65: 2.1922985 | BQ65: 4.953522 | BR65: 2.1173911
A66: Algeria | B66: DZA | C66: GDP growth (annual %) | D66: NY.GDP.MKTP.KD.ZG | F66: -13.605441 | G66: -19.685042 | H66: 34.313729 | I66: 5.839413 | J66: 6.2068982 | K66: -4.8049709 | L66: 9.4529626 | M66: 10.796239 | N66: 8.4332803 | O66: 8.8626571 | P66: -11.331719 | Q66: 27.423969 | R66: 3.8131763 | S66: 7.4949177 | T66: 5.0453416 | U66: 8.3867565 | V66: 5.258586 | W66: 9.2148357 | X66: 7.4778266 | Y66: 0.79060697 | Z66: 2.9999961 | AA66: 6.4000041 | AB66: 5.400003 | AC66: 5.5999965 | AD66: 3.6999973 | AE66: 0.400001 | AF66: -0.69999753 | AG66: -1.0000055 | AH66: 4.4000022 | AI66: 0.80000058 | AJ66: -1.2000006 | AK66: 1.8000023 | AL66: -2.1000008 | AM66: -0.89999655 | AN66: 3.7999948 | AO66: 4.0999985 | AP66: 1.0999999 | AQ66: 5.1000036 | AR66: 3.2000016 | AS66: 3.8 | AT66: 3 | AU66: 5.4 | AV66: 6.5 | AW66: 4.5 | AX66: 5.4 | AY66: 2.9 | AZ66: 3.1 | BA66: 2.5 | BB66: 1.2 | BC66: 4.8 | BD66: 3 | BE66: 2.4 | BF66: 2.6 | BG66: 4.1 | BH66: 3.2 | BI66: 3.9 | BJ66: 1.5 | BK66: 1.4 | BL66: 0.9 | BM66: -5 | BN66: 3.8 | BO66: 3.6 | BP66: 4.1 | BQ66: 3.7 | BR66: 3.8155437
A67: East Asia & Pacific (excluding high income) | B67: EAP | C67: GDP growth (annual %) | D67: NY.GDP.MKTP.KD.ZG | F67: -13.434405 | G67: -0.67188257 | H67: 6.4628902 | I67: 10.831423 | J67: 10.823223 | K67: 8.0210384 | L67: -1.4521453 | M67: 1.732843 | N67: 11.420868 | O67: 13.481923 | P67: 6.775984 | Q67: 4.8957078 | R67: 8.2629059 | S67: 3.9205442 | T67: 6.7221171 | U67: 2.7561905 | V67: 7.4712127 | W67: 9.1883933 | X67: 7.0187505 | Y67: 7.4702544 | Z67: 5.5748919 | AA67: 6.4258938 | AB67: 7.7048184 | AC67: 9.9991764 | AD67: 7.927628 | AE67: 7.1495049 | AF67: 9.1921181 | AG67: 9.7752673 | AH67: 5.686945 | AI67: 5.1423831 | AJ67: 8.1033788 | AK67: 11.249763 | AL67: 11.312417 | AM67: 10.955443 | AN67: 9.9252464 | AO67: 9.1042671 | AP67: 7.402971 | AQ67: 3.0054559 | AR67: 6.4542453 | AS67: 7.7194807 | AT67: 6.9886487 | AU67: 8.1495626 | AV67: 9.0206543 | AW67: 9.1558261 | AX67: 10.0458 | AY67: 11.070699 | AZ67: 12.452242 | BA67: 8.6476184 | BB67: 8.0186833 | BC67: 9.8941409 | BD67: 8.5853345 | BE67: 7.5804387 | BF67: 7.3172353 | BG67: 7.0222319 | BH67: 6.6637282 | BI67: 6.5085287 | BJ67: 6.6666653 | BK67: 6.5380045 | BL67: 5.8848923 | BM67: 1.3434086 | BN67: 7.7202304 | BO67: 3.5491773 | BP67: 5.2601416 | BQ67: 4.9540748 | BR67: 4.9444936
A68: Early-demographic dividend | B68: EAR | C68: GDP growth (annual %) | D68: NY.GDP.MKTP.KD.ZG | F68: 4.7440352 | G68: 4.1731131 | H68: 5.2749778 | I68: 8.451812 | J68: 6.0844323 | K68: 4.2421493 | L68: 5.571124 | M68: 7.2308367 | N68: 6.5580392 | O68: 8.4086139 | P68: 5.3276591 | Q68: 6.649462 | R68: 7.0496137 | S68: 6.7895141 | T68: 2.8949808 | U68: 7.0113099 | V68: 4.0259014 | W68: 2.1701521 | X68: 4.0553503 | Y68: 3.2112902 | Z68: 3.6314566 | AA68: 0.52311604 | AB68: 0.31748814 | AC68: 2.1293368 | AD68: 1.0353973 | AE68: 1.535826 | AF68: 2.9241583 | AG68: 3.2406338 | AH68: 1.9745866 | AI68: 5.0873745 | AJ68: 4.4057062 | AK68: 4.1238974 | AL68: 3.517177 | AM68: 3.3485641 | AN68: 2.527258 | AO68: 5.7025272 | AP68: 4.9695553 | AQ68: 2.396186 | AR68: 2.225737 | AS68: 4.3651034 | AT68: 1.2136673 | AU68: 1.7546532 | AV68: 4.9495059 | AW68: 6.3658655 | AX68: 5.9700182 | AY68: 6.1426496 | AZ68: 5.7703888 | BA68: 3.4904143 | BB68: 0.65585189 | BC68: 6.3805945 | BD68: 4.9581988 | BE68: 4.2332883 | BF68: 4.038483 | BG68: 3.9942269 | BH68: 4.2526576 | BI68: 4.1471061 | BJ68: 4.4900066 | BK68: 3.6128098 | BL68: 2.2726362 | BM68: -4.2834268 | BN68: 7.5068956 | BO68: 6.0242918 | BP68: 4.1233602 | BQ68: 3.8615587 | BR68: 4.372164
A69: East Asia & Pacific | B69: EAS | C69: GDP growth (annual %) | D69: NY.GDP.MKTP.KD.ZG | F69: 3.8410097 | G69: 5.4621918 | H69: 7.7715706 | I69: 10.413268 | J69: 6.9718456 | K69: 8.6257529 | L69: 7.3620558 | M69: 9.3417895 | N69: 11.490683 | O69: 3.8823409 | P69: 5.2804932 | Q69: 7.1708251 | R69: 7.671523 | S69: 1.0046718 | T69: 3.5485102 | U69: 4.1810888 | V69: 5.198625 | W69: 5.7986815 | X69: 5.9290939 | Y69: 3.743183 | Z69: 4.6052693 | AA69: 4.1711973 | AB69: 4.3686725 | AC69: 6.2113063 | AD69: 5.7476612 | AE69: 4.9424626 | AF69: 6.3207448 | AG69: 7.6812524 | AH69: 5.1116672 | AI69: 5.1078877 | AJ69: 4.8342448 | AK69: 4.2257203 | AL69: 4.1779274 | AM69: 5.2026059 | AN69: 5.5615097 | AO69: 5.6173695 | AP69: 4.2637742 | AQ69: 0.26936396 | AR69: 3.7910713 | AS69: 5.5325027 | AT69: 3.2646662 | AU69: 4.443114 | AV69: 4.9217097 | AW69: 5.8618876 | AX69: 5.9586676 | AY69: 6.522059 | AZ69: 7.5405978 | BA69: 4.428395 | BB69: 2.5280348 | BC69: 7.6250792 | BD69: 5.3820868 | BE69: 5.2647711 | BF69: 5.2682534 | BG69: 4.9189378 | BH69: 4.7589033 | BI69: 4.6311469 | BJ69: 5.0366702 | BK69: 4.8120031 | BL69: 4.040906 | BM69: -0.090665175 | BN69: 6.4803764 | BO69: 3.0515588 | BP69: 4.0711955 | BQ69: 3.7253417 | BR69: 3.9973414
A70: Europe & Central Asia (excluding high income) | B70: ECA | C70: GDP growth (annual %) | D70: NY.GDP.MKTP.KD.ZG | AG70: 3.3225121 | AH70: 1.2541602 | AI70: 2.7655825 | AJ70: -4.6594196 | AK70: -4.7351933 | AL70: -2.0274642 | AM70: -9.9672484 | AN70: 0.94773813 | AO70: 3.81186 | AP70: 5.469461 | AQ70: 2.0606691 | AR70: -1.1103391 | AS70: 6.7961143 | AT70: 0.086784593 | AU70: 6.3860787 | AV70: 6.6063249 | AW70: 9.5973977 | AX70: 8.5282876 | AY70: 8.2420088 | AZ70: 7.1887352 | BA70: 3.1201208 | BB70: -3.4436445 | BC70: 7.1284086 | BD70: 8.3583412 | BE70: 4.0905723 | BF70: 6.557224 | BG70: 3.2556405 | BH70: 3.4855285 | BI70: 2.8579731 | BJ70: 6.0089676 | BK70: 3.7875336 | BL70: 2.6192268 | BM70: 0.29079641 | BN70: 9.2798706 | BO70: 3.1118805 | BP70: 5.05063 | BQ70: 4.0569523 | BR70: 4.2009377
A71: Europe & Central Asia | B71: ECS | C71: GDP growth (annual %) | D71: NY.GDP.MKTP.KD.ZG | F71: 5.0588712 | G71: 4.6691855 | H71: 4.8805502 | I71: 5.9339319 | J71: 4.55342 | K71: 3.7830965 | L71: 3.4658294 | M71: 5.4280263 | N71: 5.915148 | O71: 4.9956611 | P71: 3.3162757 | Q71: 4.5197688 | R71: 6.0520363 | S71: 2.4111346 | T71: -0.20206956 | U71: 4.4985474 | V71: 2.6905913 | W71: 3.0463996 | X71: 3.6234983 | Y71: 1.3474698 | Z71: 0.3926842 | AA71: 1.075697 | AB71: 1.9151859 | AC71: 2.785395 | AD71: 2.617576 | AE71: 2.9181328 | AF71: 3.0398661 | AG71: 4.0709853 | AH71: 3.4083335 | AI71: 2.1945335 | AJ71: 0.14986792 | AK71: -0.63038997 | AL71: -0.70011895 | AM71: 1.4957525 | AN71: 2.4483935 | AO71: 1.81033 | AP71: 3.0805922 | AQ71: 2.5689113 | AR71: 2.9038719 | AS71: 4.3996813 | AT71: 2.2314272 | AU71: 1.5791052 | AV71: 1.820094 | AW71: 3.1815859 | AX71: 2.7370746 | AY71: 3.8958716 | AZ71: 3.703836 | BA71: 1.0252314 | BB71: -4.4080943 | BC71: 2.6383225 | BD71: 2.3235753 | BE71: 0.32024335 | BF71: 0.87626676 | BG71: 1.9436533 | BH71: 2.0783238 | BI71: 1.9082539 | BJ71: 2.9616868 | BK71: 2.1826166 | BL71: 1.8314979 | BM71: -5.3758493 | BN71: 6.8246072 | BO71: 3.4281024 | BP71: 1.0469541 | BQ71: 1.6109298 | BR71: 1.7032971
A72: Ecuador | B72: ECU | C72: GDP growth (annual %) | D72: NY.GDP.MKTP.KD.ZG | F72: 5.1244149 | G72: 4.9191469 | H72: 2.1063682 | I72: 7.4072454 | J72: 3.2750825 | K72: -0.33952564 | L72: 4.6210739 | M72: 1.9094384 | N72: 4.669238 | O72: 6.8719293 | P72: 6.2926062 | Q72: 5.0176407 | R72: 13.950682 | S72: 11.20851 | T72: 10.972154 | U72: 7.3971876 | V72: 1.6048421 | W72: 5.7068249 | X72: 3.7340484 | Y72: 3.708683 | Z72: 5.6128641 | AA72: 0.61484535 | AB72: -0.33686877 | AC72: 2.6252733 | AD72: 3.9350014 | AE72: 3.4647825 | AF72: -0.25909871 | AG72: 5.8904673 | AH72: 1.0057779 | AI72: 3.6799141 | AJ72: 4.2913425 | AK72: 2.1143106 | AL72: 1.9732181 | AM72: 4.2582504 | AN72: 2.2525487 | AO72: 1.7317476 | AP72: 4.3278648 | AQ72: 3.2665293 | AR72: -4.7393859 | AS72: 1.0918016 | AT72: 4.2062719 | AU72: 4.9280955 | AV72: 2.8845004 | AW72: 6.8323974 | AX72: 5.3986224 | AY72: 4.341132 | AZ72: 1.9024286 | BA72: 6.5649207 | BB72: 1.091013 | BC72: 4.0291379 | BD72: 8.4814766 | BE72: 5.7832123 | BF72: 7.2112365 | BG72: 4.2260652 | BH72: 0.11969211 | BI72: -0.68795425 | BJ72: 5.9703988 | BK72: 1.0442946 | BL72: 0.16540446 | BM72: -9.2450962 | BN72: 9.4218927 | BO72: 5.8684235 | BP72: 1.8328406 | BQ72: -1.9440902 | BR72: 3.7259486
A73: Egypt, Arab Rep. | B73: EGY | C73: GDP growth (annual %) | D73: NY.GDP.MKTP.KD.ZG | F73: 5.1611141 | G73: 3.8756167 | H73: 10.518093 | I73: 11.507577 | J73: 4.9140423 | K73: 5.0464037 | L73: 0.80526413 | M73: -1.6067923 | N73: 5.2795175 | O73: 5.598515 | P73: 4.0573463 | Q73: 3.0556806 | R73: 3.5068302 | S73: 1.5589386 | T73: 8.9391472 | U73: 13.279689 | V73: 9.0030443 | W73: 8.6287676 | X73: 4.5476896 | Y73: 10.011329 | Z73: 7.3485539 | AA73: 9.9071711 | AB73: 5.0944068 | AC73: 9.7457627 | AD73: 5.7915058 | AE73: 4.7445255 | AF73: 3.8327526 | AG73: 5.4613205 | AH73: 4.9208686 | AI73: 5.6670292 | AJ73: 1.1254046 | AK73: 4.4728592 | AL73: 2.9007908 | AM73: 3.9731722 | AN73: 4.6424588 | AO73: 4.9887306 | AP73: 5.4923547 | AQ73: 5.5754975 | AR73: 6.0534388 | AS73: 6.3700038 | AT73: 3.535252 | AU73: 2.390204 | AV73: 3.1934547 | AW73: 4.0920716 | AX73: 4.4717445 | AY73: 6.8438382 | AZ73: 7.0878274 | BA73: 7.1562836 | BB73: 4.6735998 | BC73: 5.1472349 | BD73: 1.7645719 | BE73: 2.2261998 | BF73: 2.1854661 | BG73: 2.9159119 | BH73: 4.3720191 | BI73: 4.3466435 | BJ73: 4.181221 | BK73: 5.3311086 | BL73: 5.5520931 | BM73: 3.5501648 | BN73: 3.290646 | BO73: 6.5878456 | BP73: 3.7602805 | BQ73: 2.3991693 | BR73: 4.3920107
A74: Euro area | B74: EMU | C74: GDP growth (annual %) | D74: NY.GDP.MKTP.KD.ZG | F74: 5.7427224 | G74: 5.7603499 | H74: 4.8749731 | I74: 5.8667651 | J74: 5.0448725 | K74: 4.3885531 | L74: 3.4411572 | M74: 5.678717 | N74: 7.1307027 | O74: 5.6093297 | P74: 3.757721 | Q74: 4.8928076 | R74: 6.1183263 | S74: 3.2308132 | T74: -0.76901648 | U74: 5.0255597 | V74: 3.1017184 | W74: 3.1120516 | X74: 3.9027127 | Y74: 2.1818717 | Z74: 0.56663287 | AA74: 0.69714051 | AB74: 1.4060123 | AC74: 2.4097903 | AD74: 2.3067676 | AE74: 2.5283942 | AF74: 2.5516316 | AG74: 4.3554872 | AH74: 4.0669776 | AI74: 3.5208147 | AJ74: 2.3119978 | AK74: 1.0863697 | AL74: -0.68579473 | AM74: 2.5125722 | AN74: 2.4710493 | AO74: 1.7561848 | AP74: 2.6964568 | AQ74: 3.0030998 | AR74: 2.971562 | AS74: 3.9034731 | AT74: 2.1900349 | AU74: 0.96183955 | AV74: 0.76758675 | AW74: 2.3259439 | AX74: 1.7901153 | AY74: 3.3373349 | AZ74: 3.0249937 | BA74: 0.4329694 | BB74: -4.4780504 | BC74: 2.1158695 | BD74: 1.7788444 | BE74: -0.91385909 | BF74: -0.16832234 | BG74: 1.4537154 | BH74: 2.1489448 | BI74: 1.8068143 | BJ74: 2.6231567 | BK74: 1.782293 | BL74: 1.6320894 | BM74: -6.0437492 | BN74: 6.4434975 | BO74: 3.664685 | BP74: 0.46007037 | BQ74: 0.93870726 | BR74: 1.4110724
A75: Eritrea | B75: ERI | C75: GDP growth (annual %) | D75: NY.GDP.MKTP.KD.ZG | AL75: 13.454763 | AM75: 21.221411 | AN75: 2.8583791 | AO75: 9.2588386 | AP75: 7.9086846 | AQ75: 1.7725831 | AR75: 0.013480096 | AS75: -3.1419859 | AT75: 8.7554355 | AU75: 3.0054292 | AV75: -2.6555159 | AW75: 1.4517356 | AX75: 2.5744496 | AY75: -0.96921711 | AZ75: 1.4268222 | BA75: -9.78303 | BB75: 3.8765015 | BC75: 2.1941903 | BD75: 8.6798001
A76: Spain | B76: ESP | C76: GDP growth (annual %) | D76: NY.GDP.MKTP.KD.ZG | F76: 11.838674 | G76: 9.9534382 | H76: 9.596499 | I76: 5.3085104 | J76: 6.253135 | K76: 7.2460602 | L76: 4.3403383 | M76: 6.5970202 | N76: 8.9070154 | O76: 4.2449709 | P76: 4.6494736 | Q76: 8.1497459 | R76: 7.7884653 | S76: 5.6187856 | T76: 0.54220334 | U76: 3.3037914 | V76: 2.8385744 | W76: 1.4630033 | X76: 0.041546517 | Y76: 2.2087281 | Z76: -0.1324686 | AA76: 1.2464618 | AB76: 1.7701158 | AC76: 1.7846875 | AD76: 2.3214358 | AE76: 3.2533217 | AF76: 5.5471227 | AG76: 5.0943241 | AH76: 4.8270303 | AI76: 3.7813936 | AJ76: 2.5460005 | AK76: 0.92921548 | AL76: -1.0314918 | AM76: 2.3831954 | AN76: 2.757494 | AO76: 2.6074112 | AP76: 3.5872997 | AQ76: 4.3019775 | AR76: 4.4088655 | AS76: 5.2006413 | AT76: 3.9190888 | AU76: 2.7554561 | AV76: 2.9392896 | AW76: 3.1145315 | AX76: 3.5512256 | AY76: 4.0434352 | AZ76: 3.5335001 | BA76: 0.76716575 | BB76: -3.7681331 | BC76: 0.094122312 | BD76: -0.63992064 | BE76: -2.8651137 | BF76: -1.4273222 | BG76: 1.5204859 | BH76: 4.0608667 | BI76: 2.915156 | BJ76: 2.8960421 | BK76: 2.3954112 | BL76: 1.9611785 | BM76: -10.940071 | BN76: 6.6831442 | BO76: 6.3703171 | BP76: 2.460858 | BQ76: 3.4552541 | BR76: 2.824954
A77: Estonia | B77: EST | C77: GDP growth (annual %) | D77: NY.GDP.MKTP.KD.ZG | AJ77: -7.9998454 | AK77: -21.168655 | AL77: -5.74049 | AM77: -1.6424292 | AN77: 4.5266834 | AO77: 4.9430123 | AP77: 13.050021 | AQ77: 4.3398276 | AR77: -0.42502537 | AS77: 10.087639 | AT77: 5.8807459 | AU77: 6.9330008 | AV77: 7.5963018 | AW77: 6.8007011 | AX77: 9.5230539 | AY77: 9.7625713 | AZ77: 7.5709188 | BA77: -5.1253115 | BB77: -14.630223 | BC77: 2.4497502 | BD77: 7.6069746 | BE77: 3.6720187 | BF77: 1.7564938 | BG77: 3.3227899 | BH77: 1.8381526 | BI77: 3.0930192 | BJ77: 5.6346725 | BK77: 3.6996976 | BL77: 3.7266494 | BM77: -2.8838075 | BN77: 8.2548804 | BO77: -1.2261697 | BP77: -2.7442191 | BQ77: -0.090042865 | BR77: 0.58430846
A78: Ethiopia | B78: ETH | C78: GDP growth (annual %) | D78: NY.GDP.MKTP.KD.ZG | G78: 4.3260913 | H78: 4.5186339 | I78: 4.0904856 | J78: 5.771932 | K78: 7.256598 | L78: 4.0615879 | M78: 4.1421878 | N78: 1.3886574 | O78: 3.4827287 | P78: 6.5264762 | Q78: 4.2271596 | R78: 5.1098695 | S78: 3.2736583 | T78: 1.2461317 | U78: 0.14881032 | V78: 2.7256816 | W78: 2.7400063 | X78: -1.1007637 | Y78: 6.4241662 | Z78: 4.3815481 | AA78: 0.91601386 | AB78: 8.2350057 | AC78: -2.8480215 | AD78: -11.144353 | AE78: 9.6616124 | AF78: 13.85933 | AG78: 0.50367488 | AH78: -0.36104418 | AI78: 2.7264518 | AJ78: -7.1374797 | AK78: -8.6724801 | AL78: 13.142834 | AM78: 3.1899646 | AN78: 6.1275114 | AO78: 12.426174 | AP78: 3.1339069 | AQ78: -3.4581391 | AR78: 5.1621458 | AS78: 6.0732175 | AT78: 8.3013063 | AU78: 1.5147257 | AV78: -2.1613597 | AW78: 13.572603 | AX78: 11.818766 | AY78: 10.834727 | AZ78: 11.456167 | BA78: 10.788522 | BB78: 8.8025532 | BC78: 12.550538 | BD78: 11.178296 | BE78: 8.6478116 | BF78: 10.58227 | BG78: 10.257493 | BH78: 10.392463 | BI78: 9.4334827 | BJ78: 9.5641897 | BK78: 6.8161478 | BL78: 8.3640857 | BM78: 6.0595309 | BN78: 5.6415307 | BO78: 5.3217599 | BP78: 6.594246 | BQ78: 7.6127745 | BR78: 9.7715182
A79: European Union | B79: EUU | C79: GDP growth (annual %) | D79: NY.GDP.MKTP.KD.ZG | F79: 5.7503034 | G79: 5.693951 | H79: 4.7807354 | I79: 5.9924568 | J79: 5.2472005 | K79: 4.2722461 | L79: 3.5458594 | M79: 5.5887798 | N79: 7.0305052 | O79: 5.5299628 | P79: 3.6510454 | Q79: 4.7713465 | R79: 6.0049376 | S79: 3.1476485 | T79: -0.58029631 | U79: 4.8755213 | V79: 2.9461195 | W79: 3.0605284 | X79: 3.8893648 | Y79: 2.0669333 | Z79: 0.55839813 | AA79: 0.81936698 | AB79: 1.4460287 | AC79: 2.5265791 | AD79: 2.3165604 | AE79: 2.5793047 | AF79: 2.5438797 | AG79: 4.1301567 | AH79: 3.8930877 | AI79: 3.2974382 | AJ79: 1.4603348 | AK79: 0.90165577 | AL79: -0.59602458 | AM79: 2.7014021 | AN79: 2.7246945 | AO79: 1.9160838 | AP79: 2.684487 | AQ79: 2.9814123 | AR79: 3.0037438 | AS79: 3.9335856 | AT79: 2.1611431 | AU79: 1.0976918 | AV79: 0.936973 | AW79: 2.5999036 | AX79: 1.9835859 | AY79: 3.5675402 | AZ79: 3.1418414 | BA79: 0.61797069 | BB79: -4.312085 | BC79: 2.1818022 | BD79: 1.9605958 | BE79: -0.76441294 | BF79: -0.033037256 | BG79: 1.632712 | BH79: 2.3719511 | BI79: 1.919979 | BJ79: 2.8181084 | BK79: 2.0464197 | BL79: 1.875255 | BM79: -5.5788812 | BN79: 6.3777372 | BO79: 3.5645551 | BP79: 0.43800892 | BQ79: 1.0865789 | BR79: 1.5379543
A80: Fragility, Conflict, and Violence (FCV) situations | B80: FCV | C80: GDP growth (annual %) | D80: NY.GDP.MKTP.KD.ZG | F80: 2.5393935 | G80: 8.139107 | H80: 6.7953998 | I80: 6.3433227 | J80: 9.5786521 | K80: 4.2410694 | L80: -0.43540028 | M80: 9.4139491 | N80: 14.109862 | O80: 11.526684 | P80: 10.065272 | Q80: 8.0604594 | R80: 5.4832267 | S80: 8.8307274 | T80: -0.22779673 | U80: 13.225411 | V80: 1.8050213 | W80: -5.5745868 | X80: -0.70393941 | Y80: -4.2443589 | Z80: -6.956404 | AA80: 5.7237478 | AB80: 0.20514431 | AC80: -3.4771282 | AD80: 3.2998382 | AE80: -3.5160687 | AF80: 0.93776535 | AG80: 1.15154 | AH80: 2.0637961 | AI80: 7.1216619 | AJ80: -1.8916444 | AK80: 1.1560522 | AL80: -1.8521921 | AM80: -3.2915129 | AN80: 0.39372015 | AO80: 4.1097953 | AP80: 3.6818892 | AQ80: 4.2116149 | AR80: 2.9897856 | AS80: 5.7664443 | AT80: 3.7362504 | AU80: 6.0900679 | AV80: 3.3799153 | AW80: 9.4598525 | AX80: 5.1405814 | AY80: 5.7207791 | AZ80: 6.819071 | BA80: 3.9477798 | BB80: 2.3436826 | BC80: 6.5711169 | BD80: 0.3806609 | BE80: 2.9514121 | BF80: 2.4642769 | BG80: 2.9048902 | BH80: 0.17892971 | BI80: 3.8809071 | BJ80: 2.7472217 | BK80: 1.117306 | BL80: 1.1419745 | BM80: -4.183063 | BN80: 2.1211523 | BO80: 2.1501407 | BP80: 2.9582078 | BQ80: 2.4009035 | BR80: 1.7256486
A81: Finland | B81: FIN | C81: GDP growth (annual %) | D81: NY.GDP.MKTP.KD.ZG | F81: 7.6046703 | G81: 2.9819462 | H81: 3.2850996 | I81: 5.2386865 | J81: 5.3028584 | K81: 2.3728224 | L81: 2.168829 | M81: 2.3032898 | N81: 9.5932885 | O81: 7.4704327 | P81: 2.3569212 | Q81: 7.7354848 | R81: 6.9838284 | S81: 3.2365334 | T81: 1.804898 | U81: 0.34438319 | V81: 0.23951063 | W81: 2.9197076 | X81: 7.1219259 | Y81: 5.3890475 | Z81: 1.2893843 | AA81: 3.0867154 | AB81: 3.1038488 | AC81: 3.2265329 | AD81: 3.5400544 | AE81: 2.7550993 | AF81: 3.561033 | AG81: 5.2311128 | AH81: 5.0839296 | AI81: 0.69164992 | AJ81: -5.8805962 | AK81: -3.3113736 | AL81: -0.77981506 | AM81: 3.9643728 | AN81: 4.2343671 | AO81: 3.6626572 | AP81: 6.3977007 | AQ81: 5.4542702 | AR81: 4.3892807 | AS81: 5.7537377 | AT81: 2.6402621 | AU81: 1.6873264 | AV81: 2.0117999 | AW81: 4.0053795 | AX81: 2.7773092 | AY81: 4.0195733 | AZ81: 5.3128018 | BA81: 0.78443124 | BB81: -8.0760312 | BC81: 3.1682879 | BD81: 2.3903946 | BE81: -1.5228401 | BF81: -0.97974102 | BG81: -0.47806842 | BH81: 0.46650377 | BI81: 2.5719341 | BJ81: 3.30337 | BK81: 1.1929776 | BL81: 1.3497385 | BM81: -2.4910361 | BN81: 2.6763464 | BO81: 0.76304191 | BP81: -1.2897348 | BQ81: 0.37456657 | BR81: 0.17344451
A82: Fiji | B82: FJI | C82: GDP growth (annual %) | D82: NY.GDP.MKTP.KD.ZG | F82: 3.517582 | G82: 3.6061022 | H82: 6.3587719 | I82: 4.8772807 | J82: -2.7002669 | K82: 0 | L82: 13.351828 | M82: 7.9162216 | N82: 2.5964105 | O82: 12.702711 | P82: 6.8889866 | Q82: 7.4852767 | R82: 11.612868 | S82: 2.6011499 | T82: 0.53021118 | U82: 2.7361633 | V82: 5.9040118 | W82: 1.8634015 | X82: 12.22482 | Y82: -1.6034569 | Z82: 6.3299905 | AA82: -5.9784862 | AB82: -3.960123 | AC82: 8.3930245 | AD82: -4.6134749 | AE82: 7.749908 | AF82: -6.61502 | AG82: 0.95575487 | AH82: 7.4386324 | AI82: 5.8000027 | AJ82: -2.7000034 | AK82: 6.1000016 | AL82: 2.130033 | AM82: 5.0999983 | AN82: 2.499999 | AO82: 4.8000012 | AP82: -2.1999996 | AQ82: 1.2999996 | AR82: 8.7999988 | AS82: -1.6999978 | AT82: 2.0000003 | AU82: 3.1999986 | AV82: 0.999999 | AW82: 5.3000009 | AX82: 0.69999959 | AY82: 1.8524836 | AZ82: -0.85065335 | BA82: 1.0327937 | BB82: -1.3860375 | BC82: 2.9546727 | BD82: 2.7051423 | BE82: 1.4113142 | BF82: 4.7342204 | BG82: 5.603514 | BH82: 4.5012006 | BI82: 2.445652 | BJ82: 5.3533643 | BK82: 3.8123509 | BL82: -0.58194659 | BM82: -17.183535 | BN82: -4.345962 | BO82: 17.745127 | BP82: 9.4424586 | BQ82: 3.530859 | BR82: 3.1954686
A83: France | B83: FRA | C83: GDP growth (annual %) | D83: NY.GDP.MKTP.KD.ZG | F83: 4.9464255 | G83: 6.8562646 | H83: 6.1033389 | I83: 6.5828069 | J83: 4.8387501 | K83: 5.1635427 | L83: 4.8017708 | M83: 4.5440182 | N83: 7.093647 | O83: 6.2001744 | P83: 5.2934462 | Q83: 4.5141076 | R83: 6.1945841 | S83: 4.4147138 | T83: -0.94560962 | U83: 4.3375565 | V83: 3.5541557 | W83: 3.9493622 | X83: 3.6953108 | Y83: 1.6764134 | Z83: 1.1883147 | AA83: 2.4425127 | AB83: 1.2620576 | AC83: 1.6094715 | AD83: 1.5690744 | AE83: 2.3895355 | AF83: 2.5527462 | AG83: 4.814224 | AH83: 4.4051693 | AI83: 2.8296272 | AJ83: 1.2366625 | AK83: 1.5160611 | AL83: -0.35899781 | AM83: 2.3836609 | AN83: 2.3047928 | AO83: 1.3970799 | AP83: 2.5270616 | AQ83: 3.4525943 | AR83: 3.3993081 | AS83: 4.141 | AT83: 1.899467 | AU83: 1.0677503 | AV83: 0.96782718 | AW83: 2.8682505 | AX83: 1.8885658 | AY83: 2.7140645 | AZ83: 2.5304819 | BA83: 0.38017144 | BB83: -2.8245515 | BC83: 2.0003248 | BD83: 2.4375765 | BE83: 0.18383526 | BF83: 0.78175645 | BG83: 0.99783295 | BH83: 1.0667547 | BI83: 0.86003108 | BJ83: 2.0836149 | BK83: 1.6459087 | BL83: 2.0274465 | BM83: -7.4406459 | BN83: 6.8823378 | BO83: 2.7167626 | BP83: 1.4392149 | BQ83: 1.190468 | BR83: 0.84094996
A84: Faroe Islands | B84: FRO | C84: GDP growth (annual %) | D84: NY.GDP.MKTP.KD.ZG | BB84: -4.5532982 | BC84: -0.37981799 | BD84: 3.5663632 | BE84: 7.0814834 | BF84: 5.8561439 | BG84: 5.4321421 | BH84: 0.95800193 | BI84: 1.386448 | BJ84: 3.5120137 | BK84: 2.7637095 | BL84: 4.5385103 | BM84: -1.6373212 | BN84: 5.0663629 | BO84: 3.8609998 | BP84: 3.1587387 | BQ84: 0.84371685
A85: Micronesia, Fed. Sts. | B85: FSM | C85: GDP growth (annual %) | D85: NY.GDP.MKTP.KD.ZG | P85: 2.3015745 | Q85: 1.0669155 | R85: 33.930008 | S85: 15.327277 | T85: 0.074288093 | U85: 0.35632318 | V85: 2.4262143 | W85: 5.6402092 | X85: 2.1192237 | Y85: -7.1964112 | Z85: 9.7237249 | AA85: -2.6210641 | AB85: 1.9299968 | AC85: -3.9524985 | AD85: 16.550676 | AE85: 7.9793473 | AF85: 1.19976 | AG85: 2.5489034 | AH85: 3.5260116 | AI85: 3.7409269 | AJ85: 7.4273189 | AK85: 4.0080604 | AL85: 8.1406458 | AM85: -0.53451342 | AN85: 7.014463 | AO85: -3.3390536 | AP85: -6.2110974 | AQ85: 2.836818 | AR85: 1.1288156 | AS85: 4.6245455 | AT85: 1.8201635 | AU85: 0.44321995 | AV85: 1.7627563 | AW85: -3.1903783 | AX85: 2.7434627 | AY85: -0.41322314 | AZ85: -1.659751 | BA85: -2.5316456 | BB85: 1.2987013 | BC85: 1.7094017 | BD85: 3.7815126 | BE85: -1.6194332 | BF85: -3.7037037 | BG85: -2.5641026 | BH85: 4.3859649 | BI85: 1.2605042 | BJ85: 2.0746888 | BK85: 0.40650407 | BL85: 3.6437247 | BM85: -2.0570312 | BN85: 3.0996993 | BO85: -3.114125 | BP85: 1.130978 | BQ85: 2.3013292 | BR85: 1.0626071
A86: Gabon | B86: GAB | C86: GDP growth (annual %) | D86: NY.GDP.MKTP.KD.ZG | F86: 14.766843 | G86: 7.4492116 | H86: 6.0924353 | I86: 4.5544536 | J86: 8.3333357 | K86: 4.5080046 | L86: 4.1151529 | M86: 2.5088009 | N86: 8.0829104 | O86: 8.6793422 | P86: 10.258731 | Q86: 11.336971 | R86: 10.182434 | S86: 39.487095 | T86: 19.190115 | U86: 35.625338 | V86: -12.582091 | W86: -24.049206 | X86: 0.47440528 | Y86: 2.5529372 | Z86: 5.0953293 | AA86: -3.0975204 | AB86: 5.6082407 | AC86: 7.5089023 | AD86: -2.3329493 | AE86: -0.80359773 | AF86: -17.146042 | AG86: 12.845353 | AH86: 8.54531 | AI86: 5.1922373 | AJ86: 6.1125035 | AK86: -3.0901457 | AL86: 3.946555 | AM86: 3.7127548 | AN86: 4.9738478 | AO86: 3.625049 | AP86: 5.7383674 | AQ86: 3.4778336 | AR86: -8.9326228 | AS86: -1.8829664 | AT86: 2.1352334 | AU86: -0.24903317 | AV86: 2.24733 | AW86: 0.68954306 | AX86: 2.6762033 | AY86: -2.8065784 | AZ86: 6.008108 | BA86: -3.3084306 | BB86: 0.13033112 | BC86: 7.0898873 | BD86: 7.0917533 | BE86: 5.2510769 | BF86: 5.638699 | BG86: 4.3149644 | BH86: 3.8788994 | BI86: 2.0914422 | BJ86: 0.47264203 | BK86: 0.83791658 | BL86: 3.9208088 | BM86: -1.8377611 | BN86: 1.4679573 | BO86: 3.0376145 | BP86: 2.4389367 | BQ86: 3.394039 | BR86: 2.4728796
A87: United Kingdom | B87: GBR | C87: GDP growth (annual %) | D87: NY.GDP.MKTP.KD.ZG | F87: 2.7013142 | G87: 1.0986962 | H87: 4.8595452 | I87: 5.5948111 | J87: 2.1303331 | K87: 1.5674496 | L87: 2.7757377 | M87: 5.4726931 | N87: 1.9391378 | O87: 2.7085815 | P87: 2.0045376 | Q87: 3.6263711 | R87: 7.3135242 | S87: -1.6796979 | T87: -0.67687019 | U87: 2.804656 | V87: 2.3633509 | W87: 3.4033738 | X87: 2.7467722 | Y87: -2.1791022 | Z87: -1.3234582 | AA87: 2.0930689 | AB87: 3.6243464 | AC87: 2.6709249 | AD87: 3.5993814 | AE87: 4.0123299 | AF87: 4.5620808 | AG87: 5.0321018 | AH87: 2.2814467 | AI87: 0.77926612 | AJ87: -1.2924397 | AK87: 1.2947285 | AL87: 3.4904874 | AM87: 4.9534109 | AN87: 3.533391 | AO87: 2.6149161 | AP87: 4.8799853 | AQ87: 3.2463148 | AR87: 2.9444587 | AS87: 4.5243807 | AT87: 2.3910223 | AU87: 1.7090274 | AV87: 3.2185161 | AW87: 2.3260185 | AX87: 2.7906547 | AY87: 2.1898213 | AZ87: 2.9309113 | BA87: -0.049411673 | BB87: -4.5874082 | BC87: 2.2605446 | BD87: 0.85143774 | BE87: 1.5282603 | BF87: 1.7184696 | BG87: 3.1601735 | BH87: 2.1404056 | BI87: 2.2065202 | BJ87: 3.0232222 | BK87: 1.551331 | BL87: 1.256299 | BM87: -10.047897 | BN87: 8.5431118 | BO87: 5.1497039 | BP87: 0.27165005 | BQ87: 1.0802772 | BR87: 1.3884421
A88: Georgia | B88: GEO | C88: GDP growth (annual %) | D88: NY.GDP.MKTP.KD.ZG | F88: 4.8659407 | G88: 5.1130165 | H88: 4.2018791 | I88: 5.4295876 | J88: 10.558637 | K88: 7.5356631 | L88: 6.2530822 | M88: 4.4555834 | N88: 4.776504 | O88: 12.052076 | P88: 2.4713318 | Q88: 2.8364603 | R88: 6.4825456 | S88: 8.8097406 | T88: 7.3804284 | U88: 6.0995324 | V88: 6.8943001 | W88: 7.4295604 | X88: 7.3706406 | Y88: 4.576447 | Z88: 5.2666006 | AA88: 2.0024454 | AB88: 4.3016035 | AC88: 5.4279631 | AD88: 4.9412059 | AE88: -8.1756722 | AF88: 1.2814807 | AG88: 5.5554538 | AH88: -7.1937829 | AI88: -14.788785 | AJ88: -21.099851 | AK88: -44.899775 | AL88: -29.300167 | AM88: -10.39823 | AN88: 2.5965751 | AO88: 11.202546 | AP88: 10.520804 | AQ88: 3.1015097 | AR88: 2.8672957 | AS88: 1.8403812 | AT88: 4.8072987 | AU88: 5.4740249 | AV88: 11.057031 | AW88: 5.7926829 | AX88: 9.5911383 | AY88: 9.4214808 | AZ88: 12.57557 | BA88: 2.4216144 | BB88: -3.6507523 | BC88: 6.2464087 | BD88: 7.9343365 | BE88: 6.578831 | BF88: 5.1328853 | BG88: 4.0904906 | BH88: 3.3510235 | BI88: 3.4502152 | BJ88: 5.1599026 | BK88: 6.0620364 | BL88: 5.3807193 | BM88: -6.2904718 | BN88: 10.644234 | BO88: 10.958532 | BP88: 7.8322013 | BQ88: 9.6797938 | BR88: 7.461615
A89: Ghana | B89: GHA | C89: GDP growth (annual %) | D89: NY.GDP.MKTP.KD.ZG | F89: 3.429674 | G89: 4.1091586 | H89: 4.4059742 | I89: 2.2093275 | J89: 1.3689989 | K89: -4.2582904 | L89: 3.0753641 | M89: 0.36886033 | N89: 6.006175 | O89: 9.7234726 | P89: 5.2161246 | Q89: -2.4876554 | R89: 2.8845842 | S89: 6.8525168 | T89: -12.431629 | U89: -3.5301828 | V89: 2.2741072 | W89: 8.4759356 | X89: -2.5149414 | Y89: 0.47169594 | Z89: -3.5030669 | AA89: -6.9236504 | AB89: -4.5637375 | AC89: 8.6475695 | AD89: 5.0916173 | AE89: 5.1991607 | AF89: 4.7948989 | AG89: 5.6281688 | AH89: 5.0858727 | AI89: 3.3288179 | AJ89: 5.2818264 | AK89: 3.8794191 | AL89: 4.8500006 | AM89: 3.2999997 | AN89: 4.112419 | AO89: 4.6024612 | AP89: 4.1963574 | AQ89: 4.7003908 | AR89: 4.3999968 | AS89: 3.7000001 | AT89: 4.0000001 | AU89: 4.4999996 | AV89: 5.2000001 | AW89: 5.6 | AX89: 5.9000038 | AY89: 6.3999126 | AZ89: 4.3468191 | BA89: 9.1497989 | BB89: 4.8444871 | BC89: 7.8997119 | BD89: 14.047124 | BE89: 9.2927894 | BF89: 7.312525 | BG89: 2.8562402 | BH89: 2.1207593 | BI89: 3.3734657 | BJ89: 8.1288949 | BK89: 6.2000777 | BL89: 6.5077748 | BM89: 0.51394167 | BN89: 5.0764664 | BO89: 3.8048498 | BP89: 3.140091 | BQ89: 5.8474685 | BR89: 5.9544171
A90: Gibraltar | B90: GIB | C90: GDP growth (annual %) | D90: NY.GDP.MKTP.KD.ZG
A91: Guinea | B91: GIN | C91: GDP growth (annual %) | D91: NY.GDP.MKTP.KD.ZG | P91: 5.3658184 | Q91: 2.3151795 | R91: 1.5672868 | S91: 5.2502212 | T91: 2.8769206 | U91: 7.9233683 | V91: -3.3530698 | W91: 6.7962645 | X91: -1.2078607 | Y91: 2.601388 | Z91: 0.60973716 | AA91: 1.8000048 | AB91: 1.3000118 | AC91: 1.4000095 | AD91: 4.9999306 | AE91: 3.11404 | AF91: 3.2999388 | AG91: 6.3081167 | AH91: 4.003476 | AI91: 4.3240628 | AJ91: 2.613423 | AK91: 3.2709473 | AL91: 5.0441445 | AM91: 3.9700991 | AN91: 4.6076732 | AO91: 4.4615751 | AP91: 5.1816035 | AQ91: 3.6441212 | AR91: 3.812004 | AS91: 2.5030606 | AT91: 3.6583465 | AU91: 5.1646095 | AV91: 1.2486013 | AW91: 2.3401173 | AX91: 2.9972726 | AY91: 1.1896021 | AZ91: 6.8174711 | BA91: 4.1330162 | BB91: -1.122642 | BC91: 4.8133602 | BD91: 5.6121118 | BE91: 5.9152863 | BF91: 3.9456871 | BG91: 3.6965531 | BH91: 3.8259106 | BI91: 10.820627 | BJ91: 10.300005 | BK91: 6.3584919 | BL91: 5.6169145 | BM91: 4.704591 | BN91: 5.5823328 | BO91: 3.9724078 | BP91: 5.5417267 | BQ91: 5.3500466 | BR91: 7.4470967
A92: Gambia, The | B92: GMB | C92: GDP growth (annual %) | D92: NY.GDP.MKTP.KD.ZG | L92: 0 | M92: 9.5761435 | N92: 2.4355229 | O92: 6.1538466 | P92: -0.065877039 | Q92: 0.24170479 | R92: 9.2503293 | S92: 5.8787936 | T92: 12.393429 | U92: 7.3512257 | V92: 3.4395761 | W92: 6.3164463 | X92: -1.3281832 | Y92: 6.2700796 | Z92: 3.321894 | AA92: -0.76458264 | AB92: 10.883228 | AC92: 3.5352573 | AD92: -0.81226466 | AE92: 4.0910707 | AF92: 2.4543326 | AG92: 4.4768269 | AH92: 5.8957219 | AI92: 3.5588794 | AJ92: 3.1070392 | AK92: 3.3786888 | AL92: 3.0121014 | AM92: 0.15434596 | AN92: 0.88184824 | AO92: 2.2235456 | AP92: 4.8999991 | AQ92: 3.4999987 | AR92: 6.3999991 | AS92: 5.5000002 | AT92: 5.8000002 | AU92: -3.2500001 | AV92: 6.8699996 | AW92: 7.05 | AX92: -2.3517294 | AY92: -0.55558098 | AZ92: 3.0432495 | BA92: 6.2559055 | BB92: 6.6657243 | BC92: 5.9083358 | BD92: -8.1304442 | BE92: 5.2415692 | BF92: 2.8727688 | BG92: -1.4073825 | BH92: 4.0580738 | BI92: 1.9433597 | BJ92: 4.8226112 | BK92: 7.2348903 | BL92: 6.2220532 | BM92: 0.59148729 | BN92: 5.2559688 | BO92: 5.4929982 | BP92: 5.9167958 | BQ92: 5.5512607 | BR92: 5.8930921
A93: Guinea-Bissau | B93: GNB | C93: GDP growth (annual %) | D93: NY.GDP.MKTP.KD.ZG | P93: -3.9109675 | Q93: 6.3748609 | R93: 1.1098928 | S93: 4.559241 | T93: 7.8455843 | U93: 4.9434553 | V93: -7.17007 | W93: 13.126043 | X93: 1.9941444 | Y93: -15.952651 | Z93: 18.167528 | AA93: 4.2000821 | AB93: -3.3982874 | AC93: 9.109223 | AD93: 4.1664929 | AE93: -0.79384763 | AF93: 2.9 | AG93: 4.6 | AH93: 6.1 | AI93: 6.1 | AJ93: 5.1 | AK93: 1.1 | AL93: 2.1 | AM93: 3.2 | AN93: 4.4 | AO93: 11.6 | AP93: 6.5 | AQ93: -22.445727 | AR93: 16.815021 | AS93: 1.1002782 | AT93: 4.7859717 | AU93: 3.653936 | AV93: -0.28593105 | AW93: 1.1718915 | AX93: 6.5597711 | AY93: 2.6665049 | AZ93: 2.5598265 | BA93: 4.5245751 | BB93: 2.4479511 | BC93: 5.6053631 | BD93: 8.0850417 | BE93: -1.7128696 | BF93: 3.2560719 | BG93: 0.96452575 | BH93: 6.1340894 | BI93: 5.4326783 | BJ93: 4.6636794 | BK93: 3.7614536 | BL93: 5.3274957 | BM93: 2.8914998 | BN93: 5.0173096 | BO93: 5.4577609 | BP93: 4.6305236 | BQ93: 4.4092011 | BR93: 5.8181376
A94: Equatorial Guinea | B94: GNQ | C94: GDP growth (annual %) | D94: NY.GDP.MKTP.KD.ZG | Z94: 5.7694205 | AA94: 2.2016759 | AB94: 5.0043872 | AC94: 1.0113817 | AD94: 12.905179 | AE94: -2.3305564 | AF94: 4.4367374 | AG94: 2.6552622 | AH94: -1.2291781 | AI94: -1.7585641 | AJ94: -1.0222389 | AK94: 34.74532 | AL94: 11.033213 | AM94: 16.668836 | AN94: 17.486264 | AO94: 66.579997 | AP94: 149.97296 | AQ94: 23.774482 | AR94: 25.664015 | AS94: 18.21378 | AT94: 63.379875 | AU94: 19.462834 | AV94: 13.95525 | AW94: 37.998727 | AX94: 16.748701 | AY94: 7.7049176 | AZ94: 15.282114 | BA94: 17.799109 | BB94: 1.3433563 | BC94: -8.9241759 | BD94: 6.5239236 | BE94: 8.3128718 | BF94: -4.1331985 | BG94: 0.4150663 | BH94: -9.1100411 | BI94: -8.8164172 | BJ94: -5.6675085 | BK94: -6.2365441 | BL94: -5.4818254 | BM94: -4.7910808 | BN94: 0.86026996 | BO94: 3.2235083 | BP94: -7.4250553 | BQ94: 0.39622552 | BR94: -5.8467851
A95: Greece | B95: GRC | C95: GDP growth (annual %) | D95: NY.GDP.MKTP.KD.ZG | F95: 13.203839 | G95: 0.36481229 | H95: 11.844867 | I95: 9.4096773 | J95: 10.768011 | K95: 6.4945014 | L95: 5.6694864 | M95: 7.2037177 | N95: 11.563668 | O95: 8.9305802 | P95: 7.8411766 | Q95: 10.160152 | R95: 8.0923791 | S95: -6.4382406 | T95: 6.3668079 | U95: 6.8518987 | V95: 2.9410009 | W95: 7.246864 | X95: 3.2820796 | Y95: 0.67713141 | Z95: -1.5537213 | AA95: -1.1326474 | AB95: -1.0786227 | AC95: 2.0105809 | AD95: 2.5095564 | AE95: 0.51766001 | AF95: -2.2588632 | AG95: 4.2878617 | AH95: 3.8 | AI95: 0 | AJ95: 3.0999997 | AK95: 0.70000034 | AL95: -1.6 | AM95: 1.9999998 | AN95: 2.0997195 | AO95: 1.3824706 | AP95: 3.6028833 | AQ95: 3.4369358 | AR95: 2.6587856 | AS95: 4.137827 | AT95: 4.6504146 | AU95: 4.6831373 | AV95: 5.7968227 | AW95: 5.3778663 | AX95: 1.1835064 | AY95: 6.4433976 | AZ95: 3.5068698 | BA95: 0.057474024 | BB95: -4.1192761 | BC95: -5.6937412 | BD95: -9.8767788 | BE95: -8.3311342 | BF95: -2.272117 | BG95: 0.79222506 | BH95: -0.22830189 | BI95: -0.031794768 | BJ95: 1.4731247 | BK95: 2.0646721 | BL95: 2.2771807 | BM95: -9.1962315 | BN95: 8.6544979 | BO95: 5.5219858 | BP95: 2.1359113 | BQ95: 2.0865743 | BR95: 2.0730688
A96: Grenada | B96: GRD | C96: GDP growth (annual %) | D96: NY.GDP.MKTP.KD.ZG | W96: 5.3414022 | X96: 5.6020835 | Y96: -0.53478399 | Z96: 1.5341875 | AA96: 4.1242616 | AB96: 3.6325749 | AC96: 3.5684653 | AD96: 5.9797081 | AE96: 7.1942738 | AF96: 9.0974251 | AG96: 2.9667917 | AH96: 3.7677308 | AI96: 4.0126119 | AJ96: 1.3855458 | AK96: -0.85114876 | AL96: -1.9588156 | AM96: 1.693556 | AN96: 2.1294751 | AO96: 4.4382347 | AP96: 5.0154946 | AQ96: 11.753503 | AR96: 6.8983624 | AS96: 4.8879521 | AT96: -2.0239 | AU96: 3.4373235 | AV96: 9.4639734 | AW96: -0.64745032 | AX96: 13.276188 | AY96: -3.9953282 | AZ96: 6.1234509 | BA96: 0.94754262 | BB96: -6.6132813 | BC96: -0.51114619 | BD96: 0.76477355 | BE96: -1.1548382 | BF96: 2.351098 | BG96: 7.342124 | BH96: 6.4452231 | BI96: 3.739604 | BJ96: 4.4386757 | BK96: 4.3614404 | BL96: 0.67651174 | BM96: -13.756622 | BN96: 4.697724 | BO96: 7.3102381 | BP96: 4.526575 | BQ96: 2.3996478 | BR96: 4.41201
A97: Greenland | B97: GRL | C97: GDP growth (annual %) | D97: NY.GDP.MKTP.KD.ZG | P97: 13.060851 | Q97: 6.1772736 | R97: 6.806009 | S97: 5.706254 | T97: 0.64624014 | U97: 5.9592085 | V97: 8.8223153 | W97: 6.0167172 | X97: 4.8605975 | Y97: 8.6760063 | Z97: 0.66527957 | AA97: -4.4196608 | AB97: 3.4572167 | AC97: -5.1796155 | AD97: 3.656388 | AE97: 7.0973227 | AF97: 5.5158721 | AG97: 5.6036107 | AH97: 6.659545 | AI97: -11.719533 | AJ97: -0.11346459 | AK97: -5.1117 | AL97: -5.0279326 | AM97: 5.9243698 | AN97: 3.7286775 | AO97: 1.5296374 | AP97: 1.4689264 | AQ97: 7.7579817 | AR97: 1.3778844 | AS97: 7.1015969 | AT97: 1.2690351 | AU97: -0.97117731 | AV97: 4.4300457 | AW97: 6.9065828 | AX97: 4.9874918 | AY97: 5.5556949 | AZ97: 2.352438 | BA97: 6.1661327 | BB97: 0.86595233 | BC97: 1.7358251 | BD97: -0.49651939 | BE97: 1.3941934 | BF97: -1.2982807 | BG97: 4.7421357 | BH97: -2.529318 | BI97: 4.6819541 | BJ97: 0.052728183 | BK97: 0.62306543 | BL97: 2.8321776 | BM97: 0.25078976 | BN97: 1.6340941 | BO97: 2.0045558 | BP97: 0.86596199
A98: Guatemala | B98: GTM | C98: GDP growth (annual %) | D98: NY.GDP.MKTP.KD.ZG | F98: 4.2985183 | G98: 3.5365013 | H98: 9.5410439 | I98: 4.6329924 | J98: 4.3617693 | K98: 5.512104 | L98: 4.1121756 | M98: 8.7660351 | N98: 4.736909 | O98: 5.7078836 | P98: 5.5837545 | Q98: 7.3330516 | R98: 6.7828343 | S98: 6.3750299 | T98: 1.9499908 | U98: 7.3872656 | V98: 7.8092207 | W98: 4.9966898 | X98: 4.7134561 | Y98: 3.7599782 | Z98: 0.64685861 | AA98: -3.530089 | AB98: -2.5720914 | AC98: 0.49669775 | AD98: -0.60933896 | AE98: 0.1430496 | AF98: 3.5439833 | AG98: 3.8923871 | AH98: 3.9425895 | AI98: 3.1025632 | AJ98: 3.6582488 | AK98: 4.8383388 | AL98: 3.9271319 | AM98: 4.0337415 | AN98: 4.9485475 | AO98: 2.9577799 | AP98: 4.3640899 | AQ98: 4.9935278 | AR98: 3.8470622 | AS98: 3.6088687 | AT98: 2.3325749 | AU98: 3.8392871 | AV98: 2.5603777 | AW98: 3.1379168 | AX98: 3.2760269 | AY98: 5.3513978 | AZ98: 6.3377187 | BA98: 3.293524 | BB98: 0.47689811 | BC98: 2.8841754 | BD98: 4.1639069 | BE98: 2.9747086 | BF98: 3.6947681 | BG98: 4.4439783 | BH98: 4.0921717 | BI98: 2.6778032 | BJ98: 3.0798512 | BK98: 3.4068733 | BL98: 4.0178983 | BM98: -1.7855512 | BN98: 8.041704 | BO98: 4.154922 | BP98: 3.5243043 | BQ98: 3.7155845 | BR98: 4.2800321
A99: Guam | B99: GUM | C99: GDP growth (annual %) | D99: NY.GDP.MKTP.KD.ZG | AV99: 0.87931413 | AW99: 6.4937895 | AX99: 3.6423163 | AY99: -3.6525173 | AZ99: 0.71721311 | BA99: 2.034588 | BB99: 0.43868395 | BC99: 2.2632519 | BD99: 0.077654824 | BE99: 2.1338506 | BF99: 1.6904084 | BG99: 1.7930519 | BH99: 0.82568807 | BI99: 0.18198362 | BJ99: 0.89009991 | BK99: -0.8282319 | BL99: 2.523602 | BM99: -10.51886 | BN99: 2.0581833 | BO99: 5.0998643
A100: Guyana | B100: GUY | C100: GDP growth (annual %) | D100: NY.GDP.MKTP.KD.ZG | F100: 4.6895243 | G100: 1.1049258 | H100: -12.278657 | I100: 11.360282 | J100: 10.541019 | K100: 5.2332739 | L100: 4.3136218 | M100: 1.0248276 | N100: 6.9943867 | O100: 4.2554569 | P100: 3.1128508 | Q100: -3.3176709 | R100: 1.2447194 | S100: 7.7028399 | T100: 8.4830215 | U100: 1.5369133 | V100: -2.6386797 | W100: -1.8061888 | X100: -1.8356963 | Y100: 1.7338897 | Z100: 1.4961659 | AA100: -13.190134 | AB100: -6.7923867 | AC100: -5.0287379 | AD100: 2.3996675 | AE100: -0.90060224 | AF100: 0.89939659 | AG100: -3.6935331 | AH100: -4.9166667 | AI100: -3.0674847 | AJ100: 6.0578662 | AK100: 7.7578858 | AL100: 8.1751055 | AM100: 8.5324232 | AN100: 5.0314466 | AO100: 7.9555175 | AP100: 6.1806656 | AQ100: -1.6791045 | AR100: 2.9601518 | AS100: -1.3638039 | AT100: 2.2795217 | AU100: 1.132627 | AV100: -0.63222539 | AW100: 1.5633521 | AX100: -1.9509576 | AY100: 5.1296093 | AZ100: 7.1912362 | BA100: 1.7552235 | BB100: 3.6115085 | BC100: 4.1384416 | BD100: 5.1962516 | BE100: 5.2763306 | BF100: 3.6533843 | BG100: 1.6864945 | BH100: 0.68740459 | BI100: 3.8074563 | BJ100: 3.7344915 | BK100: 4.4409129 | BL100: 5.35284 | BM100: 43.479652 | BN100: 20.059998 | BO100: 63.334634 | BP100: 33.795011 | BQ100: 43.819273 | BR100: 19.33601
A101: High income | B101: HIC | C101: GDP growth (annual %) | D101: NY.GDP.MKTP.KD.ZG | F101: 4.4132472 | G101: 5.5974974 | H101: 5.0594376 | I101: 6.4148477 | J101: 5.5641827 | K101: 5.5148213 | L101: 3.8315596 | M101: 5.9189823 | N101: 5.6131227 | O101: 3.0395258 | P101: 3.7492117 | Q101: 5.4422285 | R101: 6.3819478 | S101: 1.2439148 | T101: 0.13903765 | U101: 5.0089207 | V101: 3.8063329 | W101: 4.2408424 | X101: 4.0644377 | Y101: 1.2373986 | Z101: 1.8895274 | AA101: -0.12629994 | AB101: 2.8314247 | AC101: 4.7442319 | AD101: 3.4938806 | AE101: 3.2114524 | AF101: 3.543404 | AG101: 4.6199295 | AH101: 3.832912 | AI101: 2.6048121 | AJ101: 0.83241932 | AK101: 1.551052 | AL101: 1.1149978 | AM101: 3.0052378 | AN101: 2.8143358 | AO101: 2.9117013 | AP101: 3.5477028 | AQ101: 2.642317 | AR101: 3.5732662 | AS101: 4.2968851 | AT101: 1.5744703 | AU101: 1.6487079 | AV101: 2.2774454 | AW101: 3.5084717 | AX101: 3.0112868 | AY101: 3.2614528 | AZ101: 2.9159017 | BA101: 0.69226779 | BB101: -3.3625827 | BC101: 3.0468344 | BD101: 2.0078491 | BE101: 1.509288 | BF101: 1.6142277 | BG101: 2.2111218 | BH101: 2.3645036 | BI101: 1.8396591 | BJ101: 2.4919763 | BK101: 2.404535 | BL101: 1.9003579 | BM101: -3.8661836 | BN101: 5.9711133 | BO101: 3.1058607 | BP101: 1.7953458 | BQ101: 1.9694843 | BR101: 1.907335
A102: Hong Kong SAR, China | B102: HKG | C102: GDP growth (annual %) | D102: NY.GDP.MKTP.KD.ZG | G102: 14.290855 | H102: 15.763361 | I102: 8.6278959 | J102: 14.642384 | K102: 1.7947707 | L102: 1.6035085 | M102: 3.3974607 | N102: 11.343472 | O102: 9.2066645 | P102: 7.2928018 | Q102: 10.612049 | R102: 12.27963 | S102: 2.4153357 | T102: 0.49202818 | U102: 16.164302 | V102: 11.725814 | W102: 8.2608866 | X102: 11.556787 | Y102: 10.108175 | Z102: 9.2608812 | AA102: 2.9498801 | AB102: 5.9770692 | AC102: 9.9738642 | AD102: 0.75706264 | AE102: 11.056104 | AF102: 13.398458 | AG102: 8.5115305 | AH102: 2.277099 | AI102: 3.8305508 | AJ102: 5.7019358 | AK102: 6.2350239 | AL102: 6.2011851 | AM102: 6.0360304 | AN102: 2.3738288 | AO102: 4.2584757 | AP102: 5.0996999 | AQ102: -5.8826375 | AR102: 2.506716 | AS102: 7.663444 | AT102: 0.56086714 | AU102: 1.6567017 | AV102: 3.0563589 | AW102: 8.7000656 | AX102: 7.388154 | AY102: 7.0326477 | AZ102: 6.4648281 | BA102: 2.1279369 | BB102: -2.4590915 | BC102: 6.7677068 | BD102: 4.814668 | BE102: 1.7003221 | BF102: 3.1015526 | BG102: 2.7624138 | BH102: 2.3878012 | BI102: 2.1754482 | BJ102: 3.7961094 | BK102: 2.8469092 | BL102: -1.6724287 | BM102: -6.5447964 | BN102: 6.4544304 | BO102: -3.6852836 | BP102: 3.1503446 | BQ102: 2.6293686 | BR102: 3.4876489
...

Sheet Raw_Exchange_Rate
A1: Data Source | B1: World Development Indicators
A3: Last Updated Date | B3: 2026-10-08
A5: Country Name | B5: Country Code | C5: Indicator Name | D5: Indicator Code | E5: 1960 | F5: 1961 | G5: 1962 | H5: 1963 | I5: 1964 | J5: 1965 | K5: 1966 | L5: 1967 | M5: 1968 | N5: 1969 | O5: 1970 | P5: 1971 | Q5: 1972 | R5: 1973 | S5: 1974 | T5: 1975 | U5: 1976 | V5: 1977 | W5: 1978 | X5: 1979 | Y5: 1980 | Z5: 1981 | AA5: 1982 | AB5: 1983 | AC5: 1984 | AD5: 1985 | AE5: 1986 | AF5: 1987 | AG5: 1988 | AH5: 1989 | AI5: 1990 | AJ5: 1991 | AK5: 1992 | AL5: 1993 | AM5: 1994 | AN5: 1995 | AO5: 1996 | AP5: 1997 | AQ5: 1998 | AR5: 1999 | AS5: 2000 | AT5: 2001 | AU5: 2002 | AV5: 2003 | AW5: 2004 | AX5: 2005 | AY5: 2006 | AZ5: 2007 | BA5: 2008 | BB5: 2009 | BC5: 2010 | BD5: 2011 | BE5: 2012 | BF5: 2013 | BG5: 2014 | BH5: 2015 | BI5: 2016 | BJ5: 2017 | BK5: 2018 | BL5: 2019 | BM5: 2020 | BN5: 2021 | BO5: 2022 | BP5: 2023 | BQ5: 2024 | BR5: 2025
A6: Aruba | B6: ABW | C6: Official exchange rate (LCU per US$, period average) | D6: PA.NUS.FCRF | AE6: 1.79 | AF6: 1.79 | AG6: 1.79 | AH6: 1.79 | AI6: 1.79 | AJ6: 1.79 | AK6: 1.79 | AL6: 1.79 | AM6: 1.79 | AN6: 1.79 | AO6: 1.79 | AP6: 1.79 | AQ6: 1.79 | AR6: 1.79 | AS6: 1.79 | AT6: 1.79 | AU6: 1.79 | AV6: 1.79 | AW6: 1.79 | AX6: 1.79 | AY6: 1.79 | AZ6: 1.79 | BA6: 1.79 | BB6: 1.79 | BC6: 1.79 | BD6: 1.79 | BE6: 1.79 | BF6: 1.79 | BG6: 1.79 | BH6: 1.79 | BI6: 1.79 | BJ6: 1.79 | BK6: 1.79 | BL6: 1.79 | BM6: 1.79 | BN6: 1.79 | BO6: 1.79 | BP6: 1.79 | BQ6: 1.79 | BR6: 1.79
A7: Africa Eastern and Southern | B7: AFE | C7: Official exchange rate (LCU per US$, period average) | D7: PA.NUS.FCRF
A8: Afghanistan | B8: AFG | C8: Official exchange rate (LCU per US$, period average) | D8: PA.NUS.FCRF | E8: 17.196561 | F8: 17.196561 | G8: 17.196561 | H8: 35.109645 | I8: 38.692262 | J8: 38.692262 | K8: 38.692262 | L8: 38.692262 | M8: 38.692262 | N8: 38.692262 | O8: 38.692262 | P8: 38.692262 | Q8: 38.692262 | R8: 38.692262 | S8: 38.378709 | T8: 34.929631 | U8: 34.929631 | V8: 34.929631 | W8: 34.929631 | X8: 33.846164 | Y8: 34.369458 | Z8: 38.561659 | AA8: 39.276429 | AB8: 39.276429 | AC8: 39.276429 | AD8: 39.276429 | AE8: 39.276429 | AF8: 39.276429 | AG8: 39.276429 | AH8: 39.276429 | AI8: 39.276429 | AJ8: 39.276429 | AK8: 39.276429 | AL8: 39.276429 | AM8: 38.818463 | AN8: 36.567145 | AO8: 47.5 | AP8: 47.5 | AQ8: 47.5 | AR8: 46.619531 | AS8: 47.357575 | AT8: 47.500015 | AU8: 47.263 | AV8: 48.762754 | AW8: 47.845312 | AX8: 49.494597 | AY8: 49.925331 | AZ8: 49.962018 | BA8: 50.249615 | BB8: 50.325 | BC8: 46.452461 | BD8: 46.747008 | BE8: 50.9214 | BF8: 55.3775 | BG8: 57.2475 | BH8: 61.143462 | BI8: 67.866086 | BJ8: 68.026904 | BK8: 72.083247 | BL8: 77.737949 | BM8: 76.813536
A9: Africa Western and Central | B9: AFW | C9: Official exchange rate (LCU per US$, period average) | D9: PA.NUS.FCRF
A10: Angola | B10: AGO | C10: Official exchange rate (LCU per US$, period average) | D10: PA.NUS.FCRF | E10: 2.8668443e-08 | F10: 2.873486e-08 | G10: 2.8678443e-08 | H10: 2.8752027e-08 | I10: 2.8819777e-08 | J10: 2.8778527e-08 | K10: 2.882386e-08 | L10: 2.884161e-08 | M10: 2.872761e-08 | N10: 2.8561193e-08 | O10: 2.862511e-08 | P10: 2.819112e-08 | Q10: 2.7052815e-08 | R10: 2.451462e-08 | S10: 2.5407601e-08 | T10: 2.5552181e-08 | U10: 2.9383623e-08 | V10: 2.9918e-08 | W10: 2.9918e-08 | X10: 2.9918e-08 | Y10: 2.9918e-08 | Z10: 2.9918e-08 | AA10: 2.9918e-08 | AB10: 2.9918e-08 | AC10: 2.9918e-08 | AD10: 2.9918e-08 | AE10: 2.9918e-08 | AF10: 2.9918e-08 | AG10: 2.9918e-08 | AH10: 2.9918e-08 | AI10: 2.9918e-08 | AJ10: 5.5098333e-08 | AK10: 2.5141667e-07 | AL10: 2.6601667e-06 | AM10: 5.9515e-05 | AN10: 0.0027502296 | AO10: 0.12802917 | AP10: 0.22904008 | AQ10: 0.39282352 | AR10: 2.7907062 | AS10: 10.040544 | AT10: 22.057862 | AU10: 43.530207 | AV10: 74.606301 | AW10: 83.541363 | AX10: 87.159142 | AY10: 80.368072 | AZ10: 76.706143 | BA10: 75.033354 | BB10: 79.328167 | BC10: 91.90572 | BD10: 93.93475 | BE10: 95.467955 | BF10: 96.518279 | BG10: 98.302417 | BH10: 120.0607 | BI10: 163.65643 | BJ10: 165.91595 | BK10: 252.85575 | BL10: 364.8258 | BM10: 578.25878 | BN10: 631.44196 | BO10: 460.56751 | BP10: 685.02024 | BQ10: 869.84619 | BR10: 911.99304
A11: Albania | B11: ALB | C11: Official exchange rate (LCU per US$, period average) | D11: PA.NUS.FCRF | AK11: 75.0325 | AL11: 102.0625 | AM11: 94.623333 | AN11: 92.6975 | AO11: 104.49892 | AP11: 148.93292 | AQ11: 150.63333 | AR11: 137.69058 | AS11: 143.70942 | AT11: 143.48483 | AU11: 140.15452 | AV11: 121.86325 | AW11: 102.78005 | AX11: 99.870254 | AY11: 98.103377 | AZ11: 90.427894 | BA11: 83.894604 | BB11: 94.97812 | BC11: 103.93667 | BD11: 100.89583 | BE11: 108.18417 | BF11: 105.66917 | BG11: 105.48 | BH11: 125.96167 | BI11: 124.1425 | BJ11: 119.1 | BK11: 107.98917 | BL11: 109.85083 | BM11: 108.65 | BN11: 103.52 | BO11: 113.04167 | BP11: 100.645 | BQ11: 93.123333 | BR11: 86.803333
A12: Andorra | B12: AND | C12: Official exchange rate (LCU per US$, period average) | D12: PA.NUS.FCRF | BN12: 0.84537656 | BO12: 0.95091553 | BP12: 0.92470962 | BQ12: 0.92436745 | BR12: 0.88714425
A13: Arab World | B13: ARB | C13: Official exchange rate (LCU per US$, period average) | D13: PA.NUS.FCRF
A14: United Arab Emirates | B14: ARE | C14: Official exchange rate (LCU per US$, period average) | D14: PA.NUS.FCRF | K14: 4.7619 | L14: 4.7619 | M14: 4.7619 | N14: 4.7619 | O14: 4.7619 | P14: 4.7479629 | Q14: 4.3859778 | R14: 3.9962713 | S14: 3.9590452 | T14: 3.961285 | U14: 3.9530725 | V14: 3.9032475 | W14: 3.8712108 | X14: 3.8156758 | Y14: 3.707365 | Z14: 3.671 | AA14: 3.671 | AB14: 3.671 | AC14: 3.671 | AD14: 3.671 | AE14: 3.671 | AF14: 3.671 | AG14: 3.671 | AH14: 3.671 | AI14: 3.671 | AJ14: 3.671 | AK14: 3.671 | AL14: 3.671 | AM14: 3.671 | AN14: 3.671 | AO14: 3.671 | AP14: 3.671125 | AQ14: 3.6725 | AR14: 3.6725 | AS14: 3.6725 | AT14: 3.6725 | AU14: 3.6725 | AV14: 3.6725 | AW14: 3.6725 | AX14: 3.6725 | AY14: 3.6725 | AZ14: 3.6725 | BA14: 3.6725 | BB14: 3.6725 | BC14: 3.6725 | BD14: 3.6725 | BE14: 3.6725 | BF14: 3.6725 | BG14: 3.6725 | BH14: 3.6725 | BI14: 3.6725 | BJ14: 3.6725 | BK14: 3.6725 | BL14: 3.6725 | BM14: 3.6725 | BN14: 3.6725 | BO14: 3.6725 | BP14: 3.6725 | BQ14: 3.6725 | BR14: 3.6725
A15: Argentina | B15: ARG | C15: Official exchange rate (LCU per US$, period average) | D15: PA.NUS.FCRF | H15: 1.3871667e-11 | I15: 1.4039167e-11 | J15: 1.6956667e-11 | K15: 2.0915e-11 | L15: 3.33425e-11 | M15: 3.5e-11 | N15: 3.5e-11 | O15: 3.7916667e-11 | P15: 4.5216667e-11 | Q15: 5e-11 | R15: 5e-11 | S15: 5e-11 | T15: 3.6575e-10 | U15: 1.3998333e-09 | V15: 4.0763333e-09 | W15: 7.9575e-09 | X15: 1.3169667e-08 | Y15: 1.8371583e-08 | Z15: 4.4026917e-08 | AA15: 2.5922533e-07 | AB15: 1.0529957e-06 | AC15: 6.7649117e-06 | AD15: 6.01809e-05 | AE15: 9.4303167e-05 | AF15: 0.00021442983 | AG15: 0.00087526042 | AH15: 0.042333961 | AI15: 0.48758908 | AJ15: 0.95355442 | AK15: 0.99064167 | AL15: 0.99894583 | AM15: 0.99900833 | AN15: 0.99975 | AO15: 0.9996625 | AP15: 0.9995 | AQ15: 0.9995 | AR15: 0.9995 | AS15: 0.9995 | AT15: 0.9995 | AU15: 3.0632567 | AV15: 2.9006292 | AW15: 2.9233008 | AX15: 2.9036575 | AY15: 3.0543133 | AZ15: 3.0956488 | BA15: 3.1441646 | BB15: 3.7101068 | BC15: 3.8962952 | BD15: 4.1101396 | BE15: 4.5369344 | BF15: 5.4593527 | BG15: 8.075276 | BH15: 9.2331855 | BI15: 14.758175 | BJ15: 16.562707 | BK15: 28.094992 | BL15: 48.147892 | BM15: 70.539167 | BN15: 94.990742 | BO15: 130.61655 | BP15: 296.25804 | BQ15: 914.69488 | BR15: 1240.8512
A16: Armenia | B16: ARM | C16: Official exchange rate (LCU per US$, period average) | D16: PA.NUS.FCRF | AL16: 9.105 | AM16: 288.65083 | AN16: 405.90833 | AO16: 414.0415 | AP16: 490.84679 | AQ16: 504.915 | AR16: 535.06183 | AS16: 539.52583 | AT16: 555.07826 | AU16: 573.35333 | AV16: 578.76295 | AW16: 533.45083 | AX16: 457.68694 | AY16: 416.04037 | AZ16: 342.07912 | BA16: 305.9694 | BB16: 363.28329 | BC16: 373.66047 | BD16: 372.50088 | BE16: 401.76398 | BF16: 409.62575 | BG16: 415.91979 | BH16: 477.91831 | BI16: 480.48815 | BJ16: 482.71639 | BK16: 482.98795 | BL16: 480.44513 | BM16: 489.00886 | BN16: 503.76967 | BO16: 435.66618 | BP16: 392.4763 | BQ16: 392.72955 | BR16: 387.01015
A17: American Samoa | B17: ASM | C17: Official exchange rate (LCU per US$, period average) | D17: PA.NUS.FCRF | E17: 1 | F17: 1 | G17: 1 | H17: 1 | I17: 1 | J17: 1 | K17: 1 | L17: 1 | M17: 1 | N17: 1 | O17: 1 | P17: 1 | Q17: 1 | R17: 1 | S17: 1 | T17: 1 | U17: 1 | V17: 1 | W17: 1 | X17: 1 | Y17: 1 | Z17: 1 | AA17: 1 | AB17: 1 | AC17: 1 | AD17: 1 | AE17: 1 | AF17: 1 | AG17: 1 | AH17: 1 | AI17: 1 | AJ17: 1 | AK17: 1 | AL17: 1 | AM17: 1 | AN17: 1 | AO17: 1 | AP17: 1 | AQ17: 1 | AR17: 1 | AS17: 1 | AT17: 1 | AU17: 1 | AV17: 1 | AW17: 1 | AX17: 1 | AY17: 1 | AZ17: 1 | BA17: 1 | BB17: 1 | BC17: 1 | BD17: 1 | BE17: 1 | BF17: 1 | BG17: 1 | BH17: 1 | BI17: 1 | BJ17: 1 | BK17: 1 | BL17: 1 | BM17: 1 | BN17: 1 | BO17: 1 | BP17: 1 | BQ17: 1 | BR17: 1
A18: Antigua and Barbuda | B18: ATG | C18: Official exchange rate (LCU per US$, period average) | D18: PA.NUS.FCRF | E18: 1.71429 | F18: 1.71429 | G18: 1.71429 | H18: 1.71429 | I18: 1.71429 | J18: 1.71429 | K18: 1.71429 | L18: 1.7619083 | M18: 2 | N18: 2 | O18: 2 | P18: 1.9748727 | Q18: 1.9212781 | R18: 1.9592192 | S18: 2.0532324 | T18: 2.1697958 | U18: 2.6146708 | V18: 2.7 | W18: 2.7 | X18: 2.7 | Y18: 2.7 | Z18: 2.7 | AA18: 2.7 | AB18: 2.7 | AC18: 2.7 | AD18: 2.7 | AE18: 2.7 | AF18: 2.7 | AG18: 2.7 | AH18: 2.7 | AI18: 2.7 | AJ18: 2.7 | AK18: 2.7 | AL18: 2.7 | AM18: 2.7 | AN18: 2.7 | AO18: 2.7 | AP18: 2.7 | AQ18: 2.7 | AR18: 2.7 | AS18: 2.7 | AT18: 2.7 | AU18: 2.7 | AV18: 2.7 | AW18: 2.7 | AX18: 2.7 | AY18: 2.7 | AZ18: 2.7 | BA18: 2.7 | BB18: 2.7 | BC18: 2.7 | BD18: 2.7 | BE18: 2.7 | BF18: 2.7 | BG18: 2.7 | BH18: 2.7 | BI18: 2.7 | BJ18: 2.7 | BK18: 2.7 | BL18: 2.7 | BM18: 2.7 | BN18: 2.7 | BO18: 2.7 | BP18: 2.7 | BQ18: 2.7 | BR18: 2.7
A19: Australia | B19: AUS | C19: Official exchange rate (LCU per US$, period average) | D19: PA.NUS.FCRF | E19: 0.892857 | F19: 0.892857 | G19: 0.892857 | H19: 0.892857 | I19: 0.892857 | J19: 0.892857 | K19: 0.892857 | L19: 0.892857 | M19: 0.892857 | N19: 0.892857 | O19: 0.892857 | P19: 0.88267026 | Q19: 0.83869781 | R19: 0.70411391 | S19: 0.69666587 | T19: 0.76387125 | U19: 0.81828408 | V19: 0.901825 | W19: 0.87365925 | X19: 0.89464092 | Y19: 0.87824433 | Z19: 0.87021458 | AA19: 0.98586283 | AB19: 1.110015 | AC19: 1.1395192 | AD19: 1.431895 | AE19: 1.4959742 | AF19: 1.42818 | AG19: 1.2799083 | AH19: 1.2645967 | AI19: 1.2810567 | AJ19: 1.2837558 | AK19: 1.3616483 | AL19: 1.47056 | AM19: 1.3677508 | AN19: 1.3490325 | AO19: 1.2778633 | AP19: 1.34738 | AQ19: 1.5918283 | AR19: 1.54995 | AS19: 1.7248267 | AT19: 1.9334425 | AU19: 1.8405625 | AV19: 1.5419142 | AW19: 1.3597525 | AX19: 1.3094733 | AY19: 1.3279734 | AZ19: 1.1950725 | BA19: 1.1921783 | BB19: 1.2821888 | BC19: 1.0901595 | BD19: 0.9694632 | BE19: 0.96580103 | BF19: 1.0358431 | BG19: 1.1093633 | BH19: 1.3310903 | BI19: 1.345214 | BJ19: 1.3047581 | BK19: 1.3384121 | BL19: 1.4385065 | BM19: 1.4530851 | BN19: 1.3312243 | BO19: 1.4416645 | BP19: 1.5051911 | BQ19: 1.515358 | BR19: 1.5519979
A20: Austria | B20: AUT | C20: Official exchange rate (LCU per US$, period average) | D20: PA.NUS.FCRF | E20: 26 | F20: 26 | G20: 26 | H20: 26 | I20: 26 | J20: 26 | K20: 26 | L20: 26 | M20: 26 | N20: 26 | O20: 26 | P20: 24.985584 | Q20: 23.115333 | R20: 19.58 | S20: 18.6925 | T20: 17.41675 | U20: 17.939667 | V20: 16.526917 | W20: 14.521667 | X20: 13.3675 | Y20: 12.938 | Z20: 15.926833 | AA20: 17.05925 | AB20: 17.963333 | AC20: 20.009083 | AD20: 20.6895 | AE20: 15.267133 | AF20: 12.6425 | AG20: 12.347667 | AH20: 13.230667 | AI20: 11.369833 | AJ20: 11.675917 | AK20: 10.989333 | AL20: 11.632183 | AM20: 11.421825 | AN20: 10.081496 | AO20: 10.586557 | AP20: 12.204244 | AQ20: 12.379065 | AR20: 0.93828307 | AS20: 1.0827051 | AT20: 1.1165331 | AU20: 1.057559 | AV20: 0.88404793 | AW20: 0.80392165 | AX20: 0.80380019 | AY20: 0.79643273 | AZ20: 0.7296724 | BA20: 0.67992268 | BB20: 0.7169577 | BC20: 0.75430899 | BD20: 0.7184139 | BE20: 0.77833812 | BF20: 0.75294512 | BG20: 0.7527282 | BH20: 0.90129642 | BI20: 0.90342144 | BJ20: 0.88520551 | BK20: 0.84677267 | BL20: 0.89327626 | BM20: 0.8755064 | BN20: 0.84549414 | BO20: 0.94962375 | BP20: 0.92483956 | BQ20: 0.92388955 | BR20: 0.88496896
